Workbook

Sheet FY Target Sheet
A1: Status | B1: Type | C1: Projects | D1: Apr-26 Units Target | E1: Apr-26 Units Actual | F1: Apr-26 Rate Target | G1: Apr-26 Rate Actual | H1: Apr-26 Area Target | I1: Apr-26 Area Actual | J1: Apr-26 Sales Value Target | K1: Apr-26 Sales Value Actual | L1: Apr-26 Collection Target | M1: Apr-26 Collection Actual | N1: Apr-26 Construction Target | O1: Apr-26 Construction Actual | P1: May-26 Units Target | Q1: May-26 Units Actual | R1: May-26 Rate Target | S1: May-26 Rate Actual | T1: May-26 Area Target | U1: May-26 Area Actual | V1: May-26 Sales Value Target | W1: May-26 Sales Value Actual | X1: May-26 Collection Target | Y1: May-26 Collection Actual | Z1: May-26 Construction Target | AA1: May-26 Construction Actual | AB1: Jun-26 Units Target | AC1: Jun-26 Units Actual | AD1: Jun-26 Rate Target | AE1: Jun-26 Rate Actual | AF1: Jun-26 Area Target | AG1: Jun-26 Area Actual | AH1: Jun-26 Sales Value Target | AI1: Jun-26 Sales Value Actual | AJ1: Jun-26 Collection Target | AK1: Jun-26 Collection Actual | AL1: Jun-26 Construction Target | AM1: Jun-26 Construction Actual | AN1: Jul-26 Units Target | AO1: Jul-26 Rate Target | AP1: Jul-26 Area Target | AQ1: Jul-26 Sales Value Target | AR1: Jul-26 Collection Target | AS1: Jul-26 Construction Target | AT1: Aug-26 Units Target | AU1: Aug-26 Rate Target | AV1: Aug-26 Area Target | AW1: Aug-26 Sales Value Target | AX1: Aug-26 Collection Target | AY1: Aug-26 Construction Target | AZ1: Sep-26 Units Target | BA1: Sep-26 Rate Target | BB1: Sep-26 Area Target | BC1: Sep-26 Sales Value Target | BD1: Sep-26 Collection Target | BE1: Sep-26 Construction Target | BF1: Oct-26 Units Target | BG1: Oct-26 Rate Target | BH1: Oct-26 Area Target | BI1: Oct-26 Sales Value Target | BJ1: Oct-26 Collection Target | BK1: Oct-26 Construction Target | BL1: Nov-26 Units Target | BM1: Nov-26 Rate Target | BN1: Nov-26 Area Target | BO1: Nov-26 Sales Value Target | BP1: Nov-26 Collection Target | BQ1: Nov-26 Construction Target | BR1: Dec-26 Units Target | BS1: Dec-26 Rate Target | BT1: Dec-26 Area Target | BU1: Dec-26 Sales Value Target | BV1: Dec-26 Collection Target | BW1: Dec-26 Construction Target | BX1: Jan-27 Units Target | BY1: Jan-27 Rate Target | BZ1: Jan-27 Area Target | CA1: Jan-27 Sales Value Target | CB1: Jan-27 Collection Target | CC1: Jan-27 Construction Target | CD1: Feb-27 Units Target | CE1: Feb-27 Rate Target | CF1: Feb-27 Area Target | CG1: Feb-27 Sales Value Target | CH1: Feb-27 Collection Target | CI1: Feb-27 Construction Target | CJ1: Mar-27 Units Target | CK1: Mar-27 Rate Target | CL1: Mar-27 Area Target | CM1: Mar-27 Sales Value Target | CN1: Mar-27 Collection Target | CO1: Mar-27 Construction Target
A2: On Going | B2: RESIDENTIAL | C2: NYATI EMERALD I | D2: 5 | E2: =COUNTIF('Booking Apr'!B:B,'FY Target Sheet'!C2)-COUNTIF('Cancel Apr'!A:A,'FY Target Sheet'!C2) -> -1 | F2: 8249.1106 | G2: =(K2/I2) -> 8641.7037 | H2: 6915 | I2: =SUMIF('Booking Apr'!B:B,'FY Target Sheet'!C2,'Booking Apr'!K:K)-SUMIF('Cancel Apr'!A:A,'FY Target Sheet'!C2,'Cancel Apr'!F:F) -> -648 | J2: 57042600 | K2: =SUMIF('Booking Apr'!B:B,C2,'Booking Apr'!L:L)-SUMIF('Cancel Apr'!A:A,'FY Target Sheet'!C2,'Cancel Apr'!G:G) -> -5599824 | L2: 86722920 | M2: =SUMIF('Coll Apr'!A:A,C2,'Coll Apr'!J:J)*100000 -> 57110000 | N2: ='Construction Budget'!G5*10000000 -> 82975269 | O2: ='Construction Budget'!G6*10000000 -> 28323535 | P2: 3 | Q2: =COUNTIF('Booking May'!B:B,'FY Target Sheet'!C2)-COUNTIF('Cancel May'!A:A,'FY Target Sheet'!C2) -> 1 | R2: 8274.327 | S2: =(W2/U2) -> 8450 | T2: 4569 | U2: =SUMIF('Booking May'!B:B,'FY Target Sheet'!C2,'Booking May'!K:K)-SUMIF('Cancel May'!A:A,'FY Target Sheet'!C2,'Cancel May'!F:F) -> 1173 | V2: 37805400 | W2: =SUMIF('Booking May'!B:B,C2,'Booking May'!L:L)-SUMIF('Cancel May'!A:A,'FY Target Sheet'!C2,'Cancel May'!G:G) -> 9911850 | X2: 87309515 | Y2: =SUMIF('Coll May'!A:A,C2,'Coll May'!J:J)*100000 -> 38667000 | Z2: ='Construction Budget'!H5*10000000 -> 85868030 | AA2: ='Construction Budget'!H6*10000000 -> 40911773 | AB2: 5 | AC2: =COUNTIF('Booking Jun'!B:B,C2)-COUNTIF('Cancel Jun'!A:A,C2) -> 2 | AD2: 8268.4677 | AE2: =(AI2/AG2) -> 9516.3408 | AF2: 7440 | AG2: =SUMIF('Booking Jun'!B:B,'FY Target Sheet'!C2,'Booking Jun'!K:K)-SUMIF('Cancel Jun'!A:A,'FY Target Sheet'!C2,'Cancel Jun'!F:F) -> 5818 | AH2: 61517400 | AI2: =SUMIF('Booking Jun'!B:B,C2,'Booking Jun'!L:L)-SUMIF('Cancel Jun'!A:A,'FY Target Sheet'!C2,'Cancel Jun'!G:G) -> 55366071 | AJ2: 77332449 | AK2: =SUMIF('Coll Jun'!A:A,C2,'Coll Jun'!J:J)*100000 -> 27677000 | AL2: ='Construction Budget'!I5*10000000 -> 93591907 | AM2: ='Construction Budget'!I6*10000000 -> 81823547 | AN2: 5 | AO2: 8400 | AP2: 8490 | AQ2: 71316000 | AR2: 83974119 | AS2: ='Construction Budget'!J5*10000000 -> 1.2127371e+08 | AT2: 5 | AU2: 8400 | AV2: 8490 | AW2: 71316000 | AX2: 91105719 | AY2: ='Construction Budget'!K5*10000000 -> 1.2061047e+08 | AZ2: 7 | BA2: 8389.6752 | BB2: 11361 | BC2: 95315100 | BD2: 1.0300307e+08 | BE2: ='Construction Budget'!L5*10000000 -> 1.2921313e+08 | BF2: 7 | BG2: 8810.4616 | BH2: 12847 | BI2: 113188000 | BJ2: 1.1952348e+08 | BK2: ='Construction Budget'!M5*10000000 -> 1.2210436e+08 | BL2: 7 | BM2: 8810.4616 | BN2: 12847 | BO2: 113188000 | BP2: 1.3008375e+08 | BQ2: ='Construction Budget'!N5*10000000 -> 1.3026793e+08 | BR2: 11 | BS2: 8891.5168 | BT2: 20075 | BU2: 178497200 | BV2: 1.9092317e+08 | BW2: ='Construction Budget'!O5*10000000 -> 1.2130212e+08 | BX2: 0 | BY2: 0 | BZ2: 0 | CA2: 0 | CB2: 2.2555312e+08 | CC2: ='Construction Budget'!P5*10000000 -> 1.0811711e+08 | CD2: 0 | CE2: 0 | CF2: 0 | CG2: 0 | CH2: 2.5078737e+08 | CI2: ='Construction Budget'!Q5*10000000 -> 1.2130212e+08 | CJ2: 0 | CK2: 0 | CL2: 0 | CM2: 0 | CN2: 2.9458382e+08 | CO2: ='Construction Budget'!R5*10000000 -> 1.1339112e+08
A3: On Going | B3: RESIDENTIAL | C3: NYATI EMERALD II | E3: =COUNTIF('Booking Apr'!B:B,'FY Target Sheet'!C3)-COUNTIF('Cancel Apr'!A:A,'FY Target Sheet'!C3) -> 0 | I3: =SUMIF('Booking Apr'!B:B,'FY Target Sheet'!C3,'Booking Apr'!K:K)-SUMIF('Cancel Apr'!A:A,'FY Target Sheet'!C3,'Cancel Apr'!F:F) -> 0 | K3: =SUMIF('Booking Apr'!B:B,C3,'Booking Apr'!L:L)-SUMIF('Cancel Apr'!A:A,'FY Target Sheet'!C3,'Cancel Apr'!G:G) -> 0 | L3: 4185500 | M3: =SUMIF('Coll Apr'!A:A,C3,'Coll Apr'!J:J)*100000 -> 6546000 | N3: ='Construction Budget'!G8*10000000 -> 15625200 | O3: ='Construction Budget'!G9*10000000 -> 2412749.9 | Q3: =COUNTIF('Booking May'!B:B,'FY Target Sheet'!C3)-COUNTIF('Cancel May'!A:A,'FY Target Sheet'!C3) -> 0 | U3: =SUMIF('Booking May'!B:B,'FY Target Sheet'!C3,'Booking May'!K:K)-SUMIF('Cancel May'!A:A,'FY Target Sheet'!C3,'Cancel May'!F:F) -> 0 | W3: =SUMIF('Booking May'!B:B,C3,'Booking May'!L:L)-SUMIF('Cancel May'!A:A,'FY Target Sheet'!C3,'Cancel May'!G:G) -> 0 | X3: 18985373 | Y3: =SUMIF('Coll May'!A:A,C3,'Coll May'!J:J)*100000 -> 19258000 | Z3: ='Construction Budget'!H8*10000000 -> 24271144 | AA3: ='Construction Budget'!H9*10000000 -> 6273149.7 | AC3: =COUNTIF('Booking Jun'!B:B,C3)-COUNTIF('Cancel Jun'!A:A,C3) -> 0 | AG3: =SUMIF('Booking Jun'!B:B,'FY Target Sheet'!C3,'Booking Jun'!K:K)-SUMIF('Cancel Jun'!A:A,'FY Target Sheet'!C3,'Cancel Jun'!F:F) -> 0 | AI3: =SUMIF('Booking Jun'!B:B,C3,'Booking Jun'!L:L)-SUMIF('Cancel Jun'!A:A,'FY Target Sheet'!C3,'Cancel Jun'!G:G) -> 0 | AJ3: 16040411 | AK3: =SUMIF('Coll Jun'!A:A,C3,'Coll Jun'!J:J)*100000 -> 18610000 | AL3: ='Construction Budget'!I8*10000000 -> 22916960 | AM3: ='Construction Budget'!I8*10000000 -> 22916960 | AR3: 16040411 | AS3: ='Construction Budget'!J8*10000000 -> 21875280 | AX3: 16040411 | AY3: ='Construction Budget'!K8*10000000 -> 23021128 | BD3: 16040411 | BE3: ='Construction Budget'!L8*10000000 -> 18750240 | BJ3: 16040411 | BK3: ='Construction Budget'!M8*10000000 -> 21666944 | BP3: 16040411 | BQ3: ='Construction Budget'!N8*10000000 -> 17708560 | BV3: 16040411 | BW3: ='Construction Budget'!O8*10000000 -> 16041872 | CB3: 16040411 | CC3: ='Construction Budget'!P8*10000000 -> 19791920 | CH3: 16040411 | CI3: ='Construction Budget'!Q8*10000000 -> 21979448 | CN3: 16040411 | CO3: ='Construction Budget'!R8*10000000 -> 26354504
A4: On Going | B4: RESIDENTIAL | C4: NYATI EMERALD III | D4: 19 | E4: =COUNTIF('Booking Apr'!B:B,'FY Target Sheet'!C4)-COUNTIF('Cancel Apr'!A:A,'FY Target Sheet'!C4) -> 1 | F4: 8388.7221 | G4: =(K4/I4) -> 8803.5834 | H4: 27372 | I4: =SUMIF('Booking Apr'!B:B,'FY Target Sheet'!C4,'Booking Apr'!K:K)-SUMIF('Cancel Apr'!A:A,'FY Target Sheet'!C4,'Cancel Apr'!F:F) -> 2223 | J4: 229616100 | K4: =SUMIF('Booking Apr'!B:B,C4,'Booking Apr'!L:L)-SUMIF('Cancel Apr'!A:A,'FY Target Sheet'!C4,'Cancel Apr'!G:G) -> 19570366 | L4: 1.074241e+08 | M4: =SUMIF('Coll Apr'!A:A,C4,'Coll Apr'!J:J)*100000 -> 117679000 | N4: ='Construction Budget'!G11*10000000 -> 55858996 | O4: ='Construction Budget'!G12*10000000 -> 24366196 | P4: 17 | Q4: =COUNTIF('Booking May'!B:B,'FY Target Sheet'!C4)-COUNTIF('Cancel May'!A:A,'FY Target Sheet'!C4) -> 4 | R4: 8287.2958 | S4: =(W4/U4) -> 8356.5143 | T4: 24484 | U4: =SUMIF('Booking May'!B:B,'FY Target Sheet'!C4,'Booking May'!K:K)-SUMIF('Cancel May'!A:A,'FY Target Sheet'!C4,'Cancel May'!F:F) -> 5217 | V4: 202906150 | W4: =SUMIF('Booking May'!B:B,C4,'Booking May'!L:L)-SUMIF('Cancel May'!A:A,'FY Target Sheet'!C4,'Cancel May'!G:G) -> 43595935 | X4: 1.0779113e+08 | Y4: =SUMIF('Coll May'!A:A,C4,'Coll May'!J:J)*100000 -> 75792000 | Z4: ='Construction Budget'!H11*10000000 -> 60158222 | AA4: ='Construction Budget'!H12*10000000 -> 19303090 | AB4: 15 | AC4: =COUNTIF('Booking Jun'!B:B,C4)-COUNTIF('Cancel Jun'!A:A,C4) -> 5 | AD4: 8205.8815 | AE4: =(AI4/AG4) -> 8078.1286 | AF4: 21270 | AG4: =SUMIF('Booking Jun'!B:B,'FY Target Sheet'!C4,'Booking Jun'!K:K)-SUMIF('Cancel Jun'!A:A,'FY Target Sheet'!C4,'Cancel Jun'!F:F) -> 6390 | AH4: 174539100 | AI4: =SUMIF('Booking Jun'!B:B,C4,'Booking Jun'!L:L)-SUMIF('Cancel Jun'!A:A,'FY Target Sheet'!C4,'Cancel Jun'!G:G) -> 51619242 | AJ4: 101465380 | AK4: =SUMIF('Coll Jun'!A:A,C4,'Coll Jun'!J:J)*100000 -> 71062000 | AL4: ='Construction Budget'!I11*10000000 -> 81148015 | AM4: ='Construction Budget'!I12*10000000 -> 50631056 | AN4: 13 | AO4: 8312.8091 | AP4: 18924 | AQ4: 157311600 | AR4: 118057915 | AS4: ='Construction Budget'!J11*10000000 -> 66208722 | AT4: 13 | AU4: 8305.3726 | AV4: 18399 | AW4: 152810550 | AX4: 1.2208322e+08 | AY4: ='Construction Budget'!K11*10000000 -> 88355540 | AZ4: 10 | BA4: 8309.1432 | BB4: 14355 | BC4: 119277750 | BD4: 125542325 | BE4: ='Construction Budget'!L11*10000000 -> 88960644 | BF4: 13 | BG4: 8405.3726 | BH4: 18399 | BI4: 154650450 | BJ4: 130511780 | BK4: ='Construction Budget'!M11*10000000 -> 94609008 | BL4: 15 | BM4: 8399.1106 | BN4: 20745 | BO4: 174239550 | BP4: 1.546888e+08 | BQ4: ='Construction Budget'!N11*10000000 -> 91003889 | BR4: 12 | BS4: 8400.8353 | BT4: 16701 | BU4: 140302350 | BV4: 1.6129693e+08 | BW4: ='Construction Budget'!O11*10000000 -> 70125891 | BX4: 21 | BY4: 8515.8714 | BZ4: 30933 | CA4: 263421450 | CB4: 1.9053193e+08 | CC4: ='Construction Budget'!P11*10000000 -> 52994112 | CD4: 20 | CE4: 8504.2203 | CF4: 28185 | CG4: 239691450 | CH4: 2.0853668e+08 | CI4: ='Construction Budget'!Q11*10000000 -> 96758078 | CJ4: 23 | CK4: 8519.2476 | CL4: 34329 | CM4: 292457250 | CN4: 2.5954999e+08 | CO4: ='Construction Budget'!R11*10000000 -> 53830405
A5: Near Completion | B5: RESIDENTIAL | C5: NYATI EQUINOX I | D5: 10 | E5: =COUNTIF('Booking Apr'!B:B,'FY Target Sheet'!C5)-COUNTIF('Cancel Apr'!A:A,'FY Target Sheet'!C5) -> 7 | F5: 8057.5034 | G5: =(K5/I5) -> 8428.2704 | H5: 14067 | I5: =SUMIF('Booking Apr'!B:B,'FY Target Sheet'!C5,'Booking Apr'!K:K)-SUMIF('Cancel Apr'!A:A,'FY Target Sheet'!C5,'Cancel Apr'!F:F) -> 11992 | J5: 113344900 | K5: =SUMIF('Booking Apr'!B:B,C5,'Booking Apr'!L:L)-SUMIF('Cancel Apr'!A:A,'FY Target Sheet'!C5,'Cancel Apr'!G:G) -> 101071819 | L5: 1.5768781e+08 | M5: =SUMIF('Coll Apr'!A:A,C5,'Coll Apr'!J:J)*100000 -> 106054000 | N5: ='Construction Budget'!G14*10000000 -> 56000717 | O5: ='Construction Budget'!G15*10000000 -> 37146927 | P5: 13 | Q5: =COUNTIF('Booking May'!B:B,'FY Target Sheet'!C5)-COUNTIF('Cancel May'!A:A,'FY Target Sheet'!C5) -> 6 | R5: 8091.6436 | S5: =(W5/U5) -> 8544.5626 | T5: 19877 | U5: =SUMIF('Booking May'!B:B,'FY Target Sheet'!C5,'Booking May'!K:K)-SUMIF('Cancel May'!A:A,'FY Target Sheet'!C5,'Cancel May'!F:F) -> 6363 | V5: 160837600 | W5: =SUMIF('Booking May'!B:B,C5,'Booking May'!L:L)-SUMIF('Cancel May'!A:A,'FY Target Sheet'!C5,'Cancel May'!G:G) -> 54369052 | X5: 1.76304e+08 | Y5: =SUMIF('Coll May'!A:A,C5,'Coll May'!J:J)*100000 -> 1.29128e+08 | Z5: ='Construction Budget'!H14*10000000 -> 66500851 | AA5: ='Construction Budget'!H15*10000000 -> 72783816 | AB5: 14 | AC5: =COUNTIF('Booking Jun'!B:B,C5)-COUNTIF('Cancel Jun'!A:A,C5) -> 12 | AD5: 8070.7491 | AE5: =(AI5/AG5) -> 8288.3515 | AF5: 20437 | AG5: =SUMIF('Booking Jun'!B:B,'FY Target Sheet'!C5,'Booking Jun'!K:K)-SUMIF('Cancel Jun'!A:A,'FY Target Sheet'!C5,'Cancel Jun'!F:F) -> 14307 | AH5: 164941900 | AI5: =SUMIF('Booking Jun'!B:B,C5,'Booking Jun'!L:L)-SUMIF('Cancel Jun'!A:A,'FY Target Sheet'!C5,'Cancel Jun'!G:G) -> 118581445 | AJ5: 1.4831923e+08 | AK5: =SUMIF('Coll Jun'!A:A,C5,'Coll Jun'!J:J)*100000 -> 1.06736e+08 | AL5: ='Construction Budget'!I14*10000000 -> 80501030 | AM5: ='Construction Budget'!I15*10000000 -> 95132373 | AN5: 22 | AO5: 8991.4062 | AP5: 29754 | AQ5: 267530300 | AR5: 1.7286602e+08 | AS5: ='Construction Budget'!J14*10000000 -> 84001075 | AT5: 20 | AU5: 8846.3967 | AV5: 25629 | AW5: 226724300 | AX5: 1.9511989e+08 | AY5: ='Construction Budget'!K14*10000000 -> 91001165 | AZ5: 12 | BA5: 8617.7435 | BB5: 15183 | BC5: 130843200 | BD5: 2.1756887e+08 | BE5: ='Construction Budget'!L14*10000000 -> 77000986 | BF5: 10 | BG5: 8269.1194 | BH5: 14922 | BI5: 123391800 | BJ5: 2.1756806e+08 | BK5: ='Construction Budget'!M14*10000000 -> 87501120 | BL5: 15 | BM5: 8297.5304 | BN5: 23567 | BO5: 195547900 | BP5: 2.5452585e+08 | BQ5: ='Construction Budget'!N14*10000000 -> 84001075 | BR5: 16 | BS5: 8253.7164 | BT5: 22401 | BU5: 184891500 | BV5: 3.2237156e+08 | BW5: ='Construction Budget'!O14*10000000 -> 73500941 | BX5: 16 | BY5: 8353.7164 | BZ5: 22401 | CA5: 187131600 | CB5: 351678704 | CC5: ='Construction Budget'!P14*10000000 -> 0 | CD5: 17 | CE5: 8314.8795 | CF5: 10827 | CG5: 90025200 | CH5: 3.6298267e+08 | CI5: ='Construction Budget'!Q14*10000000 -> 0 | CJ5: 16 | CK5: 8365.7361 | CL5: 23535 | CM5: 196887600 | CN5: 239880364 | CO5: ='Construction Budget'!R14*10000000 -> 0
A6: On Going | B6: RESIDENTIAL | C6: NYATI EQUINOX II | D6: 5 | E6: =COUNTIF('Booking Apr'!B:B,'FY Target Sheet'!C6)-COUNTIF('Cancel Apr'!A:A,'FY Target Sheet'!C6) -> 2 | F6: 6629.1161 | G6: =(K6/I6) -> 6754.142 | H6: 6268 | I6: =SUMIF('Booking Apr'!B:B,'FY Target Sheet'!C6,'Booking Apr'!K:K)-SUMIF('Cancel Apr'!A:A,'FY Target Sheet'!C6,'Cancel Apr'!F:F) -> 1641 | J6: 41551300 | K6: =SUMIF('Booking Apr'!B:B,C6,'Booking Apr'!L:L)-SUMIF('Cancel Apr'!A:A,'FY Target Sheet'!C6,'Cancel Apr'!G:G) -> 11083547 | L6: 18423402 | M6: =SUMIF('Coll Apr'!A:A,C6,'Coll Apr'!J:J)*100000 -> 18198000 | N6: ='Construction Budget'!G17*10000000 -> 19343368 | O6: ='Construction Budget'!G18*10000000 -> 6718658.4 | P6: 6 | Q6: =COUNTIF('Booking May'!B:B,'FY Target Sheet'!C6)-COUNTIF('Cancel May'!A:A,'FY Target Sheet'!C6) -> 1 | R6: 6624.3366 | S6: =(W6/U6) -> 6907 | T6: 7499 | U6: =SUMIF('Booking May'!B:B,'FY Target Sheet'!C6,'Booking May'!K:K)-SUMIF('Cancel May'!A:A,'FY Target Sheet'!C6,'Cancel May'!F:F) -> 733 | V6: 49675900 | W6: =SUMIF('Booking May'!B:B,C6,'Booking May'!L:L)-SUMIF('Cancel May'!A:A,'FY Target Sheet'!C6,'Cancel May'!G:G) -> 5062831 | X6: 22984762 | Y6: =SUMIF('Coll May'!A:A,C6,'Coll May'!J:J)*100000 -> 9039000 | Z6: ='Construction Budget'!H17*10000000 -> 14646424 | AA6: ='Construction Budget'!H18*10000000 -> 11757652 | AB6: 7 | AC6: =COUNTIF('Booking Jun'!B:B,C6)-COUNTIF('Cancel Jun'!A:A,C6) -> 2 | AD6: 6644.3553 | AE6: =(AI6/AG6) -> 6559.6726 | AF6: 8229 | AG6: =SUMIF('Booking Jun'!B:B,'FY Target Sheet'!C6,'Booking Jun'!K:K)-SUMIF('Cancel Jun'!A:A,'FY Target Sheet'!C6,'Cancel Jun'!F:F) -> 1466 | AH6: 54676400 | AI6: =SUMIF('Booking Jun'!B:B,C6,'Booking Jun'!L:L)-SUMIF('Cancel Jun'!A:A,'FY Target Sheet'!C6,'Cancel Jun'!G:G) -> 9616480 | AJ6: 22339378 | AK6: =SUMIF('Coll Jun'!A:A,C6,'Coll Jun'!J:J)*100000 -> 13207000 | AL6: ='Construction Budget'!I17*10000000 -> 9540521.4 | AM6: ='Construction Budget'!I18*10000000 -> 16796846 | AN6: 9 | AO6: 6708.1879 | AP6: 10998 | AQ6: 73776650 | AR6: 28762030 | AS6: ='Construction Budget'!J17*10000000 -> 34801443 | AT6: 9 | AU6: 6708.1879 | AV6: 10998 | AW6: 73776650 | AX6: 36945329 | AY6: ='Construction Budget'!K17*10000000 -> 35715187 | AZ6: 7 | BA6: 6695.1948 | BB6: 9037 | BC6: 60504475 | BD6: 45503801 | BE6: ='Construction Budget'!L17*10000000 -> 36746355 | BF6: 8 | BG6: 6787.3707 | BH6: 9767 | BI6: 66292250 | BJ6: 53024445 | BK6: ='Construction Budget'!M17*10000000 -> 39796670 | BL6: 11 | BM6: 6776.5127 | BN6: 13767 | BO6: 93292250 | BP6: 65975589 | BQ6: ='Construction Budget'!N17*10000000 -> 36560997 | BR6: 12 | BS6: 7235.7868 | BT6: 14571 | BU6: 105432650 | BV6: 82486549 | BW6: ='Construction Budget'!O17*10000000 -> 39768326 | BX6: 13 | BY6: 7269.1273 | BZ6: 15802 | CA6: 114866750 | CB6: 1.0765911e+08 | CC6: ='Construction Budget'!P17*10000000 -> 46787648 | CD6: 14 | CE6: 7229.7347 | CF6: 17340 | CG6: 125363600 | CH6: 1.2553169e+08 | CI6: ='Construction Budget'!Q17*10000000 -> 57529433 | CJ6: 14 | CK6: 7229.7347 | CL6: 17340 | CM6: 125363600 | CN6: 1.1053288e+08 | CO6: ='Construction Budget'!R17*10000000 -> 28768749
A7: Completed | B7: RESIDENTIAL | C7: NYATI ERA II | D7: 3 | E7: =COUNTIF('Booking Apr'!B:B,'FY Target Sheet'!C7)-COUNTIF('Cancel Apr'!A:A,'FY Target Sheet'!C7) -> -1 | F7: 9318.7588 | G7: =(K7/I7) -> 3145.6446 | H7: 1418 | I7: =SUMIF('Booking Apr'!B:B,'FY Target Sheet'!C7,'Booking Apr'!K:K)-SUMIF('Cancel Apr'!A:A,'FY Target Sheet'!C7,'Cancel Apr'!F:F) -> -574 | J7: 13214000 | K7: =SUMIF('Booking Apr'!B:B,C7,'Booking Apr'!L:L)-SUMIF('Cancel Apr'!A:A,'FY Target Sheet'!C7,'Cancel Apr'!G:G) -> -1805600 | L7: 36161600 | M7: =SUMIF('Coll Apr'!A:A,C7,'Coll Apr'!J:J)*100000 -> 48702000 | P7: 3 | Q7: =COUNTIF('Booking May'!B:B,'FY Target Sheet'!C7)-COUNTIF('Cancel May'!A:A,'FY Target Sheet'!C7) -> 1 | R7: 9318.7588 | S7: =(W7/U7) -> 11682.242 | T7: 1418 | U7: =SUMIF('Booking May'!B:B,'FY Target Sheet'!C7,'Booking May'!K:K)-SUMIF('Cancel May'!A:A,'FY Target Sheet'!C7,'Cancel May'!F:F) -> 248 | V7: 13214000 | W7: =SUMIF('Booking May'!B:B,C7,'Booking May'!L:L)-SUMIF('Cancel May'!A:A,'FY Target Sheet'!C7,'Cancel May'!G:G) -> 2897196 | X7: 37247500 | Y7: =SUMIF('Coll May'!A:A,C7,'Coll May'!J:J)*100000 -> 56647000 | AB7: 3 | AC7: =COUNTIF('Booking Jun'!B:B,C7)-COUNTIF('Cancel Jun'!A:A,C7) -> 2 | AD7: 9318.7588 | AE7: =(AI7/AG7) -> 8814.739 | AF7: 1418 | AG7: =SUMIF('Booking Jun'!B:B,'FY Target Sheet'!C7,'Booking Jun'!K:K)-SUMIF('Cancel Jun'!A:A,'FY Target Sheet'!C7,'Cancel Jun'!F:F) -> 977 | AH7: 13214000 | AI7: =SUMIF('Booking Jun'!B:B,C7,'Booking Jun'!L:L)-SUMIF('Cancel Jun'!A:A,'FY Target Sheet'!C7,'Cancel Jun'!G:G) -> 8612000 | AJ7: 40551000 | AK7: =SUMIF('Coll Jun'!A:A,C7,'Coll Jun'!J:J)*100000 -> 37301000 | AN7: 3 | AO7: 9318.7588 | AP7: 1418 | AQ7: 13214000 | AR7: 36859167 | AT7: 5 | AU7: 9384.1904 | AV7: 2353 | AW7: 22081000 | AX7: 38189217 | AZ7: 5 | BA7: 9384.1904 | BB7: 2353 | BC7: 22081000 | BD7: 41292667 | BF7: 4 | BG7: 9237.7696 | BH7: 1901 | BI7: 17561000 | BJ7: 19186250 | BL7: 4 | BM7: 9237.7696 | BN7: 1901 | BO7: 17561000 | BP7: 19821000 | BR7: 4 | BS7: 9237.7696 | BT7: 1901 | BU7: 17561000 | BV7: 18691000 | BX7: 2 | BY7: 9000 | BZ7: 966 | CA7: 8694000 | CB7: 16230950 | CD7: 2 | CE7: 9000 | CF7: 966 | CG7: 8694000 | CH7: 14866300 | CJ7: 2 | CK7: 9000 | CL7: 966 | CM7: 8694000 | CN7: 10910750
A8: Near Completion | B8: RESIDENTIAL | C8: NYATI ERA III | E8: =COUNTIF('Booking Apr'!B:B,'FY Target Sheet'!C8)-COUNTIF('Cancel Apr'!A:A,'FY Target Sheet'!C8) -> 0 | I8: =SUMIF('Booking Apr'!B:B,'FY Target Sheet'!C8,'Booking Apr'!K:K)-SUMIF('Cancel Apr'!A:A,'FY Target Sheet'!C8,'Cancel Apr'!F:F) -> 0 | K8: =SUMIF('Booking Apr'!B:B,C8,'Booking Apr'!L:L)-SUMIF('Cancel Apr'!A:A,'FY Target Sheet'!C8,'Cancel Apr'!G:G) -> 0 | L8: 46511600 | M8: =SUMIF('Coll Apr'!A:A,C8,'Coll Apr'!J:J)*100000 -> 43478000 | N8: ='Construction Budget'!G20*10000000 -> 22000282 | O8: ='Construction Budget'!G21*10000000 -> 30152850 | Q8: =COUNTIF('Booking May'!B:B,'FY Target Sheet'!C8)-COUNTIF('Cancel May'!A:A,'FY Target Sheet'!C8) -> 0 | U8: =SUMIF('Booking May'!B:B,'FY Target Sheet'!C8,'Booking May'!K:K)-SUMIF('Cancel May'!A:A,'FY Target Sheet'!C8,'Cancel May'!F:F) -> 0 | W8: =SUMIF('Booking May'!B:B,C8,'Booking May'!L:L)-SUMIF('Cancel May'!A:A,'FY Target Sheet'!C8,'Cancel May'!G:G) -> 0 | X8: 35272800 | Y8: =SUMIF('Coll May'!A:A,C8,'Coll May'!J:J)*100000 -> 61047000 | Z8: ='Construction Budget'!H20*10000000 -> 30000384 | AA8: ='Construction Budget'!H21*10000000 -> 25144412 | AC8: =COUNTIF('Booking Jun'!B:B,C8)-COUNTIF('Cancel Jun'!A:A,C8) -> 0 | AE8: =(AI8/AG8) -> #DIV/0! | AG8: =SUMIF('Booking Jun'!B:B,'FY Target Sheet'!C8,'Booking Jun'!K:K)-SUMIF('Cancel Jun'!A:A,'FY Target Sheet'!C8,'Cancel Jun'!F:F) -> 0 | AI8: =SUMIF('Booking Jun'!B:B,C8,'Booking Jun'!L:L)-SUMIF('Cancel Jun'!A:A,'FY Target Sheet'!C8,'Cancel Jun'!G:G) -> 0 | AJ8: 21446000 | AK8: =SUMIF('Coll Jun'!A:A,C8,'Coll Jun'!J:J)*100000 -> 40389000 | AL8: ='Construction Budget'!I20*10000000 -> 36000461 | AM8: ='Construction Budget'!I21*10000000 -> 43951614 | AR8: 23590600 | AS8: ='Construction Budget'!J20*10000000 -> 34000435 | AX8: 25735200 | AY8: ='Construction Budget'!K20*10000000 -> 46000589 | BD8: 64338000 | BE8: ='Construction Budget'!L20*10000000 -> 32000410 | BJ8: 1.351098e+08 | BK8: ='Construction Budget'!M20*10000000 -> 0 | BP8: 0 | BQ8: ='Construction Budget'!N20*10000000 -> 0 | BV8: 0 | BW8: ='Construction Budget'!O20*10000000 -> 0 | CB8: 0 | CC8: ='Construction Budget'!P20*10000000 -> 0 | CH8: 0 | CI8: ='Construction Budget'!Q20*10000000 -> 0 | CN8: 0 | CO8: ='Construction Budget'!R20*10000000 -> 0
A9: On Going | B9: RESIDENTIAL | C9: NYATI ERA IV | D9: 4 | E9: =COUNTIF('Booking Apr'!B:B,'FY Target Sheet'!C9)-COUNTIF('Cancel Apr'!A:A,'FY Target Sheet'!C9) -> 3 | F9: 6930.7028 | G9: =(K9/I9) -> 6766.755 | H9: 5037 | I9: =SUMIF('Booking Apr'!B:B,'FY Target Sheet'!C9,'Booking Apr'!K:K)-SUMIF('Cancel Apr'!A:A,'FY Target Sheet'!C9,'Cancel Apr'!F:F) -> 3845 | J9: 34909950 | K9: =SUMIF('Booking Apr'!B:B,C9,'Booking Apr'!L:L)-SUMIF('Cancel Apr'!A:A,'FY Target Sheet'!C9,'Cancel Apr'!G:G) -> 26018173 | L9: 16961620 | M9: =SUMIF('Coll Apr'!A:A,C9,'Coll Apr'!J:J)*100000 -> 14163000 | N9: ='Construction Budget'!G23*10000000 -> 21507854 | O9: ='Construction Budget'!G24*10000000 -> 9451000 | P9: 5 | Q9: =COUNTIF('Booking May'!B:B,'FY Target Sheet'!C9)-COUNTIF('Cancel May'!A:A,'FY Target Sheet'!C9) -> 8 | R9: 6972.0171 | S9: =(W9/U9) -> 6844.9636 | T9: 6663 | U9: =SUMIF('Booking May'!B:B,'FY Target Sheet'!C9,'Booking May'!K:K)-SUMIF('Cancel May'!A:A,'FY Target Sheet'!C9,'Cancel May'!F:F) -> 10064 | V9: 46454550 | W9: =SUMIF('Booking May'!B:B,C9,'Booking May'!L:L)-SUMIF('Cancel May'!A:A,'FY Target Sheet'!C9,'Cancel May'!G:G) -> 68887714 | X9: 28976593 | Y9: =SUMIF('Coll May'!A:A,C9,'Coll May'!J:J)*100000 -> 8577000 | Z9: ='Construction Budget'!H23*10000000 -> 32261781 | AA9: ='Construction Budget'!H24*10000000 -> 3800000 | AB9: 6 | AC9: =COUNTIF('Booking Jun'!B:B,C9)-COUNTIF('Cancel Jun'!A:A,C9) -> 6 | AD9: 6997.1227 | AE9: =(AI9/AG9) -> 6831.1112 | AF9: 8289 | AG9: =SUMIF('Booking Jun'!B:B,'FY Target Sheet'!C9,'Booking Jun'!K:K)-SUMIF('Cancel Jun'!A:A,'FY Target Sheet'!C9,'Cancel Jun'!F:F) -> 7529 | AH9: 57999150 | AI9: =SUMIF('Booking Jun'!B:B,C9,'Booking Jun'!L:L)-SUMIF('Cancel Jun'!A:A,'FY Target Sheet'!C9,'Cancel Jun'!G:G) -> 51431436 | AJ9: 30319145 | AK9: =SUMIF('Coll Jun'!A:A,C9,'Coll Jun'!J:J)*100000 -> 15983000 | AL9: ='Construction Budget'!I23*10000000 -> 33460076 | AM9: ='Construction Budget'!I24*10000000 -> 13798044 | AN9: 6 | AO9: 6975.0769 | AP9: 7800 | AQ9: 54405600 | AR9: 35066633 | AS9: ='Construction Budget'!J23*10000000 -> 47132926 | AT9: 6 | AU9: 7070.0034 | AV9: 8527.86 | AW9: 60291999 | AX9: 38100332 | AY9: ='Construction Budget'!K23*10000000 -> 52141184 | AZ9: 8 | BA9: 7020.0307 | BB9: 10497.86 | BC9: 73695299 | BD9: 43586717 | BE9: ='Construction Budget'!L23*10000000 -> 55428813 | BF9: 13 | BG9: 7039.2532 | BH9: 16252.58 | BI9: 114406026 | BJ9: 57539867 | BK9: ='Construction Budget'!M23*10000000 -> 55613166 | BL9: 9 | BM9: 7106.6328 | BN9: 12177.72 | BO9: 86542584 | BP9: 65761915 | BQ9: ='Construction Budget'!N23*10000000 -> 55797519 | BR9: 8 | BS9: 7094.2129 | BT9: 10748 | BU9: 76248600 | BV9: 71330049 | BW9: ='Construction Budget'!O23*10000000 -> 43200061 | BX9: 7 | BY9: 7159.4238 | BZ9: 9414.72 | CA9: 67403970 | CB9: 75970714 | CC9: ='Construction Budget'!P23*10000000 -> 25625072 | CD9: 6 | CE9: 7099.4012 | CF9: 7549.86 | CG9: 53599485 | CH9: 84700861 | CI9: ='Construction Budget'!Q23*10000000 -> 18681108 | CJ9: 9 | CK9: 7101.0462 | CL9: 11449.86 | CM9: 81305985 | CN9: 97188190 | CO9: ='Construction Budget'!R23*10000000 -> 59156841
A10: On Going | B10: RESIDENTIAL | C10: NYATI EXUBERANCE I | E10: =COUNTIF('Booking Apr'!B:B,'FY Target Sheet'!C10)-COUNTIF('Cancel Apr'!A:A,'FY Target Sheet'!C10) -> 0 | I10: =SUMIF('Booking Apr'!B:B,'FY Target Sheet'!C10,'Booking Apr'!K:K)-SUMIF('Cancel Apr'!A:A,'FY Target Sheet'!C10,'Cancel Apr'!F:F) -> 0 | K10: =SUMIF('Booking Apr'!B:B,C10,'Booking Apr'!L:L)-SUMIF('Cancel Apr'!A:A,'FY Target Sheet'!C10,'Cancel Apr'!G:G) -> 0 | M10: =SUMIF('Coll Apr'!A:A,C10,'Coll Apr'!J:J)*100000 -> 0 | N10: ='Construction Budget'!G26*10000000 -> 0 | O10: ='Construction Budget'!G27*10000000 -> 2635577.4 | Q10: =COUNTIF('Booking May'!B:B,'FY Target Sheet'!C10)-COUNTIF('Cancel May'!A:A,'FY Target Sheet'!C10) -> 0 | U10: =SUMIF('Booking May'!B:B,'FY Target Sheet'!C10,'Booking May'!K:K)-SUMIF('Cancel May'!A:A,'FY Target Sheet'!C10,'Cancel May'!F:F) -> 0 | W10: =SUMIF('Booking May'!B:B,C10,'Booking May'!L:L)-SUMIF('Cancel May'!A:A,'FY Target Sheet'!C10,'Cancel May'!G:G) -> 0 | Y10: =SUMIF('Coll May'!A:A,C10,'Coll May'!J:J)*100000 -> 0 | Z10: ='Construction Budget'!H26*10000000 -> 0 | AA10: ='Construction Budget'!H27*10000000 -> 658894.36 | AC10: =COUNTIF('Booking Jun'!B:B,C10)-COUNTIF('Cancel Jun'!A:A,C10) -> 0 | AG10: =SUMIF('Booking Jun'!B:B,'FY Target Sheet'!C10,'Booking Jun'!K:K)-SUMIF('Cancel Jun'!A:A,'FY Target Sheet'!C10,'Cancel Jun'!F:F) -> 0 | AI10: =SUMIF('Booking Jun'!B:B,C10,'Booking Jun'!L:L)-SUMIF('Cancel Jun'!A:A,'FY Target Sheet'!C10,'Cancel Jun'!G:G) -> 0 | AK10: =SUMIF('Coll Jun'!A:A,C10,'Coll Jun'!J:J)*100000 -> 330000 | AL10: ='Construction Budget'!I26*10000000 -> 0 | AM10: ='Construction Budget'!I27*10000000 -> 732104.76 | AS10: ='Construction Budget'!J26*10000000 -> 0 | AY10: ='Construction Budget'!K26*10000000 -> 2200028.2 | BE10: ='Construction Budget'!L26*10000000 -> 2800035.8 | BK10: ='Construction Budget'!M26*10000000 -> 3200041 | BQ10: ='Construction Budget'!N26*10000000 -> 1800023 | BW10: ='Construction Budget'!O26*10000000 -> 3000038.4 | CC10: ='Construction Budget'!P26*10000000 -> 2600033.3 | CI10: ='Construction Budget'!Q26*10000000 -> 2400030.7 | CO10: ='Construction Budget'!R26*10000000 -> 2000025.6
A11: On Going | B11: RESIDENTIAL | C11: NYATI EXUBERANCE IV | D11: 8 | E11: =COUNTIF('Booking Apr'!B:B,'FY Target Sheet'!C11)-COUNTIF('Cancel Apr'!A:A,'FY Target Sheet'!C11) -> 7 | F11: 5812.5 | G11: =(K11/I11) -> 5790.9594 | H11: 7864 | I11: =SUMIF('Booking Apr'!B:B,'FY Target Sheet'!C11,'Booking Apr'!K:K)-SUMIF('Cancel Apr'!A:A,'FY Target Sheet'!C11,'Cancel Apr'!F:F) -> 6879 | J11: 45709500 | K11: =SUMIF('Booking Apr'!B:B,C11,'Booking Apr'!L:L)-SUMIF('Cancel Apr'!A:A,'FY Target Sheet'!C11,'Cancel Apr'!G:G) -> 39836010 | L11: 45789117 | M11: =SUMIF('Coll Apr'!A:A,C11,'Coll Apr'!J:J)*100000 -> 90754000 | N11: ='Construction Budget'!G29*10000000 -> 10977574 | O11: ='Construction Budget'!G30*10000000 -> 16909781 | P11: 6 | Q11: =COUNTIF('Booking May'!B:B,'FY Target Sheet'!C11)-COUNTIF('Cancel May'!A:A,'FY Target Sheet'!C11) -> 6 | R11: 5900 | S11: =(W11/U11) -> 5759.9613 | T11: 5898 | U11: =SUMIF('Booking May'!B:B,'FY Target Sheet'!C11,'Booking May'!K:K)-SUMIF('Cancel May'!A:A,'FY Target Sheet'!C11,'Cancel May'!F:F) -> 5894 | V11: 34798200 | W11: =SUMIF('Booking May'!B:B,C11,'Booking May'!L:L)-SUMIF('Cancel May'!A:A,'FY Target Sheet'!C11,'Cancel May'!G:G) -> 33949212 | X11: 53412177 | Y11: =SUMIF('Coll May'!A:A,C11,'Coll May'!J:J)*100000 -> 52939000 | Z11: ='Construction Budget'!H29*10000000 -> 11246585 | AA11: ='Construction Budget'!H30*10000000 -> 13814687 | AB11: 5 | AC11: =COUNTIF('Booking Jun'!B:B,C11)-COUNTIF('Cancel Jun'!A:A,C11) -> 12 | AD11: 6000 | AE11: =(AI11/AG11) -> 5774.822 | AF11: 4915 | AG11: =SUMIF('Booking Jun'!B:B,'FY Target Sheet'!C11,'Booking Jun'!K:K)-SUMIF('Cancel Jun'!A:A,'FY Target Sheet'!C11,'Cancel Jun'!F:F) -> 11800 | AH11: 29490000 | AI11: =SUMIF('Booking Jun'!B:B,C11,'Booking Jun'!L:L)-SUMIF('Cancel Jun'!A:A,'FY Target Sheet'!C11,'Cancel Jun'!G:G) -> 68142900 | AJ11: 56017127 | AK11: =SUMIF('Coll Jun'!A:A,C11,'Coll Jun'!J:J)*100000 -> 50007000 | AL11: ='Construction Budget'!I29*10000000 -> 11246585 | AM11: ='Construction Budget'!I30*10000000 -> 24081340 | AN11: 5 | AO11: 5930 | AP11: 4915 | AQ11: 29145950 | AR11: 24016798 | AS11: ='Construction Budget'!J29*10000000 -> 17278220 | AT11: 6 | AU11: 5825 | AV11: 5898 | AW11: 34355850 | AX11: 28344455 | AY11: ='Construction Budget'!K29*10000000 -> 15828617 | AZ11: 7 | BA11: 5878.5714 | BB11: 6881 | BC11: 40450450 | BD11: 32888372 | BE11: ='Construction Budget'!L29*10000000 -> 17487718 | BF11: 0 | BG11: 0 | BH11: 0 | BI11: 0 | BJ11: 50518910 | BK11: ='Construction Budget'!M29*10000000 -> 18681982 | BL11: 0 | BM11: 0 | BN11: 0 | BO11: 0 | BP11: 55605935 | BQ11: ='Construction Budget'!N29*10000000 -> 14820128 | BR11: 0 | BS11: 0 | BT11: 0 | BU11: 0 | BV11: 52779810 | BW11: ='Construction Budget'!O29*10000000 -> 12090612 | BX11: 0 | BY11: 0 | BZ11: 0 | CA11: 0 | CB11: 46235488 | CC11: ='Construction Budget'!P29*10000000 -> 10398135 | CD11: 0 | CE11: 0 | CF11: 0 | CG11: 0 | CH11: 35955765 | CI11: ='Construction Budget'!Q29*10000000 -> 8381156.9 | CJ11: 0 | CK11: 0 | CL11: 0 | CM11: 0 | CN11: 46235488 | CO11: ='Construction Budget'!R29*10000000 -> 1564605.9
A12: On Going | B12: RESIDENTIAL | C12: NYATI ESTEBAN II | D12: 18 | E12: =COUNTIF('Booking Apr'!B:B,'FY Target Sheet'!C12)-COUNTIF('Cancel Apr'!A:A,'FY Target Sheet'!C12) -> 5 | F12: 5916.7872 | G12: =(K12/I12) -> 5986.6978 | H12: 24796 | I12: =SUMIF('Booking Apr'!B:B,'FY Target Sheet'!C12,'Booking Apr'!K:K)-SUMIF('Cancel Apr'!A:A,'FY Target Sheet'!C12,'Cancel Apr'!F:F) -> 8495 | J12: 146712655 | K12: =SUMIF('Booking Apr'!B:B,C12,'Booking Apr'!L:L)-SUMIF('Cancel Apr'!A:A,'FY Target Sheet'!C12,'Cancel Apr'!G:G) -> 50856998 | L12: 51534025 | M12: =SUMIF('Coll Apr'!A:A,C12,'Coll Apr'!J:J)*100000 -> 89573000 | N12: ='Construction Budget'!G32*10000000 -> 52383569 | O12: ='Construction Budget'!G33*10000000 -> 37366645 | P12: 8 | Q12: =COUNTIF('Booking May'!B:B,'FY Target Sheet'!C12)-COUNTIF('Cancel May'!A:A,'FY Target Sheet'!C12) -> 10 | R12: 5924.7482 | S12: =(W12/U12) -> 5878.7526 | T12: 12014 | U12: =SUMIF('Booking May'!B:B,'FY Target Sheet'!C12,'Booking May'!K:K)-SUMIF('Cancel May'!A:A,'FY Target Sheet'!C12,'Cancel May'!F:F) -> 14355 | V12: 71179925 | W12: =SUMIF('Booking May'!B:B,C12,'Booking May'!L:L)-SUMIF('Cancel May'!A:A,'FY Target Sheet'!C12,'Cancel May'!G:G) -> 84389493 | X12: 64306080 | Y12: =SUMIF('Coll May'!A:A,C12,'Coll May'!J:J)*100000 -> 62561000 | Z12: ='Construction Budget'!H32*10000000 -> 57546945 | AA12: ='Construction Budget'!H33*10000000 -> 34447376 | AB12: 12 | AC12: =COUNTIF('Booking Jun'!B:B,C12)-COUNTIF('Cancel Jun'!A:A,C12) -> 17 | AD12: 5914.7009 | AE12: =(AI12/AG12) -> 5861.4946 | AF12: 16180 | AG12: =SUMIF('Booking Jun'!B:B,'FY Target Sheet'!C12,'Booking Jun'!K:K)-SUMIF('Cancel Jun'!A:A,'FY Target Sheet'!C12,'Cancel Jun'!F:F) -> 25194 | AH12: 95699860 | AI12: =SUMIF('Booking Jun'!B:B,C12,'Booking Jun'!L:L)-SUMIF('Cancel Jun'!A:A,'FY Target Sheet'!C12,'Cancel Jun'!G:G) -> 147674494 | AJ12: 58490496 | AK12: =SUMIF('Coll Jun'!A:A,C12,'Coll Jun'!J:J)*100000 -> 80789000 | AL12: ='Construction Budget'!I32*10000000 -> 97656809 | AM12: ='Construction Budget'!I33*10000000 -> 75317143 | AN12: 12 | AO12: 5991.3004 | AP12: 16180 | AQ12: 96939240 | AR12: 69999877 | AS12: ='Construction Budget'!J32*10000000 -> 76170244 | AT12: 22 | AU12: 5993.8736 | AV12: 31592 | AW12: 189358455 | AX12: 88069614 | AY12: ='Construction Budget'!K32*10000000 -> 87151238 | AZ12: 22 | BA12: 5993.8736 | BB12: 31592 | BC12: 189358455 | BD12: 99669827 | BE12: ='Construction Budget'!L32*10000000 -> 84852124 | BF12: 22 | BG12: 6177.345 | BH12: 31066 | BI12: 191905400 | BJ12: 1.1873302e+08 | BK12: ='Construction Budget'!M32*10000000 -> 1.1714737e+08 | BL12: 12 | BM12: 6179.5787 | BN12: 17232 | BO12: 106486500 | BP12: 1.3009362e+08 | BQ12: ='Construction Budget'!N32*10000000 -> 94856488 | BR12: 14 | BS12: 6176.0343 | BT12: 19578 | BU12: 120914400 | BV12: 1.4655568e+08 | BW12: ='Construction Budget'!O32*10000000 -> 86468350 | BX12: 13 | BY12: 6177.6936 | BZ12: 18405 | CA12: 113700450 | CB12: 1.7267991e+08 | CC12: ='Construction Budget'!P32*10000000 -> 87742761 | CD12: 13 | CE12: 6190.9592 | CF12: 45411 | CG12: 281137650 | CH12: 1.7255023e+08 | CI12: ='Construction Budget'!Q32*10000000 -> 76389841 | CJ12: 12 | CK12: 6175.425 | CL12: 16706 | CM12: 103166650 | CN12: 1.925062e+08 | CO12: ='Construction Budget'!R32*10000000 -> 81647059
A13: New | B13: RESIDENTIAL | C13: NYATI ESTEBAN III | E13: =COUNTIF('Booking Apr'!B:B,'FY Target Sheet'!C13)-COUNTIF('Cancel Apr'!A:A,'FY Target Sheet'!C13) -> 0 | I13: =SUMIF('Booking Apr'!B:B,'FY Target Sheet'!C13,'Booking Apr'!K:K)-SUMIF('Cancel Apr'!A:A,'FY Target Sheet'!C13,'Cancel Apr'!F:F) -> 0 | K13: =SUMIF('Booking Apr'!B:B,C13,'Booking Apr'!L:L)-SUMIF('Cancel Apr'!A:A,'FY Target Sheet'!C13,'Cancel Apr'!G:G) -> 0 | M13: =SUMIF('Coll Apr'!A:A,C13,'Coll Apr'!J:J) -> 0 | N13: ='Construction Budget'!G35*10000000 -> 5046916.2 | O13: ='Construction Budget'!G36*10000000 -> 0 | Q13: =COUNTIF('Booking May'!B:B,'FY Target Sheet'!C13)-COUNTIF('Cancel May'!A:A,'FY Target Sheet'!C13) -> 0 | U13: =SUMIF('Booking May'!B:B,'FY Target Sheet'!C13,'Booking May'!K:K)-SUMIF('Cancel May'!A:A,'FY Target Sheet'!C13,'Cancel May'!F:F) -> 0 | W13: =SUMIF('Booking May'!B:B,C13,'Booking May'!L:L)-SUMIF('Cancel May'!A:A,'FY Target Sheet'!C13,'Cancel May'!G:G) -> 0 | Y13: =SUMIF('Coll May'!A:A,C13,'Coll May'!J:J)*100000 -> 0 | Z13: ='Construction Budget'!H35*10000000 -> 7570374.3 | AA13: ='Construction Budget'!H36*10000000 -> 897000 | AC13: =COUNTIF('Booking Jun'!B:B,C13)-COUNTIF('Cancel Jun'!A:A,C13) -> 0 | AG13: =SUMIF('Booking Jun'!B:B,'FY Target Sheet'!C13,'Booking Jun'!K:K)-SUMIF('Cancel Jun'!A:A,'FY Target Sheet'!C13,'Cancel Jun'!F:F) -> 0 | AI13: =SUMIF('Booking Jun'!B:B,C13,'Booking Jun'!L:L)-SUMIF('Cancel Jun'!A:A,'FY Target Sheet'!C13,'Cancel Jun'!G:G) -> 0 | AK13: =SUMIF('Coll Jun'!A:A,C13,'Coll Jun'!J:J)*100000 -> 0 | AL13: ='Construction Budget'!I35*10000000 -> 7570374.3 | AM13: ='Construction Budget'!I36*10000000 -> 0 | AS13: ='Construction Budget'!J35*10000000 -> 8691911.2 | AY13: ='Construction Budget'!K35*10000000 -> 10912554 | BE13: ='Construction Budget'!L35*10000000 -> 12022876 | BK13: ='Construction Budget'!M35*10000000 -> 12022876 | BQ13: ='Construction Budget'!N35*10000000 -> 7177836.4 | BW13: ='Construction Budget'!O35*10000000 -> 6370329.8 | CC13: ='Construction Budget'!P35*10000000 -> 7290887.3 | CI13: ='Construction Budget'!Q35*10000000 -> 15422479 | CO13: ='Construction Budget'!R35*10000000 -> 19902122
A14: Completed | B14: COMMERCIAL | C14: NYATI PLAZA & NYATI ENTHRAL I | D14: 1 | E14: =COUNTIF('Booking Apr'!B:B,'FY Target Sheet'!C14)-COUNTIF('Cancel Apr'!A:A,'FY Target Sheet'!C14) -> 0 | F14: 8000 | H14: 14310 | I14: =SUMIF('Booking Apr'!B:B,'FY Target Sheet'!C14,'Booking Apr'!K:K)-SUMIF('Cancel Apr'!A:A,'FY Target Sheet'!C14,'Cancel Apr'!F:F) -> 0 | J14: 114480000 | K14: =SUMIF('Booking Apr'!B:B,C14,'Booking Apr'!L:L)-SUMIF('Cancel Apr'!A:A,'FY Target Sheet'!C14,'Cancel Apr'!G:G) -> 0 | L14: 1.7697941e+08 | M14: =SUMIF('Coll Apr'!A:A,C14,'Coll Apr'!J:J) -> 0 | P14: 1 | Q14: =COUNTIF('Booking May'!B:B,'FY Target Sheet'!C14)-COUNTIF('Cancel May'!A:A,'FY Target Sheet'!C14) -> 0 | R14: 8000 | T14: 10675 | U14: =SUMIF('Booking May'!B:B,'FY Target Sheet'!C14,'Booking May'!K:K)-SUMIF('Cancel May'!A:A,'FY Target Sheet'!C14,'Cancel May'!F:F) -> 0 | V14: 85400000 | W14: =SUMIF('Booking May'!B:B,C14,'Booking May'!L:L)-SUMIF('Cancel May'!A:A,'FY Target Sheet'!C14,'Cancel May'!G:G) -> 0 | X14: 2.1967941e+08 | Y14: =SUMIF('Coll May'!A:A,C14,'Coll May'!J:J)*100000 -> 0 | AB14: 2 | AC14: =COUNTIF('Booking Jun'!B:B,C14)-COUNTIF('Cancel Jun'!A:A,C14) -> 0 | AD14: 8388.695 | AF14: 17762 | AG14: =SUMIF('Booking Jun'!B:B,'FY Target Sheet'!C14,'Booking Jun'!K:K)-SUMIF('Cancel Jun'!A:A,'FY Target Sheet'!C14,'Cancel Jun'!F:F) -> 0 | AH14: 149000000 | AI14: =SUMIF('Booking Jun'!B:B,C14,'Booking Jun'!L:L)-SUMIF('Cancel Jun'!A:A,'FY Target Sheet'!C14,'Cancel Jun'!G:G) -> 0 | AJ14: 2.3003541e+08 | AK14: =SUMIF('Coll Jun'!A:A,C14,'Coll Jun'!J:J)*100000 -> 0 | AN14: 3 | AO14: 9288.0597 | AP14: 10720 | AQ14: 99568000 | AR14: 2.2503741e+08 | AT14: 3 | AU14: 8889.0033 | AV14: 15532 | AW14: 138064000 | AX14: 2.2647341e+08 | AZ14: 3 | BA14: 6389.3312 | BB14: 14697 | BC14: 93904000 | BD14: 2.3572341e+08 | BF14: 3 | BG14: 8650.8909 | BH14: 21214 | BI14: 183520000 | BJ14: 2.5845141e+08 | BL14: 3 | BM14: 8889.0033 | BN14: 15532 | BO14: 138064000 | BP14: 2.573177e+08 | BR14: 2 | BS14: 10000 | BT14: 6904 | BU14: 69040000 | BV14: 2.000777e+08 | BX14: 2 | BY14: 10000 | BZ14: 6904 | CA14: 69040000 | CB14: 1.655657e+08 | CD14: 2 | CE14: 10000 | CF14: 6904 | CG14: 69040000 | CH14: 82848000 | CJ14: 1 | CK14: 10000 | CL14: 3452 | CM14: 34520000 | CN14: 75944000
A15: Completed | B15: COMMERCIAL | C15: NYATI EMPRESS | D15: 0 | E15: =COUNTIF('Booking Apr'!B:B,'FY Target Sheet'!C15)-COUNTIF('Cancel Apr'!A:A,'FY Target Sheet'!C15) -> 1 | F15: 0 | G15: =(K15/I15) -> 16250 | H15: 0 | I15: =SUMIF('Booking Apr'!B:B,'FY Target Sheet'!C15,'Booking Apr'!K:K)-SUMIF('Cancel Apr'!A:A,'FY Target Sheet'!C15,'Cancel Apr'!F:F) -> 400 | J15: 0 | K15: =SUMIF('Booking Apr'!B:B,C15,'Booking Apr'!L:L)-SUMIF('Cancel Apr'!A:A,'FY Target Sheet'!C15,'Cancel Apr'!G:G) -> 6500000 | L15: 22380250 | M15: =SUMIF('Coll Apr'!A:A,C15,'Coll Apr'!J:J)*100000 -> 650000 | P15: 0 | Q15: =COUNTIF('Booking May'!B:B,'FY Target Sheet'!C15)-COUNTIF('Cancel May'!A:A,'FY Target Sheet'!C15) -> 2 | R15: 0 | S15: =(W15/U15) -> 8394.5774 | T15: 0 | U15: =SUMIF('Booking May'!B:B,'FY Target Sheet'!C15,'Booking May'!K:K)-SUMIF('Cancel May'!A:A,'FY Target Sheet'!C15,'Cancel May'!F:F) -> 3135 | V15: 0 | W15: =SUMIF('Booking May'!B:B,C15,'Booking May'!L:L)-SUMIF('Cancel May'!A:A,'FY Target Sheet'!C15,'Cancel May'!G:G) -> 26317000 | X15: 22380250 | Y15: =SUMIF('Coll May'!A:A,C15,'Coll May'!J:J)*100000 -> 31878000 | AB15: 0 | AC15: =COUNTIF('Booking Jun'!B:B,C15)-COUNTIF('Cancel Jun'!A:A,C15) -> 0 | AD15: 0 | AF15: 0 | AG15: =SUMIF('Booking Jun'!B:B,'FY Target Sheet'!C15,'Booking Jun'!K:K)-SUMIF('Cancel Jun'!A:A,'FY Target Sheet'!C15,'Cancel Jun'!F:F) -> 0 | AH15: 0 | AI15: =SUMIF('Booking Jun'!B:B,C15,'Booking Jun'!L:L)-SUMIF('Cancel Jun'!A:A,'FY Target Sheet'!C15,'Cancel Jun'!G:G) -> 0 | AJ15: 22380250 | AK15: =SUMIF('Coll Jun'!A:A,C15,'Coll Jun'!J:J)*100000 -> 5095000 | AN15: 2 | AO15: 8000 | AP15: 960 | AQ15: 7680000 | AR15: 26220250 | AT15: 2 | AU15: 8000 | AV15: 1074 | AW15: 8592000 | AX15: 8136000 | AZ15: 1 | BA15: 8000 | BB15: 5872 | BC15: 46976000 | BD15: 27784000 | BF15: 0 | BG15: 0 | BH15: 0 | BI15: 0 | BJ15: 23488000 | BL15: 0 | BM15: 0 | BN15: 0 | BO15: 0 | BP15: 0 | BR15: 0 | BS15: 0 | BT15: 0 | BU15: 0 | BV15: 0 | BX15: 0 | BY15: 0 | BZ15: 0 | CA15: 0 | CB15: 0 | CD15: 0 | CE15: 0 | CF15: 0 | CG15: 0 | CH15: 0 | CJ15: 0 | CK15: 0 | CL15: 0 | CM15: 0 | CN15: 0
A16: On Going | B16: LUXURY | C16: NYATI EVOQUE | D16: 1 | E16: =COUNTIF('Booking Apr'!B:B,'FY Target Sheet'!C16)-COUNTIF('Cancel Apr'!A:A,'FY Target Sheet'!C16) -> 2 | F16: 12000 | G16: =(K16/I16) -> 12763.811 | H16: 2150 | I16: =SUMIF('Booking Apr'!B:B,'FY Target Sheet'!C16,'Booking Apr'!K:K)-SUMIF('Cancel Apr'!A:A,'FY Target Sheet'!C16,'Cancel Apr'!F:F) -> 4301 | J16: 25800000 | K16: =SUMIF('Booking Apr'!B:B,C16,'Booking Apr'!L:L)-SUMIF('Cancel Apr'!A:A,'FY Target Sheet'!C16,'Cancel Apr'!G:G) -> 54897150 | L16: 16119500 | M16: =SUMIF('Coll Apr'!A:A,C16,'Coll Apr'!J:J)*100000 -> 41774000 | N16: ='Construction Budget'!G38*10000000 -> 46718535 | O16: ='Construction Budget'!G39*10000000 -> 11355934 | P16: 2 | Q16: =COUNTIF('Booking May'!B:B,'FY Target Sheet'!C16)-COUNTIF('Cancel May'!A:A,'FY Target Sheet'!C16) -> 4 | R16: 12000 | S16: =(W16/U16) -> 11409.271 | T16: 4681 | U16: =SUMIF('Booking May'!B:B,'FY Target Sheet'!C16,'Booking May'!K:K)-SUMIF('Cancel May'!A:A,'FY Target Sheet'!C16,'Cancel May'!F:F) -> 9364 | V16: 56172000 | W16: =SUMIF('Booking May'!B:B,C16,'Booking May'!L:L)-SUMIF('Cancel May'!A:A,'FY Target Sheet'!C16,'Cancel May'!G:G) -> 106836416 | X16: 45546093 | Y16: =SUMIF('Coll May'!A:A,C16,'Coll May'!J:J)*100000 -> 46209000 | Z16: ='Construction Budget'!H38*10000000 -> 49195027 | AA16: ='Construction Budget'!H39*10000000 -> 21503789 | AB16: 2 | AC16: =COUNTIF('Booking Jun'!B:B,C16)-COUNTIF('Cancel Jun'!A:A,C16) -> 3 | AD16: 12000 | AE16: =(AI16/AG16) -> 11034.844 | AF16: 4681 | AG16: =SUMIF('Booking Jun'!B:B,'FY Target Sheet'!C16,'Booking Jun'!K:K)-SUMIF('Cancel Jun'!A:A,'FY Target Sheet'!C16,'Cancel Jun'!F:F) -> 7634 | AH16: 56172000 | AI16: =SUMIF('Booking Jun'!B:B,C16,'Booking Jun'!L:L)-SUMIF('Cancel Jun'!A:A,'FY Target Sheet'!C16,'Cancel Jun'!G:G) -> 84240000 | AJ16: 41582187 | AK16: =SUMIF('Coll Jun'!A:A,C16,'Coll Jun'!J:J)*100000 -> 41837000 | AL16: ='Construction Budget'!I38*10000000 -> 50016851 | AM16: ='Construction Budget'!I39*10000000 -> 44214897 | AN16: 2 | AO16: 12000 | AP16: 4681 | AQ16: 56172000 | AR16: 45150087 | AS16: ='Construction Budget'!J38*10000000 -> 64614159 | AT16: 2 | AU16: 12000 | AV16: 4681 | AW16: 56172000 | AX16: 59362987 | AY16: ='Construction Budget'!K38*10000000 -> 73484312 | AZ16: 3 | BA16: 12000 | BB16: 7212 | BC16: 86544000 | BD16: 66498787 | BE16: ='Construction Budget'!L38*10000000 -> 76996625 | BF16: 3 | BG16: 12000 | BH16: 7212 | BI16: 86544000 | BJ16: 72344587 | BK16: ='Construction Budget'!M38*10000000 -> 71740277 | BL16: 3 | BM16: 12000 | BN16: 7212 | BO16: 86544000 | BP16: 80998987 | BQ16: ='Construction Budget'!N38*10000000 -> 78257760 | BR16: 4 | BS16: 12000 | BT16: 9362 | BU16: 112344000 | BV16: 91702687 | BW16: ='Construction Budget'!O38*10000000 -> 83542749 | BX16: 3 | BY16: 12000 | BZ16: 7212 | CA16: 86544000 | CB16: 1.0159149e+08 | CC16: ='Construction Budget'!P38*10000000 -> 88409218 | CD16: 3 | CE16: 12000 | CF16: 7212 | CG16: 86544000 | CH16: 1.1100519e+08 | CI16: ='Construction Budget'!Q38*10000000 -> 75810732 | CJ16: 2 | CK16: 12000 | CL16: 4681 | CM16: 56172000 | CN16: 1.2603609e+08 | CO16: ='Construction Budget'!R38*10000000 -> 91224634
A17: On Going | B17: LUXURY | C17: NYATI EVANIA | D17: 5 | E17: =COUNTIF('Booking Apr'!B:B,'FY Target Sheet'!C17)-COUNTIF('Cancel Apr'!A:A,'FY Target Sheet'!C17) -> -1 | F17: 10000 | G17: =(K17/I17) -> 10218.352 | H17: 10110.8 | I17: =SUMIF('Booking Apr'!B:B,'FY Target Sheet'!C17,'Booking Apr'!K:K)-SUMIF('Cancel Apr'!A:A,'FY Target Sheet'!C17,'Cancel Apr'!F:F) -> -2661 | J17: 1.01108e+08 | K17: =SUMIF('Booking Apr'!B:B,C17,'Booking Apr'!L:L)-SUMIF('Cancel Apr'!A:A,'FY Target Sheet'!C17,'Cancel Apr'!G:G) -> -27191036 | L17: 20873340 | M17: =SUMIF('Coll Apr'!A:A,C17,'Coll Apr'!J:J)*100000 -> 17494000 | N17: ='Construction Budget'!G41*10000000 -> 50000640 | O17: ='Construction Budget'!G42*10000000 -> 20000000 | P17: 7 | Q17: =COUNTIF('Booking May'!B:B,'FY Target Sheet'!C17)-COUNTIF('Cancel May'!A:A,'FY Target Sheet'!C17) -> 0 | R17: 9793.1135 | T17: 15032.4 | U17: =SUMIF('Booking May'!B:B,'FY Target Sheet'!C17,'Booking May'!K:K)-SUMIF('Cancel May'!A:A,'FY Target Sheet'!C17,'Cancel May'!F:F) -> 0 | V17: 147214000 | W17: =SUMIF('Booking May'!B:B,C17,'Booking May'!L:L)-SUMIF('Cancel May'!A:A,'FY Target Sheet'!C17,'Cancel May'!G:G) -> 0 | X17: 48270388 | Y17: =SUMIF('Coll May'!A:A,C17,'Coll May'!J:J)*100000 -> 13921000 | Z17: ='Construction Budget'!H41*10000000 -> 45000576 | AA17: ='Construction Budget'!H42*10000000 -> 11800000 | AB17: 6 | AC17: =COUNTIF('Booking Jun'!B:B,C17)-COUNTIF('Cancel Jun'!A:A,C17) -> 3 | AD17: 9772.7538 | AE17: =(AI17/AG17) -> 10238.918 | AF17: 13685.6 | AG17: =SUMIF('Booking Jun'!B:B,'FY Target Sheet'!C17,'Booking Jun'!K:K)-SUMIF('Cancel Jun'!A:A,'FY Target Sheet'!C17,'Cancel Jun'!F:F) -> 5690 | AH17: 133746000 | AI17: =SUMIF('Booking Jun'!B:B,C17,'Booking Jun'!L:L)-SUMIF('Cancel Jun'!A:A,'FY Target Sheet'!C17,'Cancel Jun'!G:G) -> 58259443 | AJ17: 59175805 | AK17: =SUMIF('Coll Jun'!A:A,C17,'Coll Jun'!J:J)*100000 -> 4259000 | AL17: ='Construction Budget'!I41*10000000 -> 42500544 | AM17: ='Construction Budget'!I42*10000000 -> 25100000 | AN17: 6 | AO17: 10500 | AP17: 12650.4 | AQ17: 1.328292e+08 | AR17: 65817265 | AS17: ='Construction Budget'!J41*10000000 -> 67500864 | AT17: 6 | AU17: 10500 | AV17: 12650.4 | AW17: 1.328292e+08 | AX17: 72458725 | AY17: ='Construction Budget'!K41*10000000 -> 75000960 | AZ17: 7 | BA17: 10293.114 | BB17: 15032.4 | BC17: 154730200 | BD17: 83515965 | BE17: ='Construction Budget'!L41*10000000 -> 97501248 | BF17: 7 | BG17: 12868.927 | BH17: 19249.6 | BI17: 247721700 | BJ17: 1.1050893e+08 | BK17: ='Construction Budget'!M41*10000000 -> 102501312 | BL17: 7 | BM17: 10602.002 | BN17: 15760.4 | BO17: 167091800 | BP17: 1.3743963e+08 | BQ17: ='Construction Budget'!N41*10000000 -> 92501184 | BR17: 7 | BS17: 10594.835 | BT17: 15032.4 | BU17: 159265800 | BV17: 1.4027636e+08 | BW17: ='Construction Budget'!O41*10000000 -> 107501376 | BX17: 8 | BY17: 12883.992 | BZ17: 21324.4 | CA17: 274743400 | CB17: 1.8275119e+08 | CC17: ='Construction Budget'!P41*10000000 -> 1.0000128e+08 | CD17: 6 | CE17: 10892.116 | CF17: 14413.6 | CG17: 156994600 | CH17: 1.9878981e+08 | CI17: ='Construction Budget'!Q41*10000000 -> 1.2000154e+08 | CJ17: 8 | CK17: 12883.992 | CL17: 21324.4 | CM17: 274743400 | CN17: 3.1322509e+08 | CO17: ='Construction Budget'!R41*10000000 -> 1.0000128e+08
A18: On Going | B18: LUXURY | C18: NYATI ELENOR | D18: 4 | E18: =COUNTIF('Booking Apr'!B:B,'FY Target Sheet'!C18)-COUNTIF('Cancel Apr'!A:A,'FY Target Sheet'!C18) -> 6 | F18: 10500 | G18: =(K18/I18) -> 10289.492 | H18: 10809 | I18: =SUMIF('Booking Apr'!B:B,'FY Target Sheet'!C18,'Booking Apr'!K:K)-SUMIF('Cancel Apr'!A:A,'FY Target Sheet'!C18,'Cancel Apr'!F:F) -> 20670 | J18: 113494500 | K18: =SUMIF('Booking Apr'!B:B,C18,'Booking Apr'!L:L)-SUMIF('Cancel Apr'!A:A,'FY Target Sheet'!C18,'Cancel Apr'!G:G) -> 212683800 | L18: 42298642 | M18: =SUMIF('Coll Apr'!A:A,C18,'Coll Apr'!J:J)*100000 -> 49550000 | N18: ='Construction Budget'!G44*10000000 -> 26595671 | O18: ='Construction Budget'!G45*10000000 -> 12800000 | P18: 4 | Q18: =COUNTIF('Booking May'!B:B,'FY Target Sheet'!C18)-COUNTIF('Cancel May'!A:A,'FY Target Sheet'!C18) -> 11 | R18: 10500 | S18: =(W18/U18) -> 10838.323 | T18: 11546 | U18: =SUMIF('Booking May'!B:B,'FY Target Sheet'!C18,'Booking May'!K:K)-SUMIF('Cancel May'!A:A,'FY Target Sheet'!C18,'Cancel May'!F:F) -> 32735 | V18: 121233000 | W18: =SUMIF('Booking May'!B:B,C18,'Booking May'!L:L)-SUMIF('Cancel May'!A:A,'FY Target Sheet'!C18,'Cancel May'!G:G) -> 354792500 | X18: 63296167 | Y18: =SUMIF('Coll May'!A:A,C18,'Coll May'!J:J)*100000 -> 99094000 | Z18: ='Construction Budget'!H44*10000000 -> 31755809 | AA18: ='Construction Budget'!H45*10000000 -> 13300000 | AB18: 2 | AC18: =COUNTIF('Booking Jun'!B:B,C18)-COUNTIF('Cancel Jun'!A:A,C18) -> 6 | AD18: 10500 | AE18: =(AI18/AG18) -> 10791.803 | AF18: 5036 | AG18: =SUMIF('Booking Jun'!B:B,'FY Target Sheet'!C18,'Booking Jun'!K:K)-SUMIF('Cancel Jun'!A:A,'FY Target Sheet'!C18,'Cancel Jun'!F:F) -> 18677 | AH18: 52878000 | AI18: =SUMIF('Booking Jun'!B:B,C18,'Booking Jun'!L:L)-SUMIF('Cancel Jun'!A:A,'FY Target Sheet'!C18,'Cancel Jun'!G:G) -> 201558500 | AJ18: 85940067 | AK18: =SUMIF('Coll Jun'!A:A,C18,'Coll Jun'!J:J)*100000 -> 191033000 | AL18: ='Construction Budget'!I44*10000000 -> 34033665 | AM18: ='Construction Budget'!I45*10000000 -> 17300000 | AN18: 3 | AO18: 11000 | AP18: 9633 | AQ18: 105963000 | AR18: 1.0123822e+08 | AS18: ='Construction Budget'!J44*10000000 -> 39354441 | AT18: 3 | AU18: 11000 | AV18: 8291 | AW18: 91201000 | AX18: 1.129609e+08 | AY18: ='Construction Budget'!K44*10000000 -> 44958707 | AZ18: 3 | BA18: 11000 | BB18: 9028 | BC18: 99308000 | BD18: 1.179263e+08 | BE18: ='Construction Budget'!L44*10000000 -> 46022074 | BF18: 3 | BG18: 11250 | BH18: 8291 | BI18: 93273750 | BJ18: 1.2204187e+08 | BK18: ='Construction Budget'!M44*10000000 -> 51939085 | BL18: 5 | BM18: 11250 | BN18: 15406 | BO18: 173317500 | BP18: 1.2822504e+08 | BQ18: ='Construction Budget'!N44*10000000 -> 55018808 | BR18: 4 | BS18: 11250 | BT18: 12888 | BU18: 144990000 | BV18: 1.4874189e+08 | BW18: ='Construction Budget'!O44*10000000 -> 56187625 | BX18: 4 | BY18: 11500 | BZ18: 11546 | CA18: 132779000 | CB18: 1.964979e+08 | CC18: ='Construction Budget'!P44*10000000 -> 65595318 | CD18: 4 | CE18: 11500 | CF18: 11546 | CG18: 132779000 | CH18: 2.2308483e+08 | CI18: ='Construction Budget'!Q44*10000000 -> 71260038 | CJ18: 3 | CK18: 11500 | CL18: 8291 | CM18: 95346500 | CN18: 2.3925843e+08 | CO18: ='Construction Budget'!R44*10000000 -> 77286441
A19: On Going | B19: LUXURY | C19: NYATI EMBLEM | D19: 1 | E19: =COUNTIF('Booking Apr'!B:B,'FY Target Sheet'!C19)-COUNTIF('Cancel Apr'!A:A,'FY Target Sheet'!C19) -> 1 | F19: 10200 | G19: =(K19/I19) -> 12548.051 | H19: 3642 | I19: =SUMIF('Booking Apr'!B:B,'FY Target Sheet'!C19,'Booking Apr'!K:K)-SUMIF('Cancel Apr'!A:A,'FY Target Sheet'!C19,'Cancel Apr'!F:F) -> 3642 | J19: 37148400 | K19: =SUMIF('Booking Apr'!B:B,C19,'Booking Apr'!L:L)-SUMIF('Cancel Apr'!A:A,'FY Target Sheet'!C19,'Cancel Apr'!G:G) -> 45700000 | L19: 19832853 | M19: =SUMIF('Coll Apr'!A:A,C19,'Coll Apr'!J:J)*100000 -> 16135000 | N19: ='Construction Budget'!G47*10000000 -> 38517160 | O19: ='Construction Budget'!G48*10000000 -> 13259925 | P19: 1 | Q19: =COUNTIF('Booking May'!B:B,'FY Target Sheet'!C19)-COUNTIF('Cancel May'!A:A,'FY Target Sheet'!C19) -> 1 | R19: 10200 | S19: =(W19/U19) -> 10021.966 | T19: 3642 | U19: =SUMIF('Booking May'!B:B,'FY Target Sheet'!C19,'Booking May'!K:K)-SUMIF('Cancel May'!A:A,'FY Target Sheet'!C19,'Cancel May'!F:F) -> 3642 | V19: 37148400 | W19: =SUMIF('Booking May'!B:B,C19,'Booking May'!L:L)-SUMIF('Cancel May'!A:A,'FY Target Sheet'!C19,'Cancel May'!G:G) -> 36500000 | X19: 19832853 | Y19: =SUMIF('Coll May'!A:A,C19,'Coll May'!J:J)*100000 -> 10773000 | Z19: ='Construction Budget'!H47*10000000 -> 29214945 | AA19: ='Construction Budget'!H48*10000000 -> 13454924 | AB19: 1 | AC19: =COUNTIF('Booking Jun'!B:B,C19)-COUNTIF('Cancel Jun'!A:A,C19) -> 1 | AD19: 10200 | AE19: =(AI19/AG19) -> 10708.402 | AF19: 3642 | AG19: =SUMIF('Booking Jun'!B:B,'FY Target Sheet'!C19,'Booking Jun'!K:K)-SUMIF('Cancel Jun'!A:A,'FY Target Sheet'!C19,'Cancel Jun'!F:F) -> 3642 | AH19: 37148400 | AI19: =SUMIF('Booking Jun'!B:B,C19,'Booking Jun'!L:L)-SUMIF('Cancel Jun'!A:A,'FY Target Sheet'!C19,'Cancel Jun'!G:G) -> 39000000 | AJ19: 23547693 | AK19: =SUMIF('Coll Jun'!A:A,C19,'Coll Jun'!J:J)*100000 -> 4123000 | AL19: ='Construction Budget'!I47*10000000 -> 28839922 | AM19: ='Construction Budget'!I48*10000000 -> 16379908 | AN19: 2 | AO19: 10200 | AP19: 7284 | AQ19: 74296800 | AR19: 27262533 | AS19: ='Construction Budget'!J47*10000000 -> 35083818 | AT19: 2 | AU19: 10200 | AV19: 7284 | AW19: 74296800 | AX19: 30977373 | AY19: ='Construction Budget'!K47*10000000 -> 53628330 | AZ19: 2 | BA19: 10200 | BB19: 7284 | BC19: 74296800 | BD19: 36549633 | BE19: ='Construction Budget'!L47*10000000 -> 51087723 | BF19: 2 | BG19: 10200 | BH19: 7284 | BI19: 74296800 | BJ19: 43979313 | BK19: ='Construction Budget'!M47*10000000 -> 67418686 | BL19: 2 | BM19: 10200 | BN19: 7284 | BO19: 74296800 | BP19: 49551573 | BQ19: ='Construction Budget'!N47*10000000 -> 50254097 | BR19: 2 | BS19: 10200 | BT19: 7284 | BU19: 74296800 | BV19: 62553513 | BW19: ='Construction Budget'!O47*10000000 -> 51453710 | BX19: 3 | BY19: 10200 | BZ19: 10926 | CA19: 111445200 | CB19: 73698033 | CC19: ='Construction Budget'!P47*10000000 -> 58015379 | CD19: 3 | CE19: 10200 | CF19: 10926 | CG19: 111445200 | CH19: 88557393 | CI19: ='Construction Budget'!Q47*10000000 -> 58003366 | CJ19: 3 | CK19: 10200 | CL19: 10926 | CM19: 111445200 | CN19: 1.0341675e+08 | CO19: ='Construction Budget'!R47*10000000 -> 78490543
A20: Completed | B20: COMMERCIAL | C20: NYATI ELAN COMMERCIAL | E20: =COUNTIF('Booking Apr'!B:B,'FY Target Sheet'!C20)-COUNTIF('Cancel Apr'!A:A,'FY Target Sheet'!C20) -> 0 | L20: 2252000 | M20: =SUMIF('Coll Apr'!A:A,C20,'Coll Apr'!J:J)*100000 -> 7627000 | Q20: =COUNTIF('Booking May'!B:B,'FY Target Sheet'!C20)-COUNTIF('Cancel May'!A:A,'FY Target Sheet'!C20) -> 0 | U20: =SUMIF('Booking May'!B:B,'FY Target Sheet'!C20,'Booking May'!K:K)-SUMIF('Cancel May'!A:A,'FY Target Sheet'!C20,'Cancel May'!F:F) -> 0 | W20: =SUMIF('Booking May'!B:B,C20,'Booking May'!L:L)-SUMIF('Cancel May'!A:A,'FY Target Sheet'!C20,'Cancel May'!G:G) -> 0 | X20: 3788333.3 | Y20: =SUMIF('Coll May'!A:A,C20,'Coll May'!J:J)*100000 -> 0 | AC20: =COUNTIF('Booking Jun'!B:B,C20)-COUNTIF('Cancel Jun'!A:A,C20) -> 0 | AG20: =SUMIF('Booking Jun'!B:B,'FY Target Sheet'!C20,'Booking Jun'!K:K)-SUMIF('Cancel Jun'!A:A,'FY Target Sheet'!C20,'Cancel Jun'!F:F) -> 0 | AI20: =SUMIF('Booking Jun'!B:B,C20,'Booking Jun'!L:L)-SUMIF('Cancel Jun'!A:A,'FY Target Sheet'!C20,'Cancel Jun'!G:G) -> 0 | AJ20: 3788333.3 | AK20: =SUMIF('Coll Jun'!A:A,C20,'Coll Jun'!J:J)*100000 -> 777000 | AR20: 3788333.3 | AX20: 3788333.3 | BD20: 3788333.3 | BJ20: 1536333.3 | BP20: 0 | BV20: 0 | CB20: 0 | CH20: 0 | CN20: 0
A21: Completed | B21: RESIDENTIAL | C21: NYATI DEFENCE ENCLAVE III | E21: =COUNTIF('Booking Apr'!B:B,'FY Target Sheet'!C21)-COUNTIF('Cancel Apr'!A:A,'FY Target Sheet'!C21) -> 0 | L21: 840000 | M21: =SUMIF('Coll Apr'!A:A,C21,'Coll Apr'!J:J)*100000 -> 3578000 | Q21: =COUNTIF('Booking May'!B:B,'FY Target Sheet'!C21)-COUNTIF('Cancel May'!A:A,'FY Target Sheet'!C21) -> 1 | U21: =SUMIF('Booking May'!B:B,'FY Target Sheet'!C21,'Booking May'!K:K)-SUMIF('Cancel May'!A:A,'FY Target Sheet'!C21,'Cancel May'!F:F) -> 581 | W21: =SUMIF('Booking May'!B:B,C21,'Booking May'!L:L)-SUMIF('Cancel May'!A:A,'FY Target Sheet'!C21,'Cancel May'!G:G) -> 1627000 | X21: 2738000 | Y21: =SUMIF('Coll May'!A:A,C21,'Coll May'!J:J)*100000 -> 161000 | AC21: =COUNTIF('Booking Jun'!B:B,C21)-COUNTIF('Cancel Jun'!A:A,C21) -> 0 | AG21: =SUMIF('Booking Jun'!B:B,'FY Target Sheet'!C21,'Booking Jun'!K:K)-SUMIF('Cancel Jun'!A:A,'FY Target Sheet'!C21,'Cancel Jun'!F:F) -> 0 | AI21: =SUMIF('Booking Jun'!B:B,C21,'Booking Jun'!L:L)-SUMIF('Cancel Jun'!A:A,'FY Target Sheet'!C21,'Cancel Jun'!G:G) -> 0 | AJ21: 0 | AK21: =SUMIF('Coll Jun'!A:A,C21,'Coll Jun'!J:J)*100000 -> 0 | AR21: 0 | AX21: 0 | BD21: 0 | BJ21: 0 | BP21: 0 | BV21: 0 | CB21: 0 | CH21: 0 | CN21: 0
A22: On Going | B22: COMMERCIAL | C22: NYATI QUANTUM TOWERS | E22: =COUNTIF('Booking Apr'!B:B,'FY Target Sheet'!C22)-COUNTIF('Cancel Apr'!A:A,'FY Target Sheet'!C22) -> 0 | M22: =SUMIF('Coll Apr'!A:A,C22,'Coll Apr'!J:J) -> 0 | N22: ='Construction Budget'!G53*10000000 -> 33000422 | O22: ='Construction Budget'!G54*10000000 -> 26800000 | Q22: =COUNTIF('Booking May'!B:B,'FY Target Sheet'!C22)-COUNTIF('Cancel May'!A:A,'FY Target Sheet'!C22) -> 0 | U22: =SUMIF('Booking May'!B:B,'FY Target Sheet'!C22,'Booking May'!K:K)-SUMIF('Cancel May'!A:A,'FY Target Sheet'!C22,'Cancel May'!F:F) -> 0 | W22: =SUMIF('Booking May'!B:B,C22,'Booking May'!L:L)-SUMIF('Cancel May'!A:A,'FY Target Sheet'!C22,'Cancel May'!G:G) -> 0 | Y22: =SUMIF('Coll May'!A:A,C22,'Coll May'!J:J)*100000 -> 0 | Z22: ='Construction Budget'!H53*10000000 -> 39000499 | AA22: ='Construction Budget'!H54*10000000 -> 15713000 | AC22: =COUNTIF('Booking Jun'!B:B,C22)-COUNTIF('Cancel Jun'!A:A,C22) -> 0 | AG22: =SUMIF('Booking Jun'!B:B,'FY Target Sheet'!C22,'Booking Jun'!K:K)-SUMIF('Cancel Jun'!A:A,'FY Target Sheet'!C22,'Cancel Jun'!F:F) -> 0 | AI22: =SUMIF('Booking Jun'!B:B,C22,'Booking Jun'!L:L)-SUMIF('Cancel Jun'!A:A,'FY Target Sheet'!C22,'Cancel Jun'!G:G) -> 0 | AK22: =SUMIF('Coll Jun'!A:A,C22,'Coll Jun'!J:J)*100000 -> 0 | AL22: ='Construction Budget'!I53*10000000 -> 36000461 | AM22: ='Construction Budget'!I54*10000000 -> 31500000 | AS22: ='Construction Budget'!J53*10000000 -> 51000653 | AY22: ='Construction Budget'!K53*10000000 -> 46500595 | BE22: ='Construction Budget'!L53*10000000 -> 49500634 | BK22: ='Construction Budget'!M53*10000000 -> 54000691 | BQ22: ='Construction Budget'!N53*10000000 -> 57000730 | BW22: ='Construction Budget'!O53*10000000 -> 51000653 | CC22: ='Construction Budget'!P53*10000000 -> 55500710 | CI22: ='Construction Budget'!Q53*10000000 -> 63000806 | CO22: ='Construction Budget'!R53*10000000 -> 64500826
A23: On Going | B23: COMMERCIAL | C23: NYATI UNITREE EXTENSION | E23: =COUNTIF('Booking Apr'!B:B,'FY Target Sheet'!C23)-COUNTIF('Cancel Apr'!A:A,'FY Target Sheet'!C23) -> 0 | M23: =SUMIF('Coll Apr'!A:A,C23,'Coll Apr'!J:J) -> 0 | N23: ='Construction Budget'!G56*10000000 -> 11000141 | O23: ='Construction Budget'!G57*10000000 -> 7900000 | Q23: =COUNTIF('Booking May'!B:B,'FY Target Sheet'!C23)-COUNTIF('Cancel May'!A:A,'FY Target Sheet'!C23) -> 0 | U23: =SUMIF('Booking May'!B:B,'FY Target Sheet'!C23,'Booking May'!K:K)-SUMIF('Cancel May'!A:A,'FY Target Sheet'!C23,'Cancel May'!F:F) -> 0 | W23: =SUMIF('Booking May'!B:B,C23,'Booking May'!L:L)-SUMIF('Cancel May'!A:A,'FY Target Sheet'!C23,'Cancel May'!G:G) -> 0 | Y23: =SUMIF('Coll May'!A:A,C23,'Coll May'!J:J)*100000 -> 0 | Z23: ='Construction Budget'!H56*10000000 -> 12500160 | AA23: ='Construction Budget'!H57*10000000 -> 9800000 | AC23: =COUNTIF('Booking Jun'!B:B,C23)-COUNTIF('Cancel Jun'!A:A,C23) -> 0 | AG23: =SUMIF('Booking Jun'!B:B,'FY Target Sheet'!C23,'Booking Jun'!K:K)-SUMIF('Cancel Jun'!A:A,'FY Target Sheet'!C23,'Cancel Jun'!F:F) -> 0 | AI23: =SUMIF('Booking Jun'!B:B,C23,'Booking Jun'!L:L)-SUMIF('Cancel Jun'!A:A,'FY Target Sheet'!C23,'Cancel Jun'!G:G) -> 0 | AK23: =SUMIF('Coll Jun'!A:A,C23,'Coll Jun'!J:J)*100000 -> 0 | AL23: ='Construction Budget'!I56*10000000 -> 11500147 | AM23: ='Construction Budget'!I57*10000000 -> 13000000 | AS23: ='Construction Budget'!J56*10000000 -> 17000218 | AY23: ='Construction Budget'!K56*10000000 -> 18000230 | BE23: ='Construction Budget'!L56*10000000 -> 20500262 | BK23: ='Construction Budget'!M56*10000000 -> 18000230 | BQ23: ='Construction Budget'!N56*10000000 -> 19000243 | BW23: ='Construction Budget'!O56*10000000 -> 18500237 | CC23: ='Construction Budget'!P56*10000000 -> 18000230 | CI23: ='Construction Budget'!Q56*10000000 -> 22000282 | CO23: ='Construction Budget'!R56*10000000 -> 14000179
C24: Old Projects | E24: =COUNTIF('Booking Apr'!B:B,'FY Target Sheet'!C24)-COUNTIF('Cancel Apr'!A:A,'FY Target Sheet'!C24) -> 0 | L24: 38961500 | M24: =SUMIF('Coll Apr'!A:A,C24,'Coll Apr'!J:J) -> 0 | Q24: =COUNTIF('Booking May'!B:B,'FY Target Sheet'!C24)-COUNTIF('Cancel May'!A:A,'FY Target Sheet'!C24) -> 0 | U24: =SUMIF('Booking May'!B:B,'FY Target Sheet'!C24,'Booking May'!K:K)-SUMIF('Cancel May'!A:A,'FY Target Sheet'!C24,'Cancel May'!F:F) -> 0 | W24: =SUMIF('Booking May'!B:B,C24,'Booking May'!L:L)-SUMIF('Cancel May'!A:A,'FY Target Sheet'!C24,'Cancel May'!G:G) -> 0 | X24: 32618500 | Y24: =SUMIF('Coll May'!A:A,C24,'Coll May'!J:J)*100000 -> 0 | AC24: =COUNTIF('Booking Jun'!B:B,C24)-COUNTIF('Cancel Jun'!A:A,C24) -> 0 | AG24: =SUMIF('Booking Jun'!B:B,'FY Target Sheet'!C24,'Booking Jun'!K:K)-SUMIF('Cancel Jun'!A:A,'FY Target Sheet'!C24,'Cancel Jun'!F:F) -> 0 | AI24: =SUMIF('Booking Jun'!B:B,C24,'Booking Jun'!L:L)-SUMIF('Cancel Jun'!A:A,'FY Target Sheet'!C24,'Cancel Jun'!G:G) -> 0 | AJ24: 3611000 | AK24: =SUMIF('Coll Jun'!A:A,C24,'Coll Jun'!J:J)*100000 -> 0 | AR24: 0 | AX24: 0 | BD24: 0 | BJ24: 0 | BP24: 0 | BV24: 0 | CB24: 0 | CH24: 0 | CN24: 0
C25: TOTAL | D25: =SUM(D2:D24) -> 84 | E25: =SUM(E2:E24) -> 32 | F25: =J25/H25 -> 7970.7737 | G25: =K25/I25 -> 8863.4067 | H25: =SUM(H2:H24) -> 134758.8 | I25: =SUM(I2:I24) -> 60205 | J25: =SUM(J2:J24) -> 1074131905 | K25: =SUM(K2:K24) -> 533621403 | L25: =SUM(L2:L24) -> 9.119392e+08 | M25: =SUM(M2:M24) -> 729065000 | N25: =SUM(N2:N24) -> 5.4755231e+08 | O25: =SUM(O2:O24) -> 2.8759978e+08 | ... Q25: =SUM(Q2:Q24) -> 56 | R25: =V25/T25 -> 8312.9096 | S25: =W25/U25 -> 8867.3875 | T25: =SUM(T2:T24) -> 127998.4 | U25: =SUM(U2:U24) -> 93504 | V25: =SUM(V2:V24) -> 1064039125 | W25: =SUM(W2:W24) -> 829136199 | X25: =SUM(X2:X24) -> 1.0907399e+09 | Y25: =SUM(Y2:Y24) -> 715691000 | Z25: =SUM(Z2:Z24) -> 5.9673776e+08 | AA25: =SUM(AA2:AA24) -> 3.1536356e+08 | ... AC25: =SUM(AC2:AC24) -> 71 | AD25: =AH25/AF25 -> 8128.9278 | AF25: =SUM(AF2:AF24) -> 132984.6 | AH25: =SUM(AH2:AH24) -> 1081022210 | AJ25: =SUM(AJ2:AJ24) -> 1.0423814e+09 | AL25: =SUM(AL2:AL24) -> 6.7652433e+08 | AM25: =SUM(AM2:AM24) -> 5.7267583e+08 | AN25: =SUM(AN2:AN24) -> 93 | AO25: =AQ25/AP25 -> 8587.8448 | AP25: =SUM(AP2:AP24) -> 144407.4 | AQ25: =SUM(AQ2:AQ24) -> 1240148340 | AR25: =SUM(AR2:AR24) -> 1.1037477e+09 | AS25: =SUM(AS2:AS24) -> 7.8598812e+08 | AT25: =SUM(AT2:AT24) -> 104 | AU25: =AW25/AV25 -> 8252.0193 | AV25: =SUM(AV2:AV24) -> 161399.26 | AW25: =SUM(AW2:AW24) -> 1331869804 | AX25: =SUM(AX2:AX24) -> 1.1938911e+09 | AY25: =SUM(AY2:AY24) -> 8.8451083e+08 | AZ25: =SUM(AZ2:AZ24) -> 97 | BA25: =BC25/BB25 -> 8026.2035 | BB25: =SUM(BB2:BB24) -> 160385.26 | BC25: =SUM(BC2:BC24) -> 1287284729 | BD25: =SUM(BD2:BD24) -> 1.3612205e+09 | BE25: =SUM(BE2:BE24) -> 8.968719e+08 | BF25: =SUM(BF2:BF24) -> 95 | BG25: =BI25/BH25 -> 8709.6559 | BH25: =SUM(BH2:BH24) -> 168405.18 | BI25: =SUM(BI2:BI24) -> 1466751176 | BJ25: =SUM(BJ2:BJ24) -> 1.5501065e+09 | BK25: =SUM(BK2:BK24) -> 9.3794382e+08 | BL25: =SUM(BL2:BL24) -> 93 | BM25: =BO25/BN25 -> 8726.4401 | BN25: =SUM(BN2:BN24) -> 163431.12 | BO25: =SUM(BO2:BO24) -> 1426171884 | BP25: =SUM(BP2:BP24) -> 1.5461298e+09 | BQ25: =SUM(BQ2:BQ24) -> 8.8602727e+08 | BR25: =SUM(BR2:BR24) -> 96 | BS25: =BU25/BT25 -> 8788.9789 | BT25: =SUM(BT2:BT24) -> 157445.4 | BU25: =SUM(BU2:BU24) -> 1383784300 | BV25: =SUM(BV2:BV24) -> 1.7058273e+09 | BW25: =SUM(BW2:BW24) -> 8.400549e+08 | BX25: =SUM(BX2:BX24) -> 92 | BY25: =CA25/BZ25 -> 9174.9472 | BZ25: =SUM(BZ2:BZ24) -> 155834.12 | CA25: =SUM(CA2:CA24) -> 1429769820 | CB25: =SUM(CB2:CB24) -> 1.9226846e+09 | CC25: =SUM(CC2:CC24) -> 7.4686982e+08 | CD25: =SUM(CD2:CD24) -> 90 | CE25: =CG25/CF25 -> 8403.4618 | CF25: =SUM(CF2:CF24) -> 161280.46 | CG25: =SUM(CG2:CG24) -> 1355314185 | CH25: =SUM(CH2:CH24) -> 1.9762372e+09 | CI25: =SUM(CI2:CI24) -> 8.2892046e+08 | CJ25: =SUM(CJ2:CJ24) -> 93 | CK25: =CM25/CL25 -> 9020.2604 | CL25: =SUM(CL2:CL24) -> 153000.26 | CM25: =SUM(CM2:CM24) -> 1380102185 | CN25: =SUM(CN2:CN24) -> 2.1253085e+09 | CO25: =SUM(CO2:CO24) -> 8.1211933e+08
E26: =E25/D25 -> 0.38095238 | G26: =G25/F25 -> 1.1119882 | I26: =I25/H25 -> 0.44676118 | K26: =K25/J25 -> 0.49679318 | M26: =M25/L25 -> 0.79946667 | Q26: =Q25/P25 -> 0.73684211 | S26: =S25/R25 -> 1.0667008 | U26: =U25/T25 -> 0.73050913 | W26: =W25/V25 -> 0.77923469 | Y26: =Y25/X25 -> 0.65615183 | AC26: =AC25/AB25 -> 0.8875 | AE26: =AE25/AD25 -> 0 | AG26: =AG25/AF25 -> 0 | AI26: =AI25/AH25 -> 0 | AK26: =AK25/AJ25 -> 0
A27: Status | B27: Type | C27: Projects | D27: Apr-26 Units Target | E27: Apr-26 Units Actual | F27: Apr-26 Rate Target | G27: Apr-26 Rate Actual | H27: Apr-26 Area Target | I27: Apr-26 Area Actual | J27: Apr-26 Sales Value Target | K27: Apr-26 Sales Value Actual | L27: Apr-26 Collection Target | M27: Apr-26 Collection Actual | N27: Apr-26 Construction Target | O27: Apr-26 Construction Actual | P27: May-26 Units Target | Q27: May-26 Units Actual | R27: May-26 Rate Target | S27: May-26 Rate Actual | T27: May-26 Area Target | U27: May-26 Area Actual | V27: May-26 Sales Value Target | W27: May-26 Sales Value Actual | X27: May-26 Collection Target | Y27: May-26 Collection Target | Z27: May-26 Construction Target | AA27: May-26 Construction Actual | AB27: Jun-26 Units Target | AC27: May-26 Units Actual | AD27: Jun-26 Rate Target | AF27: Jun-26 Area Target | AH27: Jun-26 Sales Value Target | AJ27: Jun-26 Collection Target | AL27: Jun-26 Construction Target | AN27: Jul-26 Units Target | AO27: Jul-26 Rate Target | AP27: Jul-26 Area Target | AQ27: Jul-26 Sales Value Target | AR27: Jul-26 Collection Target | AS27: Jul-26 Construction Target | AT27: Aug-26 Units Target | AU27: Aug-26 Rate Target | AV27: Aug-26 Area Target | AW27: Aug-26 Sales Value Target | AX27: Aug-26 Collection Target | AY27: Aug-26 Construction Target | AZ27: Sep-26 Units Target | BA27: Sep-26 Rate Target | BB27: Sep-26 Area Target | BC27: Sep-26 Sales Value Target | BD27: Sep-26 Collection Target | BE27: Sep-26 Construction Target | BF27: Oct-26 Units Target | BG27: Oct-26 Rate Target | BH27: Oct-26 Area Target | BI27: Oct-26 Sales Value Target | BJ27: Oct-26 Collection Target | BK27: Oct-26 Construction Target | BL27: Nov-26 Units Target | BM27: Nov-26 Rate Target | BN27: Nov-26 Area Target | BO27: Nov-26 Sales Value Target | BP27: Nov-26 Collection Target | BQ27: Nov-26 Construction Target | BR27: Dec-26 Units Target | BS27: Dec-26 Rate Target | BT27: Dec-26 Area Target | BU27: Dec-26 Sales Value Target | BV27: Dec-26 Collection Target | BW27: Dec-26 Construction Target | BX27: Jan-27 Units Target | BY27: Jan-27 Rate Target | BZ27: Jan-27 Area Target | CA27: Jan-27 Sales Value Target | CB27: Jan-27 Collection Target | CC27: Jan-27 Construction Target | CD27: Feb-27 Units Target | CE27: Feb-27 Rate Target | CF27: Feb-27 Area Target | CG27: Feb-27 Sales Value Target | CH27: Feb-27 Collection Target | CI27: Feb-27 Construction Target | CJ27: Mar-27 Units Target | CK27: Mar-27 Rate Target | CL27: Mar-27 Area Target | CM27: Mar-27 Sales Value Target | CN27: Mar-27 Collection Target | CO27: Mar-27 Construction Target
A28: Upcoming | B28: RESIDENTIAL | C28: NYATI ELARIS | D28: 0 | E28: =COUNTIF('Booking Apr'!B:B,'FY Target Sheet'!C28)-COUNTIF('Cancel Apr'!A:A,'FY Target Sheet'!C28) -> 0 | F28: 0 | G28: =(K28/I28) -> #DIV/0! | H28: 0 | I28: =SUMIF('Booking Apr'!B:B,'FY Target Sheet'!C28,'Booking Apr'!K:K)-SUMIF('Cancel Apr'!A:A,'FY Target Sheet'!C28,'Cancel Apr'!F:F) -> 0 | J28: 0 | K28: =SUMIF('Booking Apr'!B:B,C28,'Booking Apr'!L:L)-SUMIF('Cancel Apr'!A:A,'FY Target Sheet'!C28,'Cancel Apr'!G:G) -> 0 | M28: =SUMIF('Coll Apr'!A:A,C28,'Coll Apr'!J:J)*100000 -> 0 | P28: 0 | Q28: =COUNTIF('Booking May'!B:B,'FY Target Sheet'!C28)-COUNTIF('Cancel May'!A:A,'FY Target Sheet'!C28) -> 0 | R28: 0 | T28: 0 | U28: =SUMIF('Booking May'!B:B,'FY Target Sheet'!C28,'Booking May'!K:K)-SUMIF('Cancel May'!A:A,'FY Target Sheet'!C28,'Cancel May'!F:F) -> 0 | V28: 0 | W28: =SUMIF('Booking May'!B:B,C28,'Booking May'!L:L)-SUMIF('Cancel May'!A:A,'FY Target Sheet'!C28,'Cancel May'!G:G) -> 0 | Y28: =SUMIF('Coll May'!A:A,C28,'Coll May'!J:J)*100000 -> 0 | AB28: 0 | AC28: =COUNTIF('Booking Jun'!B:B,C28)-COUNTIF('Cancel Jun'!A:A,C28) -> 0 | AD28: 0 | AF28: 0 | AG28: =SUMIF('Booking Jun'!B:B,'FY Target Sheet'!C28,'Booking Jun'!K:K)-SUMIF('Cancel Jun'!A:A,'FY Target Sheet'!C28,'Cancel Jun'!F:F) -> 0 | AH28: 0 | AK28: =SUMIF('Coll Jun'!A:A,C28,'Coll Jun'!J:J)*100000 -> 0 | AN28: 0 | AO28: 0 | AP28: 0 | AQ28: 0 | AT28: 0 | AU28: 0 | AV28: 0 | AW28: 0 | AZ28: 0 | BA28: 0 | BB28: 0 | BC28: 0 | BF28: 203 | BG28: 7752.8224 | BH28: 369281 | BI28: 2862970000 | BL28: 103 | BM28: 7803.273 | BN28: 188881 | BO28: 1473890000 | BR28: 53 | BS28: 8080.4816 | BT28: 98681 | BU28: 797390000 | BX28: 52 | BY28: 8117.9711 | BZ28: 95854 | CA28: 778140000 | CD28: 52 | CE28: 8117.9711 | CF28: 95854 | CG28: 778140000 | CJ28: 52 | CK28: 8117.9711 | CL28: 95854 | CM28: 778140000
A29: Upcoming | B29: RESIDENTIAL | C29: NYATI EKATVA | D29: 0 | E29: =COUNTIF('Booking Apr'!B:B,'FY Target Sheet'!C29)-COUNTIF('Cancel Apr'!A:A,'FY Target Sheet'!C29) -> 0 | F29: 0 | G29: =(K29/I29) -> #DIV/0! | H29: 0 | I29: =SUMIF('Booking Apr'!B:B,'FY Target Sheet'!C29,'Booking Apr'!K:K)-SUMIF('Cancel Apr'!A:A,'FY Target Sheet'!C29,'Cancel Apr'!F:F) -> 0 | J29: 0 | K29: =SUMIF('Booking Apr'!B:B,C29,'Booking Apr'!L:L)-SUMIF('Cancel Apr'!A:A,'FY Target Sheet'!C29,'Cancel Apr'!G:G) -> 0 | M29: =SUMIF('Coll Apr'!A:A,C29,'Coll Apr'!J:J)*100000 -> 0 | P29: 0 | Q29: =COUNTIF('Booking May'!B:B,'FY Target Sheet'!C29)-COUNTIF('Cancel May'!A:A,'FY Target Sheet'!C29) -> 0 | R29: 0 | T29: 0 | U29: =SUMIF('Booking May'!B:B,'FY Target Sheet'!C29,'Booking May'!K:K)-SUMIF('Cancel May'!A:A,'FY Target Sheet'!C29,'Cancel May'!F:F) -> 0 | V29: 0 | W29: =SUMIF('Booking May'!B:B,C29,'Booking May'!L:L)-SUMIF('Cancel May'!A:A,'FY Target Sheet'!C29,'Cancel May'!G:G) -> 0 | Y29: =SUMIF('Coll May'!A:A,C29,'Coll May'!J:J)*100000 -> 0 | AB29: 0 | AC29: =COUNTIF('Booking Jun'!B:B,C29)-COUNTIF('Cancel Jun'!A:A,C29) -> 0 | AD29: 0 | AF29: 0 | AG29: =SUMIF('Booking Jun'!B:B,'FY Target Sheet'!C29,'Booking Jun'!K:K)-SUMIF('Cancel Jun'!A:A,'FY Target Sheet'!C29,'Cancel Jun'!F:F) -> 0 | AH29: 0 | AK29: =SUMIF('Coll Jun'!A:A,C29,'Coll Jun'!J:J)*100000 -> 0 | AN29: 0 | AO29: 0 | AP29: 0 | AQ29: 0 | AT29: 50 | AU29: 11500 | AV29: 79400 | AW29: 913100000 | AZ29: 50 | BA29: 11500 | BB29: 79400 | BC29: 913100000 | BF29: 50 | BG29: 11600 | BH29: 79400 | BI29: 921040000 | BL29: 50 | BM29: 11600 | BN29: 79400 | BO29: 921040000 | BR29: 10 | BS29: 11700 | BT29: 15880 | BU29: 185796000 | BX29: 10 | BY29: 11700 | BZ29: 15880 | CA29: 185796000 | CD29: 10 | CE29: 11800 | CF29: 15880 | CG29: 187384000 | CJ29: 10 | CK29: 11800 | CL29: 15880 | CM29: 187384000
A30: Upcoming | B30: RESIDENTIAL | C30: REDEV PATRAKARNAGAR | D30: 0 | E30: =COUNTIF('Booking Apr'!B:B,'FY Target Sheet'!C30)-COUNTIF('Cancel Apr'!A:A,'FY Target Sheet'!C30) -> 0 | F30: 0 | G30: =(K30/I30) -> #DIV/0! | H30: 0 | I30: =SUMIF('Booking Apr'!B:B,'FY Target Sheet'!C30,'Booking Apr'!K:K)-SUMIF('Cancel Apr'!A:A,'FY Target Sheet'!C30,'Cancel Apr'!F:F) -> 0 | J30: 0 | K30: =SUMIF('Booking Apr'!B:B,C30,'Booking Apr'!L:L)-SUMIF('Cancel Apr'!A:A,'FY Target Sheet'!C30,'Cancel Apr'!G:G) -> 0 | M30: =SUMIF('Coll Apr'!A:A,C30,'Coll Apr'!J:J)*100000 -> 0 | P30: 8 | Q30: =COUNTIF('Booking May'!B:B,'FY Target Sheet'!C30)-COUNTIF('Cancel May'!A:A,'FY Target Sheet'!C30) -> 0 | R30: 14219.078 | T30: 26995 | U30: =SUMIF('Booking May'!B:B,'FY Target Sheet'!C30,'Booking May'!K:K)-SUMIF('Cancel May'!A:A,'FY Target Sheet'!C30,'Cancel May'!F:F) -> 0 | V30: 383844000 | W30: =SUMIF('Booking May'!B:B,C30,'Booking May'!L:L)-SUMIF('Cancel May'!A:A,'FY Target Sheet'!C30,'Cancel May'!G:G) -> 0 | Y30: =SUMIF('Coll May'!A:A,C30,'Coll May'!J:J)*100000 -> 0 | AB30: 8 | AC30: =COUNTIF('Booking Jun'!B:B,C30)-COUNTIF('Cancel Jun'!A:A,C30) -> 0 | AD30: 14219.078 | AF30: 26995 | AG30: =SUMIF('Booking Jun'!B:B,'FY Target Sheet'!C30,'Booking Jun'!K:K)-SUMIF('Cancel Jun'!A:A,'FY Target Sheet'!C30,'Cancel Jun'!F:F) -> 0 | AH30: 383844000 | AK30: =SUMIF('Coll Jun'!A:A,C30,'Coll Jun'!J:J)*100000 -> 0 | AN30: 8 | AO30: 14716.501 | AP30: 26956 | AQ30: 396698000 | AT30: 2 | AU30: 15425.364 | AV30: 6391 | AW30: 98583500 | AZ30: 1 | BA30: 14500 | BB30: 3434 | BC30: 49793000 | BF30: 1 | BG30: 15000 | BH30: 3434 | BI30: 51510000 | BL30: 1 | BM30: 15000 | BN30: 3434 | BO30: 51510000 | BR30: 1 | BS30: 15000 | BT30: 3434 | BU30: 51510000 | BX30: 2 | BY30: 15000 | BZ30: 6868 | CA30: 103020000 | CD30: 2 | CE30: 15000 | CF30: 6868 | CG30: 103020000 | CJ30: 2 | CK30: 15000 | CL30: 6868 | CM30: 103020000
A31: New | B31: RESIDENTIAL | C31: NYATI ETHOS | D31: 2 | E31: =COUNTIF('Booking Apr'!B:B,'FY Target Sheet'!C31)-COUNTIF('Cancel Apr'!A:A,'FY Target Sheet'!C31) -> 0 | F31: 6250 | G31: =(K31/I31) -> #DIV/0! | H31: 2264 | I31: =SUMIF('Booking Apr'!B:B,'FY Target Sheet'!C31,'Booking Apr'!K:K)-SUMIF('Cancel Apr'!A:A,'FY Target Sheet'!C31,'Cancel Apr'!F:F) -> 0 | J31: 14150000 | K31: =SUMIF('Booking Apr'!B:B,C31,'Booking Apr'!L:L)-SUMIF('Cancel Apr'!A:A,'FY Target Sheet'!C31,'Cancel Apr'!G:G) -> 0 | M31: =SUMIF('Coll Apr'!A:A,C31,'Coll Apr'!J:J)*100000 -> 0 | N31: ='Construction Budget'!G50*10000000 -> 4531029.5 | P31: 1 | Q31: =COUNTIF('Booking May'!B:B,'FY Target Sheet'!C31)-COUNTIF('Cancel May'!A:A,'FY Target Sheet'!C31) -> 0 | R31: 6250 | T31: 1271 | U31: =SUMIF('Booking May'!B:B,'FY Target Sheet'!C31,'Booking May'!K:K)-SUMIF('Cancel May'!A:A,'FY Target Sheet'!C31,'Cancel May'!F:F) -> 0 | V31: 7943750 | W31: =SUMIF('Booking May'!B:B,C31,'Booking May'!L:L)-SUMIF('Cancel May'!A:A,'FY Target Sheet'!C31,'Cancel May'!G:G) -> 0 | Y31: =SUMIF('Coll May'!A:A,C31,'Coll May'!J:J)*100000 -> 0 | Z31: ='Construction Budget'!H50*10000000 -> 5389710.9 | AA31: ='Construction Budget'!H51*10000000 -> 796009.76 | AB31: 1 | AC31: =COUNTIF('Booking Jun'!B:B,C31)-COUNTIF('Cancel Jun'!A:A,C31) -> 0 | AD31: 6250 | AF31: 1271 | AG31: =SUMIF('Booking Jun'!B:B,'FY Target Sheet'!C31,'Booking Jun'!K:K)-SUMIF('Cancel Jun'!A:A,'FY Target Sheet'!C31,'Cancel Jun'!F:F) -> 0 | AH31: 7943750 | AK31: =SUMIF('Coll Jun'!A:A,C31,'Coll Jun'!J:J)*100000 -> 0 | AL31: ='Construction Budget'!I50*10000000 -> 7447306 | AM31: ='Construction Budget'!I51*10000000 -> 2372721.4 | AN31: 2 | AO31: 6250 | AP31: 2264 | AQ31: 14150000 | AS31: ='Construction Budget'!J50*10000000 -> 5972966.2 | AT31: 4 | AU31: 6250 | AV31: 4528 | AW31: 28300000 | AY31: ='Construction Budget'!K50*10000000 -> 7031723.7 | AZ31: 4 | BA31: 6500 | BB31: 4528 | BC31: 29432000 | BE31: ='Construction Budget'!L50*10000000 -> 7488607.1 | BF31: 4 | BG31: 6500 | BH31: 4528 | BI31: 29432000 | BK31: ='Construction Budget'!M50*10000000 -> 4667379.6 | BL31: 2 | BM31: 6500 | BN31: 2264 | BO31: 14716000 | BQ31: ='Construction Budget'!N50*10000000 -> 5894375.9 | BR31: 3 | BS31: 6700 | BT31: 3396 | BU31: 22753200 | BW31: ='Construction Budget'!O50*10000000 -> 3021303.6 | BX31: 3 | BY31: 6700 | BZ31: 3396 | CA31: 22753200 | CC31: ='Construction Budget'!P50*10000000 -> 3154516.2 | CD31: 2 | CE31: 6700 | CF31: 2264 | CG31: 15168800 | CI31: ='Construction Budget'!Q50*10000000 -> 3028504.2 | CJ31: 2 | CK31: 6700 | CL31: 2264 | CM31: 15168800 | CO31: ='Construction Budget'!R50*10000000 -> 2373345
C32: TOTAL | D32: =SUM(D28:D31) -> 2 | E32: =SUM(E28:E31) -> 0 | F32: =J32/H32 -> 6250 | H32: =SUM(H28:H31) -> 2264 | J32: =SUM(J28:J31) -> 14150000 | L32: =SUM(L28:L31) -> 0 | N32: =SUM(N28:N31) -> 4531029.5 | O32: =SUM(O28:O31) -> 0 | P32: =SUM(P28:P31) -> 9 | R32: =V32/T32 -> 13860.743 | T32: =SUM(T28:T31) -> 28266 | V32: =SUM(V28:V31) -> 391787750 | X32: =SUM(X28:X31) -> 0 | Z32: =SUM(Z28:Z31) -> 5389710.9 | AA32: =SUM(AA28:AA31) -> 796009.76 | AB32: =SUM(AB28:AB31) -> 9 | AC32: =SUM(AC28:AC31) -> 0 | AD32: =AH32/AF32 -> 13860.743 | AF32: =SUM(AF28:AF31) -> 28266 | AH32: =SUM(AH28:AH31) -> 391787750 | AJ32: =SUM(AJ28:AJ31) -> 0 | AL32: =SUM(AL28:AL31) -> 7447306 | AM32: =SUM(AM28:AM31) -> 2372721.4 | AN32: =SUM(AN28:AN31) -> 10 | AO32: =AQ32/AP32 -> 14060.507 | AP32: =SUM(AP28:AP31) -> 29220 | AQ32: =SUM(AQ28:AQ31) -> 410848000 | AR32: =SUM(AR28:AR31) -> 0 | AS32: =SUM(AS28:AS31) -> 5972966.2 | AT32: =SUM(AT28:AT31) -> 56 | AU32: =AW32/AV32 -> 11514.56 | AV32: =SUM(AV28:AV31) -> 90319 | AW32: =SUM(AW28:AW31) -> 1039983500 | AX32: =SUM(AX28:AX31) -> 0 | AY32: =SUM(AY28:AY31) -> 7031723.7 | AZ32: =SUM(AZ28:AZ31) -> 55 | BA32: =BC32/BB32 -> 11358.772 | BB32: =SUM(BB28:BB31) -> 87362 | BC32: =SUM(BC28:BC31) -> 992325000 | BD32: =SUM(BD28:BD31) -> 0 | BE32: =SUM(BE28:BE31) -> 7488607.1 | BF32: =SUM(BF28:BF31) -> 258 | BG32: =BI32/BH32 -> 8463.8372 | BH32: =SUM(BH28:BH31) -> 456643 | BI32: =SUM(BI28:BI31) -> 3864952000 | BJ32: =SUM(BJ28:BJ31) -> 0 | BK32: =SUM(BK28:BK31) -> 4667379.6 | BL32: =SUM(BL28:BL31) -> 156 | BM32: =BO32/BN32 -> 8983.0096 | BN32: =SUM(BN28:BN31) -> 273979 | BO32: =SUM(BO28:BO31) -> 2461156000 | BP32: =SUM(BP28:BP31) -> 0 | BQ32: =SUM(BQ28:BQ31) -> 5894375.9 | BR32: =SUM(BR28:BR31) -> 67 | BS32: =BU32/BT32 -> 8711.1005 | BT32: =SUM(BT28:BT31) -> 121391 | BU32: =SUM(BU28:BU31) -> 1057449200 | BV32: =SUM(BV28:BV31) -> 0 | BW32: =SUM(BW28:BW31) -> 3021303.6 | BX32: =SUM(BX28:BX31) -> 67 | BY32: =CA32/BZ32 -> 8932.1891 | BZ32: =SUM(BZ28:BZ31) -> 121998 | CA32: =SUM(CA28:CA31) -> 1089709200 | CB32: =SUM(CB28:CB31) -> 0 | CC32: =SUM(CC28:CC31) -> 3154516.2 | CD32: =SUM(CD28:CD31) -> 66 | CE32: =CG32/CF32 -> 8966.2337 | CF32: =SUM(CF28:CF31) -> 120866 | CG32: =SUM(CG28:CG31) -> 1083712800 | CH32: =SUM(CH28:CH31) -> 0 | CI32: =SUM(CI28:CI31) -> 3028504.2 | CJ32: =SUM(CJ28:CJ31) -> 66 | CK32: =CM32/CL32 -> 8966.2337 | CL32: =SUM(CL28:CL31) -> 120866 | CM32: =SUM(CM28:CM31) -> 1083712800 | CN32: =SUM(CN28:CN31) -> 0 | CO32: =SUM(CO28:CO31) -> 2373345
C34: GRAND TOTAL | D34: =D32+D25 -> 86 | E34: =E32+E25 -> 32 | H34: =H32+H25 -> 137022.8 | J34: =J32+J25 -> 1088281905 | L34: =L32+L25 -> 9.119392e+08 | N34: =N32+N25 -> 5.5208334e+08 | O34: =O32+O25 -> 2.8759978e+08 | Z34: =Z32+Z25 -> 6.0212747e+08 | AA34: =AA32+AA25 -> 3.1615957e+08 | AB34: =AB32+AB25 -> 89 | AC34: =AC32+AC25 -> 71 | AL34: =AL32+AL25 -> 6.8397163e+08 | AM34: =AM32+AM25 -> 5.7504855e+08 | AS34: =AS32+AS25 -> 7.9196108e+08 | AY34: =AY32+AY25 -> 8.9154256e+08 | BE34: =BE32+BE25 -> 9.0436051e+08 | BK34: =BK32+BK25 -> 9.426112e+08 | BQ34: =BQ32+BQ25 -> 8.9192165e+08 | BW34: =BW32+BW25 -> 8.430762e+08 | CC34: =CC32+CC25 -> 7.5002433e+08 | CI34: =CI32+CI25 -> 8.3194896e+08 | CO34: =CO32+CO25 -> 8.1449267e+08

Sheet Construction Budget
A1: TYPE | B1: STATUS | C1: Projects | G1: 46113 | H1: 46143 | I1: 46174 | J1: 46204 | K1: 46235 | L1: 46266 | M1: 46296 | N1: 46327 | O1: 46357 | P1: 46388 | Q1: 46419 | R1: 46447
F2: Planned | G2: =G5+G8+G11+G14+G17+G20+G23+G26+G29+G32+G35+G38+G41+G44+G47+G50+G53+G56 -> 55.208334 | H2: =H5+H8+H11+H14+H17+H20+H23+H26+H29+H32+H35+H38+H41+H44+H47+H50+H53+H56 -> 60.212747 | I2: =I5+I8+I11+I14+I17+I20+I23+I26+I29+I32+I35+I38+I41+I44+I47+I50+I53+I56 -> 68.397163 | J2: =J5+J8+J11+J14+J17+J20+J23+J26+J29+J32+J35+J38+J41+J44+J47+J50+J53+J56 -> 79.196108 | K2: =K5+K8+K11+K14+K17+K20+K23+K26+K29+K32+K35+K38+K41+K44+K47+K50+K53+K56 -> 89.154256 | L2: =L5+L8+L11+L14+L17+L20+L23+L26+L29+L32+L35+L38+L41+L44+L47+L50+L53+L56 -> 90.436051 | M2: =M5+M8+M11+M14+M17+M20+M23+M26+M29+M32+M35+M38+M41+M44+M47+M50+M53+M56 -> 94.26112 | N2: =N5+N8+N11+N14+N17+N20+N23+N26+N29+N32+N35+N38+N41+N44+N47+N50+N53+N56 -> 89.192165 | ... R2: =R5+R8+R11+R14+R17+R20+R23+R26+R29+R32+R35+R38+R41+R44+R47+R50+R53+R56 -> 81.449267
F3: Actual | G3: =G6+G9+G12+G15+G18+G21+G24+G27+G30+G33+G36+G39+G42+G45+G48+G51+G54+G57 -> 29.067666 | H3: =H6+H9+H12+H15+H18+H21+H24+H27+H30+H33+H36+H39+H42+H45+H48+H51+H54+H57 -> 31.615957 | I3: =I6+I9+I12+I15+I18+I21+I24+I27+I30+I33+I36+I39+I42+I45+I48+I51+I54+I57 -> 56.409883 | J3: =J6+J9+J12+J15+J18+J21+J24+J27+J30+J33+J36+J39+J42+J45+J48+J51+J54+J57 -> 0 | K3: =K6+K9+K12+K15+K18+K21+K24+K27+K30+K33+K36+K39+K42+K45+K48+K51+K54+K57 -> 0 | L3: =L6+L9+L12+L15+L18+L21+L24+L27+L30+L33+L36+L39+L42+L45+L48+L51+L54+L57 -> 0 | M3: =M6+M9+M12+M15+M18+M21+M24+M27+M30+M33+M36+M39+M42+M45+M48+M51+M54+M57 -> 0 | N3: =N6+N9+N12+N15+N18+N21+N24+N27+N30+N33+N36+N39+N42+N45+N48+N51+N54+N57 -> 0 | ... R3: =R6+R9+R12+R15+R18+R21+R24+R27+R30+R33+R36+R39+R42+R45+R48+R51+R54+R57 -> 0
F4: Effi. % | G4: =G3/G2 -> 0.52650866 | H4: =H3/H2 -> 0.52507084 | I4: =I3/I2 -> 0.8247401
A5: RESIDENTIAL | B5: Ongoing | C5: Nyati Emerald - I | D5: Sign Off Cost (Cr.) | E5: 449.58 | F5: Planned | G5: 8.2975269 | H5: 8.586803 | I5: 9.3591907 | J5: 12.127371 | K5: 12.061047 | L5: 12.921313 | M5: 12.210436 | N5: 13.026793 | O5: 12.130212 | P5: 10.811711 | Q5: 12.130212 | R5: 11.339112
D6: Actual Cost (Cr.) | E6: =E7*E5 -> 190.26226 | F6: Actual | G6: 2.8323535 | H6: 4.0911773 | I6: 8.1823547
D7: Actual Progress (%) | E7: 0.4232 | F7: Effi. % | G7: =G6/G5 -> 0.34134912 | H7: =H6/H5 -> 0.47644942 | I7: 0.87425878
A8: RESIDENTIAL | B8: Ongoing | C8: Nyati Emerald - II | D8: Sign Off Cost (Cr.) | E8: 48.25 | F8: Planned | G8: 1.56252 | H8: 2.4271144 | I8: 2.291696 | J8: 2.187528 | K8: 2.3021128 | L8: 1.875024 | M8: 2.1666944 | N8: 1.770856 | O8: 1.6041872 | P8: 1.979192 | Q8: 2.1979448 | R8: 2.6354504
D9: Actual Cost (Cr.) | E9: =E10*E8 -> 17.3121 | F9: Actual | G9: 0.24127499 | H9: 0.62731497 | I9: 1.1967239
D10: Actual Progress (%) | E10: 0.3588 | F10: Effi. % | G10: =G9/G8 -> 0.15441402 | H10: =H9/H8 -> 0.25846123 | I10: 0.52220012
A11: RESIDENTIAL | B11: Ongoing | C11: Nyati Emerald - III | D11: Sign Off Cost (Cr.) | E11: 316.44 | F11: Planned | G11: 5.5858996 | H11: 6.0158222 | I11: 8.1148015 | J11: 6.6208722 | K11: 8.835554 | L11: 8.8960644 | M11: 9.4609008 | N11: 9.1003889 | O11: 7.0125891 | P11: 5.2994112 | Q11: 9.6758078 | R11: 5.3830405
D12: Actual Cost (Cr.) | E12: =E13*E11 -> 58.161672 | F12: Actual | G12: 2.4366196 | H12: 1.930309 | I12: 5.0631056
D13: Actual Progress (%) | E13: 0.1838 | F13: Effi. % | G13: =G12/G11 -> 0.43620898 | H13: =H12/H11 -> 0.32087202 | I13: 0.62393463
A14: RESIDENTIAL | B14: Nearing Compleiton | C14: Nyati Equinox - I | D14: Sign Off Cost (Cr.) | E14: 302 | F14: Planned | G14: 5.6000717 | H14: 6.6500851 | I14: 8.050103 | J14: 8.4001075 | K14: 9.1001165 | L14: 7.7000986 | M14: 8.750112 | N14: 8.4001075 | O14: 7.3500941 | P14: 0 | Q14: 0 | R14: 0
D15: Actual Cost (Cr.) | E15: =E16*E14 -> 217.70606 | F15: Actual | G15: 3.7146927 | H15: 7.2783816 | I15: 9.5132373
D16: Actual Progress (%) | E16: 0.720881 | F16: Effi. % | G16: =G15/G14 -> 0.66332949 | H16: =H15/H14 -> 1.0944795 | I16: 1.1817535
A17: RESIDENTIAL | B17: Ongoing | C17: Nyati Equinox - II | D17: Sign Off Cost (Cr.) | E17: 88.4 | F17: Planned | G17: 1.9343368 | H17: 1.4646424 | I17: 0.95405214 | J17: 3.4801443 | K17: 3.5715187 | L17: 3.6746355 | M17: 3.979667 | N17: 3.6560997 | O17: 3.9768326 | P17: 4.6787648 | Q17: 5.7529433 | R17: 2.8768749
D18: Actual Cost (Cr.) | E18: =E19*E17 -> 31.692903 | F18: Actual | G18: 0.67186584 | H18: 1.1757652 | I18: 1.6796846
D19: Actual Progress (%) | E19: 0.358517 | F19: Effi. % | G19: =G18/G17 -> 0.34733654 | H19: =H18/H17 -> 0.80276609 | I19: 1.7605794
A20: RESIDENTIAL | B20: Nearing Compleiton | C20: Nyati Era - III | D20: Sign Off Cost (Cr.) | E20: 102.213 | F20: Planned | G20: 2.2000282 | H20: 3.0000384 | I20: 3.6000461 | J20: 3.4000435 | K20: 4.6000589 | L20: 3.200041 | M20: 0 | N20: 0 | O20: 0 | P20: 0 | Q20: 0 | R20: 0
D21: Actual Cost (Cr.) | E21: =E22*E20 -> 77.004514 | F21: Actual | G21: 3.015285 | H21: 2.5144412 | I21: 4.3951614
D22: Actual Progress (%) | E22: 0.753373 | F22: Effi. % | G22: =G21/G20 -> 1.3705666 | H22: =H21/H20 -> 0.83813633 | I22: 1.2208626
A23: RESIDENTIAL | B23: Newly Started | C23: Nyati Era - IV | D23: Sign Off Cost (Cr.) | E23: 124.306 | F23: Planned | G23: 2.1507854 | H23: 3.2261781 | I23: 3.3460076 | J23: 4.7132926 | K23: 5.2141184 | L23: 5.5428813 | M23: 5.5613166 | N23: 5.5797519 | O23: 4.3200061 | P23: 2.5625072 | Q23: 1.8681108 | R23: 5.9156841
D24: Actual Cost (Cr.) | E24: =E25*E23 -> 14.601604 | F24: Actual | G24: 0.9451 | H24: 0.38 | I24: 1.3798044
D25: Actual Progress (%) | E25: 0.117465 | F25: Effi. % | G25: =G24/G23 -> 0.43942087 | H25: =H24/H23 -> 0.11778643 | I25: 0.41237336
A26: RESIDENTIAL | B26: Completed | C26: Nyati Exuberance-I | D26: Sign Off Cost (Cr.) | E26: 73.21 | F26: Planned | G26: 0 | H26: 0 | I26: 0 | J26: 0 | K26: 0.22000282 | L26: 0.28000358 | M26: 0.3200041 | N26: 0.1800023 | O26: 0.30000384 | P26: 0.26000333 | Q26: 0.24000307 | R26: 0.20000256
D27: Actual Cost (Cr.) | E27: =E28*E26 -> 69.373796 | F27: Actual | G27: 0.26355774 | H27: 0.065889436 | I27: 0.073210476
D28: Actual Progress (%) | E28: 0.9476 | F28: Effi. %
A29: RESIDENTIAL | B29: Ongoing | C29: Nyati Exuberance-IV | D29: Sign Off Cost (Cr.) | E29: 75.49 | F29: Planned | G29: 1.0977574 | H29: 1.1246585 | I29: 1.1246585 | J29: 1.727822 | K29: 1.5828617 | L29: 1.7487718 | M29: 1.8681982 | N29: 1.4820128 | O29: 1.2090612 | P29: 1.0398135 | Q29: 0.83811569 | R29: 0.15646059
D30: Actual Cost (Cr.) | E30: =E31*E29 -> 56.893189 | F30: Actual | G30: 1.6909781 | H30: 1.3814687 | I30: 2.408134
D31: Actual Progress (%) | E31: 0.753652 | F31: Effi. % | G31: =G30/G29 -> 1.5403932 | H31: =H30/H29 -> 1.228345 | I31: 2.1412135
A32: RESIDENTIAL | B32: Ongoing | C32: Nyati Esteban - II | D32: Sign Off Cost (Cr.) | E32: 291.92 | F32: Planned | G32: 5.2383569 | H32: 5.7546945 | I32: 9.7656809 | J32: 7.6170244 | K32: 8.7151238 | L32: 8.4852124 | M32: 11.714737 | N32: 9.4856488 | O32: 8.646835 | P32: 8.7742761 | Q32: 7.6389841 | R32: 8.1647059
D33: Actual Cost (Cr.) | E33: =E34*E32 -> 79.286348 | F33: Actual | G33: 3.7366645 | H33: 3.4447376 | I33: 7.5317143
D34: Actual Progress (%) | E34: 0.271603 | F34: Effi. % | G34: =G33/G32 -> 0.71332758 | H34: =H33/H32 -> 0.59859608 | I34: 0.77124313
A35: RESIDENTIAL | B35: Newly Started | C35: Nyati Esteban - III | D35: Sign Off Cost (Cr.) | E35: 0 | F35: Planned | G35: 0.50469162 | H35: 0.75703743 | I35: 0.75703743 | J35: 0.86919112 | K35: 1.0912554 | L35: 1.2022876 | M35: 1.2022876 | N35: 0.71778364 | O35: 0.63703298 | P35: 0.72908873 | Q35: 1.5422479 | R35: 1.9902122
D36: Actual Cost (Cr.) | E36: =E37*E35 -> 0 | F36: Actual | G36: 0 | H36: 0.0897 | I36: 0
D37: Actual Progress (%) | E37: 0 | F37: Effi. % | G37: =G36/G35 -> 0 | H37: =H36/H35 -> 0.1184882 | I37: 0
A38: LUXURY | B38: Ongoing | C38: Nyati Evoque | D38: Sign Off Cost (Cr.) | E38: 241.615 | F38: Planned | G38: 4.6718535 | H38: 4.9195027 | I38: 5.0016851 | J38: 6.4614159 | K38: 7.3484312 | L38: 7.6996625 | M38: 7.1740277 | N38: 7.825776 | O38: 8.3542749 | P38: 8.8409218 | Q38: 7.5810732 | R38: 9.1224634
D39: Actual Cost (Cr.) | E39: =E40*E38 -> 41.780066 | F39: Actual | G39: 1.1355934 | H39: 2.1503789 | I39: 4.4214897
D40: Actual Progress (%) | E40: 0.17292 | F40: Effi. % | G40: =G39/G38 -> 0.24307127 | H40: =H39/H38 -> 0.43711306 | I40: 0.88400002
A41: LUXURY | B41: Ongoing | C41: Nyati Evania | D41: Sign Off Cost (Cr.) | E41: 421.96 | F41: Planned | G41: 5.000064 | H41: 4.5000576 | I41: 4.2500544 | J41: 6.7500864 | K41: 7.500096 | L41: 9.7501248 | M41: 10.250131 | N41: 9.2501184 | O41: 10.750138 | P41: 10.000128 | Q41: 12.000154 | R41: 10.000128
D42: Actual Cost (Cr.) | E42: 48.54 | F42: Actual | G42: 2 | H42: 1.18 | I42: 2.51
D43: Actual Progress (%) | E43: =E42/E41 -> 0.1150346 | F43: Effi. % | G43: =G42/G41 -> 0.39999488 | H43: =H42/H41 -> 0.26221887 | I43: 0.59058068
A44: LUXURY | B44: Ongoing | C44: Nyati Elenor | D44: Sign Off Cost (Cr.) | E44: 371.29 | F44: Planned | G44: 2.6595671 | H44: 3.1755809 | I44: 3.4033665 | J44: 3.9354441 | K44: 4.4958707 | L44: 4.6022074 | M44: 5.1939085 | N44: 5.5018808 | O44: 5.6187625 | P44: 6.5595318 | Q44: 7.1260038 | R44: 7.7286441
D45: Actual Cost (Cr.) | E45: 25.56 | F45: Actual | G45: 1.28 | H45: 1.33 | I45: 1.73
D46: Actual Progress (%) | E46: =E45/E44 -> 0.068841068 | F46: Effi. % | G46: =G45/G44 -> 0.48128134 | H46: =H45/H44 -> 0.41882101 | I46: 0.50832022
A47: LUXURY | B47: Ongoing | C47: Nyati Emblem | D47: Sign Off Cost (Cr.) | E47: 194.99 | F47: Planned | G47: 3.851716 | H47: 2.9214945 | I47: 2.8839922 | J47: 3.5083818 | K47: 5.362833 | L47: 5.1087723 | M47: 6.7418686 | N47: 5.0254097 | O47: 5.145371 | P47: 5.8015379 | Q47: 5.8003366 | R47: 7.8490543
D48: Actual Cost (Cr.) | E48: =E49*E47 -> 33.25223 | F48: Actual | G48: 1.3259925 | H48: 1.3454924 | I48: 1.6379908
D49: Actual Progress (%) | E49: 0.170533 | F49: Effi. % | G49: =G48/G47 -> 0.3442602 | H49: =H48/H47 -> 0.46054936 | I49: 0.5679595
A50: RESIDENTIAL | B50: Newly Started | C50: Nyati Ethos | D50: Sign Off Cost (Cr.) | E50: 15.3078 | F50: Planned | G50: 0.45310295 | H50: 0.53897109 | I50: 0.7447306 | J50: 0.59729662 | K50: 0.70317237 | L50: 0.74886071 | M50: 0.46673796 | N50: 0.58943759 | O50: 0.30213036 | P50: 0.31545162 | Q50: 0.30285042 | R50: 0.2373345
D51: Actual Cost (Cr.) | E51: =E52*E50 -> 1.0480945 | F51: Actual | G51: 0.30768839 | H51: 0.079600976 | I51: 0.23727214
D52: Actual Progress (%) | E52: 0.068468 | F52: Effi. % | G52: =G51/G50 -> 0.67906948 | H52: =H51/H50 -> 0.14769062 | I52: 0.3186013
A53: COMMERCIAL | B53: Ongoing | C53: Nyati Quantum Towers | D53: Sign Off Cost (Cr.) | F53: Planned | G53: 3.3000422 | H53: 3.9000499 | I53: 3.6000461 | J53: 5.1000653 | K53: 4.6500595 | L53: 4.9500634 | M53: 5.4000691 | N53: 5.700073 | O53: 5.1000653 | P53: 5.550071 | Q53: 6.3000806 | R53: 6.4500826
D54: Actual Cost (Cr.) | E54: 13.47 | F54: Actual | G54: 2.68 | H54: 1.5713 | I54: 3.15
D55: Actual Progress (%) | F55: Effi. % | G55: =G54/G53 -> 0.81211082 | H55: =H54/H53 -> 0.40289228 | I55: 0.8749888
A56: COMMERCIAL | B56: Ongoing | C56: Nyati Unitree Extension | D56: Sign Off Cost (Cr.) | F56: Planned | G56: 1.1000141 | H56: 1.250016 | I56: 1.1500147 | J56: 1.7000218 | K56: 1.800023 | L56: 2.0500262 | M56: 1.800023 | N56: 1.9000243 | O56: 1.8500237 | P56: 1.800023 | Q56: 2.2000282 | R56: 1.4000179
D57: Actual Cost (Cr.) | E57: 16.75 | F57: Actual | G57: 0.79 | H57: 0.98 | I57: 1.3
D58: Actual Progress (%) | F58: Effi. % | G58: =G57/G56 -> 0.71817263 | H58: =H57/H56 -> 0.78398996 | I58: 1.1304203

Sheet Booking Apr
A1: Company | B1: project | C1: Building | D1: Unit | E1: customer_name | F1: Customer_address | G1: Customer_Mobile | H1: PAN_NO | I1: Booking_Date | J1: Aggr_Date | K1: Area1 | L1: Agg_Value | M1: Claimed_Amt | N1: Claimed_GST | O1: Amount_Received | P1: RelationManager | Q1: SaleManager | R1: Source | S1: Subsource | T1: Referredbycustomer | U1: Sourcing Team/ROM | V1: Swabhiman (Defence) | W1: International Office | X1: Poona Office | Y1: Reference By
A2: Mihir Homes Enterprise LLP | B2: NYATI EQUINOX I | C2: VESTA - (PMC NO. 2D) | D2: VESTA - 2D -2701 | E2: ROHIT SHYAMKANT SHEGOKAR | F2: C - 803, VIVA HALLMARK, OPP. SURYADATTA COLLEGE, PATIL NAGAR, BAVDHAN, PUNE - 411021 (MAHARASHTRA) | G2: 9545859655 | H2: ASDPS1206K | I2: 46128 | J2: 46141 | K2: 2878 | L2: 23743500 | M2: 0 | N2: 0 | O2: 9497400 | P2: Prasad Kamble | Q2: Swapnil Gavande (Mihir Team) | R2: REFERENCE | S2: CHANNEL PARTNER
A3: Mihir Homes Enterprise LLP | B3: NYATI EQUINOX I | C3: PHOENIX - (PMC NO. 2A) | D3: PHOENIX - 2A - 2002 | E3: SHITAL PRATHAMESH ABNAVE | F3: FLAT NO. 401, SOLITAIRE 5, BIBWEWADI - KONDHWA ROAD, OPP. KUMAR PARK, PUNE - 411037 (MAHARASHTRA) | G3: 744780311 | H3: ARJPV3198A | I3: 46129 | J3: 46131 | K3: 1719 | L3: 13752000 | M3: 4125600 | N3: 206280 | O3: 4690000 | P3: Prasad Kamble
A4: Mihir Homes Enterprise LLP | B4: NYATI EQUINOX I | C4: GALAXY - (PMC NO. 2B) | D4: GALAXY - 2B -2203 | E4: PRAKASH GANESH PHATAK | F4: H.NO. 404 - N, SECTOR - C, OPP. FLOUR MILL, N - 1, CIDCO, CHH. SAMBHAJI NAGAR - 431003 (MAHARASHTRA) | G4: 9325210305 | H4: AAVPP3287D | I4: 46130 | J4: 46158 | K4: 1152 | L4: 9216000 | M4: 0 | N4: 0 | O4: 2856960 | P4: Prasad Kamble | Q4: Swapnil Gavande (Mihir Team) | R4: REFERENCE | S4: CHANNEL PARTNER | X4: YES
A5: Mihir Homes Enterprise LLP | B5: NYATI EQUINOX I | C5: GALAXY - (PMC NO. 2B) | D5: GALAXY - 2B -2204 | E5: KANCHAN PRAKASH PHATAK | F5: H.NO. 404 - N, SECTOR - C, OPP. FLOUR MILL, N - 1, CIDCO, CHH. SAMBHAJI NAGAR - 431003 (MAHARASHTRA) | G5: 9325210305 | H5: EEVPP5333A | I5: 46130 | J5: 46158 | K5: 1152 | L5: 9216000 | M5: 0 | N5: 0 | O5: 2764800 | P5: Prasad Kamble | Q5: Swapnil Gavande (Mihir Team) | R5: REFERENCE | S5: CHANNEL PARTNER
A6: Mihir Homes Enterprise LLP | B6: NYATI EQUINOX I | C6: VESTA - (PMC NO. 2D) | D6: VESTA - 2D -2301 PREMIUM PNN FLAT | E6: SANTOSHKUMAR GURUDATH ULLAL | F6: FLAT NO. 408, SERAPH-10, PLOT NO. 21/B, RAMNAGAR COLONY, N D A PASHAN ROAD, BAVDHAN POLICE CHOWKI, PUNE, MAHARASHTRA - 411021 | G6: 9822615860 | H6: AALPU2364G | I6: 46133 | J6: 46198 | K6: 2878 | L6: 24463000 | M6: 0 | N6: 0 | O6: 2446300 | P6: Prasad Kamble | Q6: Swapnil Gavande (Mihir Team) | R6: CHANNEL PARTNER | S6: BK ALPHA HOUSING REALTY LLP | X6: YES
A7: Mihir Homes Enterprise LLP | B7: NYATI EQUINOX I | C7: GALAXY - (PMC NO. 2B) | D7: GALAXY - 2B -2303 | E7: NANDAN PATHAK | F7: VILLAGE - PARA, SUKHIPUR, AZAMGARH, UTTAR PRADESH - 223221 | G7: 7499542733 | H7: CCGPP8618H | I7: 46133 | J7: 46161 | K7: 1152 | L7: 9112320 | M7: 0 | N7: 0 | O7: 911232 | P7: Prasad Kamble | Q7: Jitendra Reddy | R7: REFERENCE | S7: EXISTING CLIENT | X7: YES
A8: Mihir Homes Enterprise LLP | B8: NYATI EQUINOX I | C8: REGAL - (PMC NO. 1A) | D8: REGAL - 1A -1802 | E8: MANDAR KISHOR HIRALIKAR | F8: H2-204, ROSE ICON SOCIETY, NEAR KUNJIR CHOWK, PIMPLE SAUDAGAR, PUNE :411027 (MAHARASHTRA) | G8: 9552573251 | H8: ACAPH1452K | I8: 46133 | J8: 46181 | K8: 1719 | L8: 13888470 | M8: 0 | N8: 0 | O8: 1388847 | P8: Prasad Kamble | Q8: Shushant Desai (Mihir Team) | X8: YES
A9: Mihir Homes Enterprise LLP | B9: NYATI EQUINOX I | C9: PODIUM - 3 | D9: P3 - SHOP NO - 222 | E9: ABHAY SURYKANT KULKARNI | F9: FLAT NO. 501, SILVER OAK, RIGHT BHUSARI COLONY, NEAR NEW INDIA SCHOOL, KOTHRUD, PUNE - 411038 (MAHARASHTRA) | G9: 7774096307 | H9: AIYPK5959N | I9: 46134 | J9: 46155 | K9: 494 | L9: 6115500 | M9: 0 | N9: 0 | O9: 2813131 | P9: Prasad Kamble | Q9: Shushant Desai (Mihir Team) | R9: REFERENCE | S9: CHANNEL PARTNER | X9: YES
A10: Mihir Homes Enterprise LLP | B10: NYATI EQUINOX I | C10: PHOENIX - (PMC NO. 2A) | D10: PHOENIX - 2A - 2703 | E10: Meera Madhav Kamat | F10: Flat No 18/1 J Daulat Housing Society Near Macdonald Karve Nagar Road Kothrud : 411038 | G10: 77680492674 | I10: 46135 | J10: 2 | K10: 1152 | L10: 9100800 | M10: 0 | N10: 0 | O10: 200000 | P10: Prasad Kamble | Q10: Harshvardhan | R10: DIRECT SALES | S10: WALK IN | X10: YES
A11: Mihir Homes Enterprise LLP | B11: NYATI EQUINOX I | C11: PHOENIX - (PMC NO. 2A) | D11: PHOENIX - 2A - 2702 | E11: Meera Madhav Kamat | F11: FLAT 18/19 DAULAT HOUSING SOCIETY NEAR MC DONALD KARVE ROAD KOTHRUD PUNE :411038 | G11: 9423013444 | I11: 46135 | J11: 2 | K11: 1719 | L11: 14224065 | M11: 0 | N11: 0 | O11: 300000 | P11: Prasad Kamble | Q11: Harshvardhan | R11: DIRECT SALES | S11: WALK IN | X11: YES
A12: Mihir Homes Enterprise LLP | B12: NYATI EQUINOX I | C12: SIRIUS - (PMC NO.2F) | D12: SIRIUS - 2F - 903 | E12: Anubhav Karkar | F12: 24/25 SHANTI NIKETAN , SECTOR 3 VASHI , NAVI MUMBAI :400703 | G12: 9322278356 | I12: 46142 | J12: 2 | K12: 1698 | L12: 13329300 | M12: 0 | N12: 0 | O12: 166464 | P12: Prasad Kamble | R12: DIRECT SALES
A13: Mihir Homes Enterprise LLP | B13: NYATI EQUINOX I | C13: PHOENIX - (PMC NO. 2A) | D13: PHOENIX - 2A - 2502 | E13: Sachin Hanmantrao Gaikwad | F13: D4 204, NYATI EQUITORIAL -2 , BAVDHAN PUNE :411021 | G13: 8149467720 | I13: 46142 | J13: 2 | K13: 1719 | L13: 13752000 | M13: 0 | N13: 0 | O13: 200000 | P13: Prasad Kamble | Q13: Shushant Desai (Mihir Team) | R13: REFERENCE | S13: CHANNEL PARTNER | X13: YES
A14: Mihir Homes Enterprise LLP | B14: NYATI EQUINOX II | C14: MIRA (PMC - B) | D14: MIRA - B -2605 | E14: ALANKAR ANKUSH PATIL | F14: LANE NO. 49, JANTA VASAHAT, DESAI CLINIC SAMOR, PARVATI PAYATHA, PUNE 411009 (MAHARASHTRA) | G14: 9970016816 | H14: CPQPP6817P | I14: 46126 | J14: 46163 | K14: 733 | L14: 5049637 | M14: 0 | N14: 0 | O14: 1160996 | P14: Prasad Kamble | Q14: Anirudh Nair (Mihir Team) | R14: DIRECT SALES | S14: WALK IN | X14: YES
A15: Mihir Homes Enterprise LLP | B15: NYATI EQUINOX II | C15: MIRA (PMC - B) | D15: MIRA - B -2503 | E15: Manjiree Ankur Kumar Singh | F15: 56/2 SAISADAN A-13 SANT NAGAR OPPOSITE EDUNEED SHOP ARANESHYWAR PARVATI PUNE : 411009 | G15: 971562853083 | H15: APWPP9235K | I15: 46130 | J15: 2 | K15: 730 | L15: 4745000 | M15: 0 | N15: 0 | O15: 300000 | P15: Prasad Kamble
A16: Mihir Homes Enterprise LLP | B16: NYATI EQUINOX II | C16: CERES - (PMC NO A) | D16: CERES - A -2601 | E16: Amruta Rajesh Titade | F16: F 04 , SHRI SAMARTHVANDAN SOC , DHAYARI GANESH NAGAR PUNE : 411041 | H16: APPPT8639E | I16: 46133 | J16: 2 | K16: 1230 | L16: 8364000 | M16: 0 | N16: 0 | O16: 836400 | P16: Prasad Kamble | Q16: Anirudh Nair (Mihir Team) | R16: CHANNEL PARTNER | S16: ASSET DEALS
A17: Mihir Homes Enterprise LLP | B17: NYATI EQUINOX II | C17: CERES - (PMC NO A) | D17: CERES - A -2301 | E17: NEHA SHIRISHKUMAR SARPOTDAR | F17: SAMRUDDHI CO. HSG. SOC. LTD., FLAT NO. 401, D. P. ROAD, KUMBARE PARK, NEAR CITY INT. SCHOOL, KOTHRUD, PUNE - 411038 (MAHARASHTRA) | G17: 7208774788 | H17: AMQPS0061F | I17: 46141 | J17: 2 | K17: 1230 | L17: 8487000 | M17: 0 | N17: 0 | O17: 848700 | P17: Prasad Kamble | Q17: Shushant Desai (Mihir Team) | R17: CHANNEL PARTNER | S17: ASSET DEALS | X17: YES
A18: Nyati Builders Pvt Ltd | B18: NYATI ELENOR | C18: A TOWER | D18: A TOWER -803 | E18: RAGHUBIR SINGH SALUJA | F18: GVK SkY City Flat no 102 Block - B Beside Rajbhavan Somaji Guda Nampally Hyderabad Telangana 500082 | G18: 9849026348 | I18: 46130 | J18: 2 | K18: 2580 | L18: 25800000 | M18: 0 | N18: 0 | O18: 3600000 | P18: Ashish Bhasin | Q18: Janavhi Chugera | R18: CHANNEL PARTNER | S18: THEME PROPERTIES
A19: Nyati Builders Pvt Ltd | B19: NYATI ELENOR | C19: B TOWER | D19: B TOWER - 1203 | E19: ANSHUMAN NAGESH SETH | F19: A3 - 801, MARGOSA HEIGHTS, OPP. H V DESAI EYE HOSPITAL, MOHAMMEDWADI, PUNE - 411060 | G19: 16504001755 | H19: BLTPS6317K | I19: 46130 | J19: 2 | K19: 3255 | L19: 44600000 | M19: 0 | N19: 0 | O19: 500000 | P19: Ashish Bhasin | Q19: Nikita Patil | X19: YES
A20: Nyati Builders Pvt Ltd | B20: NYATI ELENOR | C20: A TOWER | D20: A TOWER -1204 | E20: BHARAT MOHANLAL PAREKH | F20: SR NO.77/48/1A, 71, FLAT NO.1204, CYPRUS COURT, WING-7, PARMAR PARK-2, NEAR JAGTAP NAGAR, WANOWRIE, PUNE – 411040, MAHARASHTRA | G20: 9890509951 | I20: 46132 | J20: 46132 | K20: 3255 | L20: 32600000 | M20: 0 | N20: 0 | O20: 5775000 | P20: Ashish Bhasin | Q20: Janavhi Chugera | R20: REFERENCE | S20: CHANNEL PARTNER | X20: YES
A21: Nyati Builders Pvt Ltd | B21: NYATI ELENOR | C21: B TOWER | D21: B TOWER -2902 | E21: SMITA MAHINDRA KOTHARI | F21: 201 Kumar Padma CTS 1187/2 FP550 Shivaji Nagar, Behind Modern College Pune - 411005 | G21: 9890000056 | I21: 46140 | J21: 2 | K21: 3860 | L21: 38683800 | M21: 0 | N21: 0 | O21: 11605140 | P21: Ashish Bhasin | Q21: Janavhi Chugera | R21: REFERENCE | S21: CHANNEL PARTNER
A22: Nyati Builders Pvt Ltd | B22: NYATI ELENOR | C22: B TOWER | D22: B TOWER -2302 | E22: DEEPENDER SINGH RAJPAL | F22: D - 803 Bramha Exhuberance NIMB Road Kondhwa Pune - 411048 | G22: 9881123361 | I22: 46140 | J22: 2 | K22: 3860 | L22: 40400000 | M22: 0 | N22: 0 | O22: 500000 | P22: Ashish Bhasin | Q22: Janavhi Chugera | R22: CHANNEL PARTNER | S22: THEME PROPERTIES | X22: YES
A23: Nyati Builders Pvt Ltd | B23: NYATI ELENOR | C23: B TOWER | D23: B TOWER -2202 | E23: LALIT OSWAL | F23: 801 Siddhi Signet, Near Golden Bakery, Salisbury Park Pune - 411037 | G23: 8390792957 | I23: 46140 | J23: 2 | K23: 3860 | L23: 41000000 | M23: 0 | N23: 0 | O23: 1100000 | P23: Ashish Bhasin | Q23: Janavhi Chugera | X23: YES
A24: Nyati Builders Pvt Ltd | B24: NYATI ELENOR | C24: B TOWER | D24: B TOWER - 1202 | E24: Sanjay Babulal Oswal | F24: 1/10 New Prasanna Park Society Shankersheth Road Pune 411037 | G24: 9423012543 | I24: 46140 | J24: 2 | K24: 3860 | L24: 41000000 | M24: 0 | N24: 0 | O24: 1100000 | P24: Ashish Bhasin | Q24: Janavhi Chugera
A25: Nyati Builders Pvt Ltd | B25: NYATI EMERALD I | C25: BERYL - (PMC - B1) | D25: BERYL - B1 - 503 | E25: SHWETA UPADHYAY | F25: 487, RAJ NIKETAN, GOPAL PURAM, MANDLA ROAD, BILHARI, JABALPOR, BILHARI, PO BILHARI, DIST: JABALPUR, MADHYA PRADESH-482020 | G25: 9623424790 | H25: AISPU0456G | I25: 46133 | J25: 46147 | K25: 1698 | L25: 14016990 | M25: 0 | N25: 0 | O25: 11213596 | P25: Sanjeev Deshpande | Q25: Manoj Udawant | R25: DEFENCE | S25: DEFENCE | X25: YES
A26: Nyati Builders Pvt Ltd | B26: NYATI EMERALD III | C26: AGATE - (PMC NO - D1) | D26: AGATE - D1 -2202 | E26: NACHIKET SANDEEP LOHKARE | F26: PLOT NO.55, ARYA NAGAR, KORADI ROAD, BEHIND CHUNGIKAR NAKA NO.1, MANKAPUR S.O, NAGPUR – 440030, MAHARASHTRA | G26: 9168945474 | H26: BGRPL9744G | I26: 46121 | J26: 46153 | K26: 1173 | L26: 10230357 | M26: 0 | N26: 0 | O26: 4603661 | P26: Ashish Bhasin | Q26: Digant Kumar | R26: CHANNEL PARTNER | S26: Channel Partner | X26: YES
A27: Nyati Builders Pvt Ltd | B27: NYATI EMERALD III | C27: AGATE - (PMC NO - D1) | D27: AGATE - D1 -2003 | E27: SANJAY RAMGONDA PATIL | F27: D-6-9, Jalnidhi Co Op HSG Society, Bangur Nagar, Goregaon West, Near Police Chowky, Mumbai - 400104, Maharashtra. | G27: 9321484091 | H27: ACBPP3079M | I27: 46121 | J27: 46176 | K27: 1698 | L27: 14283036 | M27: 0 | N27: 0 | O27: 1571133 | P27: Ashish Bhasin | Q27: Digant Kumar | R27: CHANNEL PARTNER | S27: NITIN DHAMANE | X27: YES
A28: Nyati Builders Pvt Ltd | B28: NYATI EMERALD III | C28: TOPAZ - (PMC NO - C3) | D28: TOPAZ - C3 -2203 | E28: POOJA VINAYAK THAKUR | F28: F-8, B WING, AUDUMBAR PLAZA, AUDUMBAR NAGAR, KUDAL, SINDHUDURG, MAHARASHTRA - 416520 | G28: 7456840216 | H28: AYBPT4475D | I28: 46130 | J28: 46156 | K28: 1698 | L28: 14238223 | M28: 0 | N28: 0 | O28: 8827698 | P28: Ashish Bhasin | Q28: Mrunal Wankhade | X28: YES
A29: Nyati Builders Pvt Ltd | B29: NYATI EMERALD III | C29: TOPAZ - (PMC NO - C3) | D29: TOPAZ - C3 -2004 | E29: ASHITA RAINA | F29: C 1201, MARVEL BOUNTY, HADAPSAR , PUNE – 411028, MAHARASHTRA | G29: 9818665501 | H29: BEYPR9348B | I29: 46133 | J29: 46139 | K29: 1698 | L29: 14015179 | M29: 8549259 | N29: 427462 | O29: 8689410.9 | P29: Ashish Bhasin | Q29: Sanjay Zaveri | R29: DIRECT SALES | S29: WALK IN | X29: YES
A30: Nyati Builders Pvt Ltd | B30: NYATI EMERALD III | C30: RUBY - (PMC NO - C2) | D30: RUBY - C2 -802 | E30: ANAND NARENDRA ABRUK | F30: AT POST : GANORI , IBRAHIMPUR, AMRAVATI - 444701, MAHARASHTRA | G30: 8408077361 | H30: BLCPA7675R | I30: 46133 | J30: 46157 | K30: 1173 | L30: 9694643 | M30: 0 | N30: 0 | O30: 5913733 | P30: Ashish Bhasin | Q30: Digant Kumar | R30: CHANNEL PARTNER | S30: SQUARE YARDS | X30: YES
A31: Nyati Builders Pvt Ltd | B31: NYATI EMERALD III | C31: OPAL - (PMC NO - C1) | D31: OPAL - C1 -1401 | E31: NAHUSH PRAKASH ZILPILWAR | F31: Gundoba chauk, WARD NO. 4, Bori (patan), PO : Patanbori, DIST : Yavatmal, Maharashtra - 445305 | G31: 8668726567 | H31: ABHPZ4232B | I31: 46140 | J31: 46191 | K31: 1173 | L31: 9694643 | M31: 0 | N31: 0 | O31: 1066410 | P31: Ashish Bhasin | Q31: Digant Kumar | R31: CHANNEL PARTNER | X31: YES
A32: Nyati Builders Pvt Ltd | B32: NYATI EVOQUE | C32: LAVENDER - (PMC NO. A1) | D32: LAVENDER - A 1 -2003 | E32: VARSHADEVI PRATHVIRAJ DESHMUKH | F32: ATHARVA PARK, WING - B, FLAT NO. 102, AMBEJOGAI ROAD, BELAMBE NAGAR, LATUR - 413512 (MAHARASHTRA) | G32: 447545357317 | H32: CNIPD8644L | I32: 46130 | J32: 2 | K32: 2175 | L32: 28314150 | M32: 0 | N32: 0 | O32: 500000 | P32: Ashish Bhasin | Q32: Shivam Shrivas | X32: YES
A33: Nyati Builders Pvt Ltd | B33: NYATI EVOQUE | C33: OLIVE - (PMC NO A2) | D33: OLIVE - A2 -1501 | E33: AISHWARYA JEETKUMAR VITHALANI | F33: A – 805, AARYA HEIGHTS, OLD VALSAD ROAD, VAPI - 396191 (GUJARAT) | G33: 9545126030 | H33: BYDPM2133G | I33: 46140 | J33: 2 | K33: 2126 | L33: 26583000 | M33: 0 | N33: 0 | O33: 2658000 | P33: Ashish Bhasin | Q33: Janavhi Chugera | R33: CHANNEL PARTNER | S33: BK ALPHA HOUSING REALTY LLP | X33: YES
A34: Nyati Builders Pvt Ltd | B34: NYATI EXUBERANCE III | C34: BLUEBELL (PMC NO. D) | D34: BLUEBELL - D-107 | E34: SURENDRA MAYANLAL CHIKHLONDE | F34: MATA MANDIR SAMOR, CHANDNI TOLA, NAGARA, GONDIYA - 441601 (MAHARASHTRA) | G34: 7875367645 | H34: AVZPC3395C | I34: 46119 | J34: 46127 | K34: 457 | L34: 1513200 | M34: 1513200 | N34: 0 | O34: 1513200 | P34: Harish Shroff | X34: YES
A35: Nyati Builders Pvt Ltd | B35: NYATI EXUBERANCE III | C35: BLUEBELL (PMC NO. D) | D35: BLUEBELL - D -507 | E35: ASHISH RAMLAL POL | F35: S/O: RAMLALA POL SR NO.48/1 ICHHA TRUPTI HOUSING SOCIETY GANESH NAGAR NEAR RAHUL VIDEO CENTAR PUNE - 411014 (MAHARASHTRA) | G35: 9922346106 | H35: AUGPP5257L | I35: 46120 | J35: 46125 | K35: 457 | L35: 1513200 | M35: 1513200 | N35: 0 | O35: 1513200 | P35: Harish Shroff | X35: YES
A36: Nyati Builders Pvt Ltd | B36: NYATI EXUBERANCE III | C36: BLUEBELL (PMC NO. D) | D36: BLUEBELL - D - 803 | E36: AMEER HAQSHENASS | F36: FLAT NO. 601, A-1(AMBER), NYATI ESTEBAN I, UNDRI, PUNE- 411060 (MAHARASHTRA) | G36: 09833698975 | H36: ALLPH7886F | I36: 46142 | J36: 46150 | K36: 473 | L36: 1892000 | M36: 0 | N36: 0 | O36: 1892000 | P36: Sanjeev Deshpande | R36: DIRECT SALES | S36: EXISTING CLIENT | X36: YES
A37: Nyati Builders Pvt Ltd | B37: NYATI EXUBERANCE IV | C37: PRIMROSE (PMC NO. C4) | D37: PRIMROSE - C4 -1803 | E37: Lata Bhandurge | F37: 606 Rasta Peth , Pune City - 411011. | G37: 9823400564 | I37: 46130 | J37: 2 | K37: 981 | L37: 5910525 | M37: 0 | N37: 0 | O37: 100000 | P37: Sanjeev Deshpande | Q37: Ganesh Waghmare | R37: CHANNEL PARTNER | X37: YES
A38: Nyati Builders Pvt Ltd | B38: NYATI EXUBERANCE IV | C38: PRIMROSE (PMC NO. C4) | D38: PRIMROSE - C4 -203 | E38: SUPERNA DEEPAK BHAT | F38: CSN NO. 2094B/2/1, FLAT NO. B-504, MAHADIK VASAHAT GUR, MARKET YARD, KOLHAPUR - 416005 | G38: 8390395395 | H38: BAYPR8550F | I38: 46130 | J38: 46191 | K38: 981 | L38: 5788881 | M38: 0 | N38: 0 | O38: 5788881 | P38: Ashish Bhasin | Q38: Ganesh Waghmare | R38: CHANNEL PARTNER | X38: YES
A39: Nyati Builders Pvt Ltd | B39: NYATI EXUBERANCE IV | C39: PRIMROSE (PMC NO. C4) | D39: PRIMROSE - C4 -204 | E39: MOKAL SANJAY LAXMAN | F39: LAXMINAGAR, KOPARGAON, PO : KOPARGAON, DIST : AHMADNAGAR MAHARASHTRA - 423601 | G39: 9067440822 | H39: ATOPM3704A | I39: 46136 | J39: 46142 | K39: 981 | L39: 5886000 | M39: 0 | N39: 0 | O39: 5886000 | P39: Sanjeev Deshpande | Q39: Neharkar Swapnil
A40: Nyati Builders Pvt Ltd | B40: NYATI EXUBERANCE IV | C40: CAMELLIA (PMC NO. C5) | D40: CAMELLIA - C5 -601 | E40: SUNEET SINGH | F40: MID TOWN SOCIETY, C-64, FLORENTINE SOCIETY, SOPAN BAUG, GHORPADI, PUNE - 411001, MAHARASHTRA. | G40: 9823728439 | H40: DLGPS5581A | I40: 46136 | J40: 46177 | K40: 985 | L40: 5446065 | M40: 0 | N40: 0 | O40: 3757785 | P40: Sanjeev Deshpande | Q40: Pallavi Shendge | R40: DEFENCE | S40: DEFENCE | X40: YES
A41: Nyati Builders Pvt Ltd | B41: NYATI EXUBERANCE IV | C41: CAMELLIA (PMC NO. C5) | D41: CAMELLIA - C5 -602 | E41: RAVINDER PAL SINGH | F41: C-64, Florentine Society, Sopan Baug , Ghorpadi, Pune - 411001. | G41: 9129433007 | H41: BKFPS3835R | I41: 46136 | J41: 2 | K41: 985 | L41: 5446065 | M41: 0 | N41: 0 | O41: 3757785 | P41: Sanjeev Deshpande | Q41: Pallavi Shendge | R41: DEFENCE | S41: DEFENCE | X41: YES
A42: Nyati Builders Pvt Ltd | B42: NYATI EXUBERANCE IV | C42: CAMELLIA (PMC NO. C5) | D42: CAMELLIA - C5 -1001 PREMIUM FLAT | E42: AJINKYA WAJURKAR | F42: Yashodeep Niwas Narsinha Colony Pangri Road Beed - 431122. | G42: 9028593693 | I42: 46141 | J42: 2 | K42: 985 | L42: 5910000 | M42: 0 | N42: 0 | O42: 591000 | P42: Sanjeev Deshpande | Q42: Neharkar Swapnil
A43: Nyati Builders Pvt Ltd | B43: NYATI EXUBERANCE IV | C43: CAMELLIA (PMC NO. C5) | D43: CAMELLIA - C5 -803 | E43: NIKHIL BAKSHI | F43: A-2/603, Nyati Epitome, OPP - Corinthians CLUB, Mohammed Wadi, Pune - 411060, MAHARASHTRA. | G43: 9790051759 | H43: CFKPB0983E | I43: 46142 | J43: 46182 | K43: 981 | L43: 5423949 | M43: 0 | N43: 0 | O43: 542394 | P43: Sanjeev Deshpande | Q43: Pallavi Shendge | R43: DIRECT SALES | S43: EXISTING CLIENT | X43: YES
A44: Nyati Builders Pvt Ltd | B44: NYATI EXUBERANCE IV | C44: CAMELLIA (PMC NO. C5) | D44: CAMELLIA - C5 -703 | E44: ALLEN MICHAEL BROWN | F44: HOUSE NO – 101, SR. NO – 14, JAI JAWAN NAGAR, NEAR CHANDANI CHOWK, GANPATI MANDIR, YERWADA, PUNE – 411006, MAHARASHTRA | G44: 7798006327 | H44: ASZPB1528R | I44: 46142 | J44: 46179 | K44: 981 | L44: 5494581 | M44: 0 | N44: 0 | O44: 604404 | P44: Sanjeev Deshpande | Q44: Ganesh Waghmare | R44: CHANNEL PARTNER
A45: Nyati Builders Pvt Ltd | B45: NYATI EXUBERANCE IV | C45: CAMELLIA (PMC NO. C5) | D45: CAMELLIA - C5 -1503 | E45: ANURADHA BHAU PATIL | F45: 48/20, QUATER, S.R.P.F GROUP NO. 2, RAMTEKDI, PUNE - 411022, MAHARASHTRA | G45: 9373776158 | I45: 46142 | J45: 46183 | K45: 981 | L45: 5542650 | M45: 0 | N45: 0 | O45: 350000 | P45: Sanjeev Deshpande | Q45: Akshay Tagad | R45: CHANNEL PARTNER | S45: SKYLINE GROUP | X45: YES
A46: Nyati Construction Pvt.Ltd. | B46: NYATI EMBLEM | C46: F BUILDING | D46: F BUILDING - UNIT NO.2402 | E46: SHWETA RAVIRAJ LAYGUDE | F46: 901 Primerose Near D Mart Katraj Pune - 411046 | G46: 9762815186 | I46: 46142 | J46: 2 | K46: 3642 | L46: 45700000 | M46: 0 | N46: 0 | O46: 1500000 | P46: Ashish Bhasin | Q46: Girish N | R46: REFERENCE | S46: CHANNEL PARTNER
A47: Nyati Construction Pvt.Ltd. | B47: NYATI ERA IV | C47: NOBLE - (PMC NO. WING N) | D47: NOBLE - N - 302 | E47: KHUSBUH SHAIKH | F47: walki suger factory road, walki, ahmed nagar, maharashtra - 414006 | G47: 8830522021 | H47: PVBPS4813Q | I47: 46130 | J47: 2 | K47: 1376 | L47: 9563200 | M47: 0 | N47: 0 | O47: 200000 | P47: Sanjeev Deshpande | Q47: Anna Saheb Bhosale | R47: DIRECT SALES | S47: WALK IN | X47: YES
A48: Nyati Construction Pvt.Ltd. | B48: NYATI ERA IV | C48: JOY - (PMC NO. WING J) | D48: JOY - J - 302 | E48: JOGENDER SINGH | F48: H NO. 31, VILL : NUNSAR THE LOHARU, DIST : BHIWAI, HARYANA - 127028 | G48: 9728777447 | H48: DXZPS0497A | I48: 46135 | J48: 2 | K48: 1625 | L48: 11382000 | M48: 0 | N48: 0 | O48: 100000 | P48: Rakesh Pillai | R48: CHANNEL PARTNER | X48: YES
A49: Nyati Construction Pvt.Ltd. | B49: NYATI ERA IV | C49: ORION - (PMC NO. WING O) | D49: ORION - O - 804 | E49: VIDYA ANIL SAVALE | F49: FLAT NO. C - 301, MAJESTIQUE MANHATTAN (PHASE-1), GAT NO. 569, WAGHOLI, DIST : PUNE, MAHARASHTRA - 412207 | G49: 9404897242 | I49: 46142 | J49: 46163 | K49: 844 | L49: 5072973 | M49: 0 | N49: 0 | O49: 1572622 | P49: Rakesh Pillai | Q49: Marmik | R49: CHANNEL PARTNER | X49: YES
A50: Nyati Construction Pvt.Ltd. | B50: NYATI EVANIA | C50: B WING | D50: B -1803 | E50: TANMAY SHRIKANT JOG | F50: SR. No. 12, FLAT NUMBER B - 703, SUN ORBIT HOUSING SOCIETY, ANANDNAGAR, SINHGAD ROAD, PUNE – 411051 (MAHARASHTRA) | G50: 8080787896 | H50: AOGPJ5414F | I50: 46142 | J50: 46183 | K50: 1287 | L50: 15129464 | M50: 0 | N50: 0 | O50: 1512946 | P50: Rakesh Pillai | X50: YES
A51: Nyati Realtors LLP | B51: NYATI ESTEBAN II | C51: ALEXANDRITE (PMC - D5) | D51: ALEXANDRITE - D5 - 2103 | E51: ASHWINI VITTHAL RODAGE | F51: FLAT NO. 301, AKSHARGATHA TOWER, SR NO. 17, LANE NO. 3, SUKHSAGR NAGAR, KATRAJ, PUNE – 411046, MAHARASHTRA | G51: 9921776595 | H51: BYTPR7693N | I51: 46130 | J51: 2 | K51: 1172 | L51: 6899107 | M51: 0 | N51: 0 | O51: 100000 | P51: Sanjeev Deshpande | Q51: Akshay Tagad | R51: DIRECT SALES | X51: YES
A52: Nyati Realtors LLP | B52: NYATI ESTEBAN II | C52: GARNET (PMC - D2) | D52: GARNET - D2 - 503 | E52: SANDEEP RAMBHAU RODE | F52: RAVI PARK HOUSING SOCIETY, FLAT NO. 12, LANE NO. 4, PLOT NO. 31, SAHAKARNAGAR, MIDC, BARAMATI, PUNE - - 413133, MAHARASHTRA | G52: 8275465059 | H52: AFUPR2046E | I52: 46130 | J52: 46150 | K52: 1172 | L52: 6921873 | M52: 0 | N52: 0 | O52: 4637654.3 | P52: Sanjeev Deshpande | Q52: Akshay Tagad | R52: DIRECT SALES | X52: YES
A53: Nyati Realtors LLP | B53: NYATI ESTEBAN II | C53: TANZANITE (PMC - D4) | D53: TANZANITE - D4 - 2701 | E53: SHATRUJEET SINGH | F53: VIKAS KHAND, 2/48, GOMTI NAGAR, LUCKNOW – 226010, UTTAR PRADESH | G53: 6591017190 | H53: AZJPS9003P | I53: 46130 | J53: 2 | K53: 1699 | L53: 9991819 | M53: 0 | N53: 0 | O53: 999182 | P53: Sanjeev Deshpande | Q53: Pushkar Shinde | R53: DIRECT SALES | S53: EXISTING CLIENT | X53: YES
A54: Nyati Realtors LLP | B54: NYATI ESTEBAN II | C54: ALEXANDRITE (PMC - D5) | D54: ALEXANDRITE - D5 - 2601 | E54: ANANYA MOHANTY | F54: A802, SAFFRON HILLSCAPES, KEDARI NAGAR ROAD, VILAS PETROL PUMP, HEAVEN PARK PETROL PUMP, PUNE, MAHARASHTRA – 411060. | G54: 7331123110 | H54: BQXPM2074C | I54: 46141 | J54: 46189 | K54: 1699 | L54: 10201802 | M54: 0 | N54: 0 | O54: 3270180.2 | P54: Sanjeev Deshpande | Q54: Pallavi Shendge | R54: REFERENCE | S54: CHANNEL PARTNER | X54: YES
A55: Nyati Realtors LLP | B55: NYATI ESTEBAN II | C55: ALEXANDRITE (PMC - D5) | D55: ALEXANDRITE - D5 - 601 | E55: VIVEK SINGH PARIHAR | F55: FLAT NO. F-704, F WING GANGA GLITZ SOCIETY, KAD NAGAR, UNDRI – PUNE – 411060, MAHARASHTRA | G55: 7798192920 | H55: BAYPS2305H | I55: 46142 | J55: 46181 | K55: 1699 | L55: 10109050 | M55: 0 | N55: 0 | O55: 1010905 | P55: Sanjeev Deshpande | Q55: Pushkar Shinde | R55: DIRECT SALES | X55: YES
A56: Nyati Realtors LLP | B56: NYATI ESTEBAN II | C56: ALEXANDRITE (PMC - D5) | D56: ALEXANDRITE - D5 - 401 | E56: GAURAV SHARMA | F56: F-408, GANGA GLITZ, UNDRI, PUNE – 411060, MAHARASHTRA | G56: 7042527711 | I56: 46142 | J56: 46191 | K56: 1699 | L56: 10109050 | M56: 0 | N56: 0 | O56: 710905 | P56: Sanjeev Deshpande | Q56: Pushkar Shinde | R56: REFERENCE | X56: YES
A57: Nyati Realtors LLP | B57: NYATI ESTEBAN II | C57: TANZANITE (PMC - D4) | D57: TANZANITE - D4 - 502 | E57: RUPA SINGH | F57: Sr. No 61/1/2B, Flat No. 403, Shama Heightgs, Ambegaon Khurd, Pune, Maharashtra - 411046 | G57: 9067844944 | H57: JZAPS2347E | I57: 46142 | J57: 46197 | K57: 1699 | L57: 10114997 | M57: 0 | N57: 0 | O57: 1011499.7 | P57: Sanjeev Deshpande | Q57: Neharkar Swapnil | R57: CHANNEL PARTNER
A58: Nyati Realtors LLP | B58: NYATI ESTEBAN II | C58: GARNET (PMC - D2) | D58: GARNET - D2 - 1401 | E58: SOUMYA SIDHARTHA MOHANTY | F58: D1-602, KUMAR PEBBEL PARK, SURVEY NO. 55, NEAR JSPM COLLEGE, HADAPSAR (N.V.), PUNE - 411028, MAHARASHTRA. | G58: 9583487712 | H58: AZCPM6649J | I58: 46142 | J58: 46197 | K58: 1699 | L58: 10092060 | M58: 0 | N58: 0 | O58: 100000 | P58: Sanjeev Deshpande | Q58: Akshay Tagad | R58: DIRECT SALES | X58: YES
A59: Nyati Realtors LLP | B59: NYATI ESTEBAN II | C59: TANZANITE (PMC - D4) | D59: TANZANITE - D4 - 402 | E59: MOHAMED FARHAN MOHAMED AEJAZ | F59: 165/166, DR. AMBEDKAR NAGAR, MAJREWADI, NEAR PANCHASHIL MARATHI SCHOOL, POST – TIKEKARWADI, SOLAPUR – 413224, MAHARASHTRA | G59: 8766646995 | H59: BSBPS9766D | I59: 46142 | J59: 46168 | K59: 1699 | L59: 10136234 | M59: 0 | N59: 0 | O59: 6081739 | P59: Sanjeev Deshpande | Q59: Pallavi Shendge | R59: DIRECT SALES | X59: YES
A60: Nyshaa Builders LLP | B60: NYATI EMPRESS | C60: A WING | D60: A WING - KIOSK - 1ST FLOOR | E60: INDU JAIN | F60: D-712, Jalvayu Towers, Sector – 47, Noida, Dist – Gautam Buddha Nagar, Uttar Pradesh - 201301 | G60: 9818332085 | H60: ACSPJ9530C | I60: 46132 | J60: 46137 | K60: 400 | L60: 6500000 | M60: 0 | N60: 0 | O60: 6500000 | P60: Harish Shroff | R60: CHANNEL PARTNER | X60: YES

Sheet Cancel Apr
A1: ProjectName | B1: Building | C1: UnitNo | D1: CustomerName | E1: Customer_Address | F1: TotalArea | G1: Agg_Value | H1: Sale_Date | I1: TransCan_Remark | J1: Cancel_Date | K1: Column5 | L1: Aadhaar_Card_No | M1: PAN_NO | N1: ReceivedAmount | O1: Sale_Status
A2: NYATI ELENOR | B2: B TOWER | C2: B TOWER -2902 | D2: Sameer Jain | E2: A 19 Arihant Housing Society Market Yard Pune - 411037 | F2: 3860 | G2: 51400000 | H2: 45777 | I2: As per HS | J2: 46132 | K2: 25000 | N2: 2100000 | O2: Cancel
A3: NYATI EMERALD I | B3: SAPPHIRE - (PMC - A2) | C3: SAPPHIRE - A2 - 2901 PREMIUM PNN FLAT | D3: SANGITA ANIL SHAH | E3: AASHIRWAD, 7 SUJAY GARDEN 12, MUKUND NAGAR PUNE- 411037 | F3: 1173 | G3: 9618600 | H3: 46142 | I3: Shifted to Patrakar Nagar | J3: 46142 | K3: 0 | M3: ADFPS7327E | N3: 4500000 | O3: Cancel
A4: NYATI EMERALD I | B4: BERYL - (PMC - B1) | C4: BERYL - B1 - 2901 | D4: PRAMOD GULUMKAR | E4: J- 1504 PRIDE PLATINUM SOCIETY BANER PAN CARD CLUB ROAD BANER PUNE 411045 | F4: 1173 | G4: 9998214 | H4: 46081 | I4: Due to financial Reason | J4: 46142 | K4: 0 | M4: AJDPG4850A | N4: 210000 | O4: Cancel
A5: NYATI EMERALD III | B5: RUBY - (PMC NO - C2) | C5: RUBY - C2 -702 | D5: CHANDAN KUMAR | E5: RANJANA TEXTILES, DARJI MUHALLAH, RAJDHANWAR DIST- GIRIDIH, JHARKHAND- 825412 | F5: 1173 | G5: 9238393 | H5: 46112 | I5: Due to Financial Reason | J5: 46142 | K5: 0 | M5: ATPPK6512M | N5: 100000 | O5: Cancel
A6: NYATI EMERALD III | B6: AGATE - (PMC NO - D1) | C6: AGATE - D1 -1003 | D6: DEBASISH ROY | E6: 4/6 KABI SUKANTA LANE 1ST FLOOR SANTOSHPUR KOLKATA-700075 | F6: 1698 | G6: 14550893 | H6: 46112 | I6: Financial Reason | J6: 46142 | K6: 0 | M6: AGGPR8099C | N6: 100101 | O6: Cancel
A7: NYATI EMERALD III | B7: RUBY - (PMC NO - C2) | C7: RUBY - C2 -1502 | D7: BHUSHAN AJAYRAO DHAGE | E7: AT/POST - WASHI, TA - SAMUDRAPUR, DIST - WARDHA, MAHARASHTRA - 442305 WARDHA- 442305 | F7: 1173 | G7: 9962500 | H7: 46105 | I7: Due to Financial Reason | J7: 46142 | K7: 0 | M7: ERNPD1904C | N7: 1778462 | O7: Cancel
A8: NYATI EMERALD III | B8: RUBY - (PMC NO - C2) | C8: RUBY - C2 -502 | D8: RANI KUMARI | E8: FLAT NO.808, TOWER 42, AMANORA GOLD TOWERS, HADAPSAR, PUNE- 411028 | F8: 1173 | G8: 9238393 | H8: 46112 | I8: Financial Reason | J8: 46142 | K8: 0 | M8: BBOPP7149B | N8: 100000 | O8: Cancel
A9: NYATI EMERALD III | B9: RUBY - (PMC NO - C2) | C9: RUBY - C2 -2401 | D9: SWANAND ANIL DHAWAN | E9: C-14, Sai Vihar Residency, Pashan-Sus Road, Near Sai Chowk, Pashan, Pashan, PO: Armament, DIST: Pune, Maharashtra-411021 | F9: 1173 | G9: 9595536 | H9: 45854 | I9: Cancellation Deed | J9: 46129 | K9: 0 | M9: BQOPD6965J | N9: 4735399 | O9: Cancel
A10: NYATI EQUINOX I | B10: EROS - (PMC NO. 2C) | C10: EROS - 2C -803 | D10: Mrinal Nitin Deshpande | E10: 166 shivaji Nagar Kanchan Vimals A2 Flat Nagpur: 440010 | F10: 1152 | G10: 9100800 | H10: 46098 | I10: no token amount | J10: 46126 | K10: 0 | N10: 0 | O10: Cancel
A11: NYATI EQUINOX I | B11: REGAL - (PMC NO. 1A) | C11: REGAL - 1A -2101 | D11: Shital Abnave | E11: Solitaire Bibewadi Near Khushboo Hotel | F11: 1719 | G11: 13681950 | H11: 46112 | I11: Shifted to 2A 2002 | J11: 46129 | K11: 0 | N11: 1000000 | O11: Cancel
A12: NYATI EQUINOX I | B12: PHOENIX - (PMC NO. 2A) | C12: PHOENIX - 2A - 1204 | D12: GAUTAM ARVIND KULKARNI | E12: 501 ANNAPURNA SMRUTI 1234 SHUKRAW AR PETH SUBHASHNAGAR LANE - 5 PUNE 411002. | F12: 1152 | G12: 8891136 | H12: 45731 | I12: Cancellation Deed - Financial Issue. | J12: 46140 | K12: 0 | M12: ABQPK4686G | N12: 2800709 | O12: Cancel
A13: NYATI EQUINOX I | B13: SIRIUS - (PMC NO.2F) | C13: SIRIUS - 2F - 603 | D13: Anubhav Karkar | E13: 24/25 Shanti Niketan Sector 3 Vashi Navi Mumbai -400703 | F13: 1698 | G13: 13329300 | H13: 46112 | I13: Shifted to 2F 903 | J13: 46140 | K13: 0 | N13: 166646 | O13: Cancel
A14: NYATI EQUINOX I | B14: EROS - (PMC NO. 2C) | C14: EROS - 2C -2402 | D14: YOGITA BHIMDAS BAHIRAT | E14: D/O BHIMDAS BAHIRAT, F/4, SHIV VILAS SOCIETY, S B ROAD, NEAR MARRIOTE HOTEL, SR. NO. 103, BAHIRATWADI, PUNE - 411016 (MAHARASHTRA) | F14: 1719 | G14: 13837950 | H14: 46053 | I14: PARKING ISSUE | J14: 46126 | K14: 0 | M14: AOIPB1449N | N14: 300000 | O14: Cancel
A15: NYATI EQUINOX II | B15: MIRA (PMC - B) | C15: MIRA - B -2503 | D15: SUMAN GEORGE | E15: S/O GEORGE DAVID, ST. PAULS ACADEMY, GAURI SHANKAR COLONY, GAI GHAT, GULZARBAGH, PATNA, BIHAR -800007 | F15: 730 | G15: 4781250 | H15: 45961 | I15: Financial Reason. | J15: 46118 | K15: 0 | M15: AVMPG9902E | N15: 659763 | O15: Cancel
A16: NYATI EQUINOX II | B16: CERES - (PMC NO A) | C16: CERES - A -2704 | D16: KETKEE SANJAY KOLI | E16: A-802, LAKESHIRE, JAMBHULWADI ROAD, AMBEGAON, PUNE - 411046 (MAHARASHTRA) | F16: 1552 | G16: 10780840 | H16: 46112 | I16: Finance Issue | J16: 46126 | K16: 0 | M16: APDPJ4850P | N16: 1868805 | O16: Cancel
A17: NYATI ERA II | B17: T WING (PMC NO. T) | C17: T WING -310 | D17: RAVINDRA JANARDHAN PARDHI | F17: 574 | G17: 1805600 | H17: 2 | J17: 46120 | K17: 0 | N17: 0 | O17: Cancel
A18: NYATI ESTEBAN II | B18: PEARL (PMC - D1) | C18: PEARL - D1 - 3002 | D18: Siddique Inamdar | E18: Sr.No 55/16,Lane No.14,Bhagyoday Nagar ,Kondhwa Khurd Near Khan Building , Pune - 411048. | F18: 1699 | G18: 10226281 | H18: 46133 | I18: Zero Token Amount | J18: 46142 | K18: 0 | N18: 0 | O18: Cancel
A19: NYATI ESTEBAN II | B19: GARNET (PMC - D2) | C19: GARNET - D2 - 2602 | D19: Harvinder Singh Kapoor | E19: 701 Serin Nyati Enclave , Mohammadwadi , Pune - 411060 | F19: 1699 | G19: 9869491 | H19: 46099 | I19: Personal Issue | J19: 46142 | K19: 0 | N19: 100000 | O19: Cancel
A20: NYATI ESTEBAN II | B20: PEARL (PMC - D1) | C20: PEARL - D1 - 3003 | D20: Siddique Inamdar | E20: Sr.No 55/16,Lane No.14,Bhagyoday Nagar ,Kondhwa Khurd Near Khan Building , Pune - 411048. | F20: 1172 | G20: 6833898 | H20: 46102 | I20: Zero Token Amount | J20: 46142 | K20: 0 | N20: 0 | O20: Cancel
A21: NYATI ESTEBAN II | B21: ALEXANDRITE (PMC - D5) | C21: ALEXANDRITE - D5 - 2103 | D21: RAVI SHANKAR SHETTY | E21: FLAT NO. 506, B BUILDING, DORABJEE PARADISE, NEAR VIBGYOR SCHOOL, MOHAMMADWADI, PUNE – 411060, MAHARASHTRA | F21: 1172 | G21: 6789324 | H21: 46021 | I21: UAE Current Circumstances. | J21: 46130 | K21: 0 | L21: 913945250733 | M21: AQZPS1842B | N21: 100000 | O21: Cancel
A22: NYATI EVANIA | B22: A WING | C22: A -706 | D22: Sonal Sumeet Polkam | E22: Flat no - 6 1458 Shree Ganesh Niwas Apartment Sadashiv Peth Pune 411030 | F22: 1405 | G22: 15595500 | H22: 46081 | I22: NO TOKEN AMOUNT | J22: 46128 | K22: 0 | N22: 0 | O22: Cancel
A23: NYATI EVANIA | B23: B WING | C23: B -501 | D23: VINOD GAJANAN SHAH | E23: USHA 21, PHATAK BAUG, NEAT MHATRE BRIDGE, NAVI PETH, PUNE - 411030 (MAHARASHTRA) | F23: 2543 | G23: 26725000 | H23: 45881 | I23: As per HS | J23: 46132 | K23: 0 | N23: 5600800 | O23: Cancel
A24: NYATI EXUBERANCE IV | B24: CAMELLIA (PMC NO. C5) | C24: CAMELLIA - C5 -1503 | D24: Agnisha Singh | E24: Old Chalk Bazar Road, Thana Mukh, Ward No.3, Sivasagar, Assam, Sivasagar - 785640. | F24: 981 | G24: 5519106 | H24: 46137 | I24: Might go for Esteban II | J24: 46140 | K24: 0 | N24: 100000 | O24: Cancel
A25: NYATI EXUBERANCE IV | B25: PRIMROSE (PMC NO. C4) | C25: PRIMROSE - C4 -1404 | D25: Memuna Dedhwal | E25: BAGEFIRDOSH BALESHWAR PO BALESHWAR SURAT 394617 | F25: 981 | G25: 5493600 | H25: 46081 | I25: Zero Payment | J25: 46142 | K25: 0 | N25: 0 | O25: Cancel

Sheet Coll Apr
A1: Project_Name | B1: Building_Name | C1: Opening Sales Value | D1: Sales Value For The Period | E1: Total Sales Value | F1: Opening Due | G1: Due For Period | H1: Total Due | I1: Opening Collection | J1: Collection For Period | K1: Total Collection | L1: Opening Outstanding | M1: Closing Outstanding
A2: NYATI DEFENCE ENCLAVE I | B2: VIKRANT ( PMC NO. D) | C2: 1719.42 | D2: 0 | E2: 1719.42 | F2: 1847.1 | G2: 0 | H2: 1847.1 | I2: 1847.1 | J2: 0 | K2: 1847.1 | L2: 0 | M2: 0
A3: NYATI DEFENCE ENCLAVE I | B3: SUKHOI ( PMC NO. C) | C3: 1826.28 | D3: 0 | E3: 1826.28 | F3: 1826.28 | G3: 0 | H3: 1826.28 | I3: 1824.82 | J3: 0 | K3: 1824.82 | L3: 1.46 | M3: 1.46
A4: NYATI DEFENCE ENCLAVE II | B4: CHETAK ( PMC NO. E) | C4: 1564.46 | D4: 0 | E4: 1564.46 | F4: 1564.46 | G4: 0 | H4: 1564.46 | I4: 1564.46 | J4: 0 | K4: 1564.46 | L4: 0 | M4: 0
A5: NYATI DEFENCE ENCLAVE II | B5: BEAS ( PMC NO. F) | C5: 1445.34 | D5: 0 | E5: 1445.34 | F5: 1554.8 | G5: 0 | H5: 1554.8 | I5: 1554.8 | J5: 0 | K5: 1554.8 | L5: 0 | M5: 0
A6: NYATI DEFENCE ENCLAVE III | B6: "G" (MHADA) | C6: 436.63 | D6: 0 | E6: 436.63 | F6: 417.65 | G6: 18.98 | H6: 436.63 | I6: 400.85 | J6: 35.78 | K6: 436.63 | L6: 16.8 | M6: 0
A7: NYATI DEFENCE ENCLAVE III | B7: BHISHMA ( PMC NO. B) | C7: 1868.35 | D7: 0 | E7: 1868.35 | F7: 1868.35 | G7: 0 | H7: 1868.35 | I7: 1868.35 | J7: 0 | K7: 1868.35 | L7: 0 | M7: 0
A8: NYATI DEFENCE ENCLAVE III | B8: ARJUN ( PMC NO. A) | C8: 1852.79 | D8: 0 | E8: 1852.79 | F8: 1852.79 | G8: 0 | H8: 1852.79 | I8: 1852.79 | J8: 0 | K8: 1852.79 | L8: 0 | M8: 0
A9: NYATI ELAN COMMERCIAL | B9: GROUND LEVEL OFFICE | C9: 1738.86 | D9: 0 | E9: 1738.86 | F9: 1646.68 | G9: 40 | H9: 1686.68 | I9: 1511.63 | J9: 76.27 | K9: 1587.9 | L9: 135.05 | M9: 98.78
A10: NYATI ELAN COMMERCIAL | B10: FIRST FLOOR OFFICE | C10: 966.72 | D10: 0 | E10: 966.72 | F10: 966.72 | G10: 0 | H10: 966.72 | I10: 966.65 | J10: 0 | K10: 966.65 | L10: 0.07 | M10: 0.07
A11: NYATI ELENOR | B11: A TOWER | C11: 15711.1 | D11: 584 | E11: 16295.1 | F11: 1387.63 | G11: 1057.18 | H11: 2444.81 | I11: 3504.17 | J11: 170.91 | K11: 3675.08 | L11: -2116.53 | M11: -1230.26
A12: NYATI ELENOR | B12: COMMERCIAL | C12: 2028 | D12: 0 | E12: 2028 | F12: 461.1 | G12: 0 | H12: 461.1 | I12: 986.5 | J12: 55.07 | K12: 1041.57 | L12: -525.4 | M12: -580.47
A13: NYATI ELENOR | B13: B TOWER | C13: 10048.62 | D13: 2056.84 | E13: 12105.46 | F13: 1085.07 | G13: 95.22 | H13: 1180.29 | I13: 1767.71 | J13: 269.52 | K13: 2037.23 | L13: -682.64 | M13: -856.93
... A89: NYATI PLAZA | B89: FOOD COURT 202 | C89: 526 | D89: 0 | E89: 526 | F89: 369.07 | G89: 0 | H89: 369.07 | I89: 389.07 | J89: 0 | K89: 389.07 | L89: -20 | M89: -20

Sheet Ageing Apr
A1: SrNo | B1: Project | C1: Building | D1: Unit | E1: Customer | F1: Booking_Date | G1: Registration_Date | H1: Agg_Value | I1: Claimed Value | J1: Received | K1: Total Outstanding | L1: 0-30 Days | M1: 31-60 Days | N1: 61-90 Days | O1: 91-120 Days | P1: > 120 Days | Q1: Regis Status
A2: 10767 | B2: NYATI ENTHRAL I | C2: OFFICE | D2: OFFICE - 1101 | E2: SHANKAR KISAN NIMBALKAR | F2: 45149 | G2: 01 Jan 1900 | H2: 85782000 | I2: 0 | J2: 36000000 | K2: -36000000 | L2: 0 | M2: 0 | N2: 0 | O2: 0 | P2: 0 | Q2: =IF(G2="01 Jan 1900","Unregistered","Registered") -> Unregistered
A3: 10766 | B3: NYATI EMBLEM | C3: G BUILDING | D3: G BUILDING UNIT NO 1802 | E3: SAMIR D SHELAR | F3: 45961 | G3: 01 Jan 1900 | H3: 35400000 | I3: 0 | J3: 31600000 | K3: -31600000 | L3: 0 | M3: 0 | N3: 0 | O3: 0 | P3: 0 | Q3: =IF(G3="01 Jan 1900","Unregistered","Registered") -> Unregistered
A4: 10765 | B4: NYATI ENTHRAL I | C4: OFFICE | D4: OFFICE - 1308 | E4: AAKAR SONS SHOPEE LLP | F4: 45686 | G4: 01 Jan 1900 | H4: 85400000 | I4: 0 | J4: 26000000 | K4: -26000000 | L4: 0 | M4: 0 | N4: 0 | O4: 0 | P4: 0 | Q4: =IF(G4="01 Jan 1900","Unregistered","Registered") -> Unregistered
A5: 10764 | B5: NYATI ELENOR | C5: B TOWER | D5: B TOWER -2802 | E5: MUKUL VARSHNEY | F5: 45990 | G5: 01 Jan 1900 | H5: 48829000 | I5: 0 | J5: 25000000 | K5: -25000000 | L5: 0 | M5: 0 | N5: 0 | O5: 0 | P5: 0 | Q5: =IF(G5="01 Jan 1900","Unregistered","Registered") -> Unregistered
A6: 10763 | B6: NYATI ELENOR | C6: B TOWER | D6: B TOWER - 1403 | E6: HITESH MADHUSUDAN MUNDHADA | F6: 46053 | G6: 29 Apr 2026 | H6: 40400000 | I6: 0 | J6: 23265000 | K6: -23265000 | L6: 0 | M6: 0 | N6: 0 | O6: 0 | P6: 0 | Q6: =IF(G6="01 Jan 1900","Unregistered","Registered") -> Registered
A7: 10761 | B7: NYATI ELENOR | C7: A TOWER | D7: A TOWER -1801 | E7: Ronak Gupta | F7: 45777 | G7: 01 Jan 1900 | H7: 37662175 | I7: 0 | J7: 20000000 | K7: -20000000 | L7: 0 | M7: 0 | N7: 0 | O7: 0 | P7: 0 | Q7: =IF(G7="01 Jan 1900","Unregistered","Registered") -> Unregistered
A8: 10762 | B8: NYATI ELENOR | C8: A TOWER | D8: A TOWER -1804 | E8: Swati Gupta | F8: 45777 | G8: 01 Jan 1900 | H8: 37662175 | I8: 0 | J8: 20000000 | K8: -20000000 | L8: 0 | M8: 0 | N8: 0 | O8: 0 | P8: 0 | Q8: =IF(G8="01 Jan 1900","Unregistered","Registered") -> Unregistered
A9: 10759 | B9: NYATI EMERALD I | C9: WING - H - COMM | D9: SHOP - H - 01 | E9: RITESH AMRUT MEHTA | F9: 45107 | G9: 01 Jan 1900 | H9: 25254000 | I9: 0 | J9: 17652000 | K9: -17652000 | L9: 0 | M9: 0 | N9: 0 | O9: 0 | P9: 0 | Q9: =IF(G9="01 Jan 1900","Unregistered","Registered") -> Unregistered
A10: 10758 | B10: NYATI EMERALD I | C10: WING - H - COMM | D10: SHOP - H - 03 | E10: RITESH AMRUT MEHTA | F10: 45107 | G10: 01 Jan 1900 | H10: 30294000 | I10: 0 | J10: 17252000 | K10: -17252000 | L10: 0 | M10: 0 | N10: 0 | O10: 0 | P10: 0 | Q10: =IF(G10="01 Jan 1900","Unregistered","Registered") -> Unregistered
A11: 10757 | B11: NYATI EMBLEM | C11: F BUILDING | D11: F BUILDING - UNIT NO.1302 | E11: KEDAR SHASHIKANT GOKHALE | F11: 45991 | G11: 27 Feb 2026 | H11: 45100000 | I11: 13530000 | J11: 30200000 | K11: -16670000 | L11: 0 | M11: 0 | N11: 0 | O11: 0 | P11: 0 | Q11: =IF(G11="01 Jan 1900","Unregistered","Registered") -> Registered
A12: 10756 | B12: NYATI EMERALD I | C12: WING - H - COMM | D12: SHOP - H - 02 | E12: GURPREET SINGH BHASIN | F12: 45107 | G12: 01 Jan 1900 | H12: 25155000 | I12: 0 | J12: 14904000 | K12: -14904000 | L12: 0 | M12: 0 | N12: 0 | O12: 0 | P12: 0 | Q12: =IF(G12="01 Jan 1900","Unregistered","Registered") -> Unregistered
A13: 10755 | B13: NYATI EVOQUE | C13: LAVENDER - (PMC NO. A1) | D13: LAVENDER - A 1 -2401 | E13: NEEL NAWANI | F13: 45625 | G13: 21 Mar 2025 | H13: 33598214 | I13: 16463125 | J13: 31279465 | K13: -14816340 | L13: 0 | M13: 0 | N13: 0 | O13: 0 | P13: 0 | Q13: =IF(G13="01 Jan 1900","Unregistered","Registered") -> Registered
... A332: 10203 | B332: NYATI EQUINOX II | C332: MIRA (PMC - B) | D332: MIRA - B -2504 | E332: Kaira Utpal Shah | F332: 45911 | G332: 01 Jan 1900 | H332: 4870560 | I332: 0 | J332: 100000 | K332: -100000 | L332: 0 | M332: 0 | N332: 0 | O332: 0 | P332: 0 | Q332: =IF(G332="01 Jan 1900","Unregistered","Registered") -> Unregistered
A333: 10204 | B333: NYATI ERA IV | C333: JOY - (PMC NO. WING J) | D333: JOY - J - 1104 | E333: GAURAV GULATI | F333: 46021 | G333: 1 | H333: 11300700 | I333: 0 | J333: 100000 | K333: -100000 | L333: 0 | M333: 0 | N333: 0 | O333: 0 | P333: 0 | Q333: =IF(G333="01 Jan 1900","Unregistered","Registered") -> Registered
A334: 10205 | B334: NYATI ESTEBAN II | C334: ALEXANDRITE (PMC - D5) | D334: ALEXANDRITE - D5 - 1002 | E334: BRAJESH SHARMA | F334: 46078 | G334: 10 Jun 2026 | H334: 9956140 | I334: 0 | J334: 100000 | K334: -100000 | L334: 0 | M334: 0 | N334: 0 | O334: 0 | P334: 0 | Q334: =IF(G334="01 Jan 1900","Unregistered","Registered") -> Registered
A335: 10206 | B335: NYATI ESTEBAN II | C335: ALEXANDRITE (PMC - D5) | D335: ALEXANDRITE - D5 - 1004 | E335: RAHUL BHATNAGAR | F335: 46111 | G335: 27 Apr 2026 | H335: 7038000 | I335: 0 | J335: 100000 | K335: -100000 | L335: 0 | M335: 0 | N335: 0 | O335: 0 | P335: 0 | Q335: =IF(G335="01 Jan 1900","Unregistered","Registered") -> Registered
A336: 10207 | B336: NYATI ESTEBAN II | C336: ALEXANDRITE (PMC - D5) | D336: ALEXANDRITE - D5 - 1401 | E336: HABIB GANI SHAIKH | F336: 46102 | G336: 14 May 2026 | H336: 10278950 | I336: 0 | J336: 100000 | K336: -100000 | L336: 0 | M336: 0 | N336: 0 | O336: 0 | P336: 0 | Q336: =IF(G336="01 Jan 1900","Unregistered","Registered") -> Registered
A337: 10208 | B337: NYATI ESTEBAN II | C337: ALEXANDRITE (PMC - D5) | D337: ALEXANDRITE - D5 - 1502 | E337: PRAJAKTA RAMESH SUKHADEVE | F337: 46111 | G337: 30 Apr 2026 | H337: 9940849 | I337: 0 | J337: 100000 | K337: -100000 | L337: 0 | M337: 0 | N337: 0 | O337: 0 | P337: 0 | Q337: =IF(G337="01 Jan 1900","Unregistered","Registered") -> Registered
A338: 10209 | B338: NYATI ESTEBAN II | C338: ALEXANDRITE (PMC - D5) | D338: ALEXANDRITE - D5 - 1703 | E338: JHARNA RASTOGI | F338: 46106 | G338: 05 May 2026 | H338: 6686100 | I338: 0 | J338: 100000 | K338: -100000 | L338: 0 | M338: 0 | N338: 0 | O338: 0 | P338: 0 | Q338: =IF(G338="01 Jan 1900","Unregistered","Registered") -> Registered
A339: 10210 | B339: NYATI ESTEBAN II | C339: ALEXANDRITE (PMC - D5) | D339: ALEXANDRITE - D5 - 1804 | E339: AMIT VIJAYRAO KAWALE | F339: 46111 | G339: 14 May 2026 | H339: 7100000 | I339: 0 | J339: 100000 | K339: -100000 | L339: 0 | M339: 0 | N339: 0 | O339: 0 | P339: 0 | Q339: =IF(G339="01 Jan 1900","Unregistered","Registered") -> Registered
A340: 10211 | B340: NYATI ESTEBAN II | C340: ALEXANDRITE (PMC - D5) | D340: ALEXANDRITE - D5 - 1901 | E340: SWATI MISHRA | F340: 46102 | G340: 16 Apr 2026 | H340: 9959609 | I340: 0 | J340: 100000 | K340: -100000 | L340: 0 | M340: 0 | N340: 0 | O340: 0 | P340: 0 | Q340: =IF(G340="01 Jan 1900","Unregistered","Registered") -> Registered
A341: 10212 | B341: NYATI ESTEBAN II | C341: ALEXANDRITE (PMC - D5) | D341: ALEXANDRITE - D5 - 2004 | E341: ANISH KUMAR | F341: 46111 | G341: 22 May 2026 | H341: 7038000 | I341: 0 | J341: 100000 | K341: -100000 | L341: 0 | M341: 0 | N341: 0 | O341: 0 | P341: 0 | Q341: =IF(G341="01 Jan 1900","Unregistered","Registered") -> Registered
A342: 10213 | B342: NYATI ESTEBAN II | C342: ALEXANDRITE (PMC - D5) | D342: ALEXANDRITE - D5 - 404 | E342: HEMANT PANDEY | F342: 46112 | G342: 01 Jan 1900 | H342: 6600259 | I342: 0 | J342: 100000 | K342: -100000 | L342: 0 | M342: 0 | N342: 0 | O342: 0 | P342: 0 | Q342: =IF(G342="01 Jan 1900","Unregistered","Registered") -> Unregistered
A343: 10214 | B343: NYATI ESTEBAN II | C343: ALEXANDRITE (PMC - D5) | D343: ALEXANDRITE - D5 - 904 | E343: ROHINI RAVINDRA SHINDE | F343: 46102 | G343: 21 Apr 2026 | H343: 6730796 | I343: 0 | J343: 100000 | K343: -100000 | L343: 0 | M343: 0 | N343: 0 | O343: 0 | P343: 0 | Q343: =IF(G343="01 Jan 1900","Unregistered","Registered") -> Registered
A344: 10215 | B344: NYATI ESTEBAN II | C344: PEARL (PMC - D1) | D344: PEARL - D1 - 2703 | E344: SAYRA BANO | F344: 46081 | G344: 29 Apr 2026 | H344: 7074363 | I344: 0 | J344: 100000 | K344: -100000 | L344: 0 | M344: 0 | N344: 0 | O344: 0 | P344: 0 | Q344: =IF(G344="01 Jan 1900","Unregistered","Registered") -> Registered
A345: 10216 | B345: NYATI ESTEBAN II | C345: PEARL (PMC - D1) | D345: PEARL - D1 - 2802 | E345: RALPH ROHIT SHAW | F345: 46108 | G345: 30 Apr 2026 | H345: 10136448 | I345: 0 | J345: 100000 | K345: -100000 | L345: 0 | M345: 0 | N345: 0 | O345: 0 | P345: 0 | Q345: =IF(G345="01 Jan 1900","Unregistered","Registered") -> Registered
... A508: 1733 | B508: NYATI DEFENCE ENCLAVE III | C508: BHISHMA ( PMC NO. B) | D508: BHISHMA - B - 702 | E508: NEELESH KUMAR JHA | F508: 45183 | G508: 26 Dec 2023 | H508: 13740800 | I508: 13740800 | J508: 13740800 | K508: 0 | L508: 0 | M508: 0 | N508: 0 | O508: 0 | P508: 0 | Q508: =IF(G508="01 Jan 1900","Unregistered","Registered") -> Registered
A509: 10776 | B509: NYATI DEFENCE ENCLAVE III | C509: "G" (MHADA) | D509: G -1 | E509: PATHAN SAMAD HAMID | F509: 46164 | G509: 01 Jan 1900 | H509: 1627000 | I509: 0 | L509: 0 | M509: 0 | N509: 0 | O509: 0 | P509: 0 | Q509: =IF(G509="01 Jan 1900","Unregistered","Registered") -> Unregistered
A510: 3083 | B510: NYATI ELAN COMMERCIAL | C510: FIRST FLOOR OFFICE | D510: SHOP -115 | E510: VISHNU PRIYA | F510: 44739 | G510: 23 Mar 2023 | H510: 2057000 | I510: 2057000 | J510: 2057000 | K510: 0 | L510: 0 | M510: 0 | N510: 0 | O510: 0 | P510: 0 | Q510: =IF(G510="01 Jan 1900","Unregistered","Registered") -> Registered
A511: 3084 | B511: NYATI ELAN COMMERCIAL | C511: FIRST FLOOR OFFICE | D511: SHOP - 102 | E511: MRITYUNJAY DUDHNATH TIWARI | F511: 44078 | G511: 09 Oct 2020 | H511: 2000000 | I511: 2000000 | J511: 2000000 | K511: 0 | L511: 0 | M511: 0 | N511: 0 | O511: 0 | P511: 0 | Q511: =IF(G511="01 Jan 1900","Unregistered","Registered") -> Registered
A512: 3085 | B512: NYATI ELAN COMMERCIAL | C512: FIRST FLOOR OFFICE | D512: SHOP - 103 | E512: NUTAN KISHANCHAND SONAR | F512: 44408 | G512: 08 Sep 2021 | H512: 2121698 | I512: 2121698 | J512: 2121698 | K512: 0 | L512: 0 | M512: 0 | N512: 0 | O512: 0 | P512: 0 | Q512: =IF(G512="01 Jan 1900","Unregistered","Registered") -> Registered
A513: 3086 | B513: NYATI ELAN COMMERCIAL | C513: FIRST FLOOR OFFICE | D513: SHOP - 104 | E513: JYOTI KISHANCHAND DHARMANI | F513: 44663 | G513: 27 Jun 2022 | H513: 2019600 | I513: 2019600 | J513: 2019600 | K513: 0 | L513: 0 | M513: 0 | N513: 0 | O513: 0 | P513: 0 | Q513: =IF(G513="01 Jan 1900","Unregistered","Registered") -> Registered
A514: 3087 | B514: NYATI ELAN COMMERCIAL | C514: FIRST FLOOR OFFICE | D514: SHOP - 105 | E514: KIRAN KUMAR GANJI | F514: 44522 | G514: 17 Feb 2022 | H514: 1870000 | I514: 1870000 | J514: 1870000 | K514: 0 | L514: 0 | M514: 0 | N514: 0 | O514: 0 | P514: 0 | Q514: =IF(G514="01 Jan 1900","Unregistered","Registered") -> Registered
A515: 3088 | B515: NYATI ELAN COMMERCIAL | C515: FIRST FLOOR OFFICE | D515: SHOP - 106 | E515: Rajesh Satyanarayan Bolli | F515: 42509 | G515: 06 Jun 2018 | H515: 2100000 | I515: 2100000 | J515: 2100000 | K515: 0 | L515: 0 | M515: 0 | N515: 0 | O515: 0 | P515: 0 | Q515: =IF(G515="01 Jan 1900","Unregistered","Registered") -> Registered
A516: 3089 | B516: NYATI ELAN COMMERCIAL | C516: FIRST FLOOR OFFICE | D516: SHOP - 107 | E516: SATHEESH KUMAR SURESH | F516: 44500 | G516: 15 Nov 2021 | H516: 2030000 | I516: 2030000 | J516: 2030000 | K516: 0 | L516: 0 | M516: 0 | N516: 0 | O516: 0 | P516: 0 | Q516: =IF(G516="01 Jan 1900","Unregistered","Registered") -> Registered
A517: 3090 | B517: NYATI ELAN COMMERCIAL | C517: FIRST FLOOR OFFICE | D517: SHOP - 108 | E517: CHINNIAH DHARMALINGAM | F517: 44500 | G517: 15 Nov 2021 | H517: 2030000 | I517: 2030000 | J517: 2030000 | K517: 0 | L517: 0 | M517: 0 | N517: 0 | O517: 0 | P517: 0 | Q517: =IF(G517="01 Jan 1900","Unregistered","Registered") -> Registered
A518: 3091 | B518: NYATI ELAN COMMERCIAL | C518: FIRST FLOOR OFFICE | D518: SHOP - 109 | E518: GORAKH ANNASAHEB MANAL | F518: 44404 | G518: 02 Aug 2021 | H518: 2451650 | I518: 2451650 | J518: 2451650 | K518: 0 | L518: 0 | M518: 0 | N518: 0 | O518: 0 | P518: 0 | Q518: =IF(G518="01 Jan 1900","Unregistered","Registered") -> Registered
A519: 3092 | B519: NYATI ELAN COMMERCIAL | C519: FIRST FLOOR OFFICE | D519: SHOP - 110 | E519: ANIL KUMAR SAH | F519: 43645 | G519: 31 Mar 2022 | H519: 2935900 | I519: 2935900 | J519: 2935900 | K519: 0 | L519: 0 | M519: 0 | N519: 0 | O519: 0 | P519: 0 | Q519: =IF(G519="01 Jan 1900","Unregistered","Registered") -> Registered
A520: 3093 | B520: NYATI ELAN COMMERCIAL | C520: FIRST FLOOR OFFICE | D520: SHOP - 111 | E520: SULAKSHANA RAMDAS SHINGADE | F520: 44628 | G520: 24 May 2022 | H520: 1932832 | I520: 1932832 | J520: 1932832 | K520: 0 | L520: 0 | M520: 0 | N520: 0 | O520: 0 | P520: 0 | Q520: =IF(G520="01 Jan 1900","Unregistered","Registered") -> Registered
A521: 3094 | B521: NYATI ELAN COMMERCIAL | C521: FIRST FLOOR OFFICE | D521: SHOP - 112 | E521: RAMDAS SOPAN SHINGADE | F521: 44628 | G521: 23 May 2022 | H521: 1932832 | I521: 1932832 | J521: 1932832 | K521: 0 | L521: 0 | M521: 0 | N521: 0 | O521: 0 | P521: 0 | Q521: =IF(G521="01 Jan 1900","Unregistered","Registered") -> Registered
... A586: 3987 | B586: NYATI ELENOR | C586: B TOWER | D586: B TOWER -2103 | E586: VIDYA VINOD SATAV | F586: 45944 | G586: 18 Oct 2025 | H586: 32600000 | I586: 9780000 | J586: 9780000 | K586: 0 | L586: 0 | M586: 0 | N586: 0 | O586: 0 | P586: 0 | Q586: =IF(G586="01 Jan 1900","Unregistered","Registered") -> Registered
A587: 10782 | B587: NYATI ELENOR | C587: A TOWER | D587: A TOWER -1004 | E587: Bharat Vinod shah | F587: 46168 | G587: 01 Jan 1900 | H587: 34300000 | I587: 0 | L587: 0 | M587: 0 | N587: 0 | O587: 0 | P587: 0 | Q587: =IF(G587="01 Jan 1900","Unregistered","Registered") -> Unregistered
A588: 10783 | B588: NYATI ELENOR | C588: A TOWER | D588: A TOWER -1204 | E588: BHARAT MOHANLAL PAREKH | F588: 46132 | G588: 20 Apr 2026 | H588: 32600000 | I588: 0 | L588: 0 | M588: 0 | N588: 0 | O588: 0 | P588: 0 | Q588: =IF(G588="01 Jan 1900","Unregistered","Registered") -> Registered
A589: 10784 | B589: NYATI ELENOR | C589: A TOWER | D589: A TOWER -1303 | E589: MUKESH OSWAL | F589: 46195 | G589: 01 Jan 1900 | H589: 25200000 | I589: 0 | L589: 0 | M589: 0 | N589: 0 | O589: 0 | P589: 0 | Q589: =IF(G589="01 Jan 1900","Unregistered","Registered") -> Unregistered
A590: 10785 | B590: NYATI ELENOR | C590: A TOWER | D590: A TOWER -1401 | E590: Kejal Mehta | F590: 46173 | G590: 01 Jan 1900 | H590: 32700000 | I590: 0 | L590: 0 | M590: 0 | N590: 0 | O590: 0 | P590: 0 | Q590: =IF(G590="01 Jan 1900","Unregistered","Registered") -> Unregistered
A591: 10786 | B591: NYATI ELENOR | C591: A TOWER | D591: A TOWER -1601 | E591: Bharti Shah | F591: 46170 | G591: 01 Jan 1900 | H591: 26800000 | I591: 0 | L591: 0 | M591: 0 | N591: 0 | O591: 0 | P591: 0 | Q591: =IF(G591="01 Jan 1900","Unregistered","Registered") -> Unregistered
A592: 10787 | B592: NYATI ELENOR | C592: A TOWER | D592: A TOWER -1602 | E592: MAHAVEER KOTHARI | F592: 46168 | G592: 01 Jan 1900 | H592: 28200000 | I592: 0 | L592: 0 | M592: 0 | N592: 0 | O592: 0 | P592: 0 | Q592: =IF(G592="01 Jan 1900","Unregistered","Registered") -> Unregistered
A593: 10788 | B593: NYATI ELENOR | C593: A TOWER | D593: A TOWER -1901 | E593: PRADEEP SOLANKI | F593: 46168 | G593: 01 Jan 1900 | H593: 33500000 | I593: 0 | L593: 0 | M593: 0 | N593: 0 | O593: 0 | P593: 0 | Q593: =IF(G593="01 Jan 1900","Unregistered","Registered") -> Unregistered
A594: 10789 | B594: NYATI ELENOR | C594: A TOWER | D594: A TOWER -2101 | E594: UTTAMCHAND KOTHARI | F594: 46168 | G594: 01 Jan 1900 | H594: 31100000 | I594: 0 | L594: 0 | M594: 0 | N594: 0 | O594: 0 | P594: 0 | Q594: =IF(G594="01 Jan 1900","Unregistered","Registered") -> Unregistered
A595: 10790 | B595: NYATI ELENOR | C595: A TOWER | D595: A TOWER -2404 | E595: DINESH PRAVIN PALRECHA | F595: 46148 | G595: 15 May 2026 | H595: 33500000 | I595: 0 | L595: 0 | M595: 0 | N595: 0 | O595: 0 | P595: 0 | Q595: =IF(G595="01 Jan 1900","Unregistered","Registered") -> Registered
A596: 10791 | B596: NYATI ELENOR | C596: A TOWER | D596: A TOWER -2601 | E596: Trupti Manish Dudhedia | F596: 46147 | G596: 01 Jan 1900 | H596: 33705000 | I596: 0 | L596: 0 | M596: 0 | N596: 0 | O596: 0 | P596: 0 | Q596: =IF(G596="01 Jan 1900","Unregistered","Registered") -> Unregistered
A597: 10792 | B597: NYATI ELENOR | C597: A TOWER | D597: A TOWER -3001 | E597: SAGAR SHAH | F597: 46170 | H597: 26800000 | I597: 0 | L597: 0 | M597: 0 | N597: 0 | O597: 0 | P597: 0 | Q597: =IF(G597="01 Jan 1900","Unregistered","Registered") -> Registered
A598: 10793 | B598: NYATI ELENOR | C598: A TOWER | D598: A TOWER -803 | E598: RAGHUBIR SINGH SALUJA | F598: 46130 | G598: 01 Jan 1900 | H598: 25800000 | I598: 0 | L598: 0 | M598: 0 | N598: 0 | O598: 0 | P598: 0 | Q598: =IF(G598="01 Jan 1900","Unregistered","Registered") -> Unregistered
A599: 10794 | B599: NYATI ELENOR | C599: B TOWER | D599: B TOWER - 1202 | E599: Sanjay Babulal Oswal | F599: 46140 | G599: 01 Jan 1900 | H599: 41000000 | I599: 0 | L599: 0 | M599: 0 | N599: 0 | O599: 0 | P599: 0 | Q599: =IF(G599="01 Jan 1900","Unregistered","Registered") -> Unregistered
A600: 10795 | B600: NYATI ELENOR | C600: B TOWER | D600: B TOWER - 1203 | E600: ANSHUMAN NAGESH SETH | F600: 46130 | G600: 01 Jan 1900 | H600: 44600000 | I600: 0 | L600: 0 | M600: 0 | N600: 0 | O600: 0 | P600: 0 | Q600: =IF(G600="01 Jan 1900","Unregistered","Registered") -> Unregistered
A601: 10796 | B601: NYATI ELENOR | C601: B TOWER | D601: B TOWER - 1303 | E601: KAPIL BINAKIYA | F601: 46147 | G601: 01 Jan 1900 | H601: 40687500 | I601: 0 | L601: 0 | M601: 0 | N601: 0 | O601: 0 | P601: 0 | Q601: =IF(G601="01 Jan 1900","Unregistered","Registered") -> Unregistered
A602: 10797 | B602: NYATI ELENOR | C602: B TOWER | D602: B TOWER - 902 | E602: VINITA NITIN BAFANA | F602: 46193 | G602: 24 Jun 2026 | H602: 49000000 | I602: 0 | L602: 0 | M602: 0 | N602: 0 | O602: 0 | P602: 0 | Q602: =IF(G602="01 Jan 1900","Unregistered","Registered") -> Registered
A603: 10798 | B603: NYATI ELENOR | C603: B TOWER | D603: B TOWER -1703 | E603: Ritesh Pravin Palrecha | F603: 46148 | G603: 01 Jan 1900 | H603: 33500000 | I603: 0 | L603: 0 | M603: 0 | N603: 0 | O603: 0 | P603: 0 | Q603: =IF(G603="01 Jan 1900","Unregistered","Registered") -> Unregistered
A604: 10799 | B604: NYATI ELENOR | C604: B TOWER | D604: B TOWER -2101 | E604: Akshay Sureshkumar Jain | F604: 46195 | G604: 01 Jan 1900 | H604: 25250000 | I604: 0 | L604: 0 | M604: 0 | N604: 0 | O604: 0 | P604: 0 | Q604: =IF(G604="01 Jan 1900","Unregistered","Registered") -> Unregistered
A605: 10800 | B605: NYATI ELENOR | C605: B TOWER | D605: B TOWER -2202 | E605: LALIT OSWAL | F605: 46140 | G605: 01 Jan 1900 | H605: 41000000 | I605: 0 | L605: 0 | M605: 0 | N605: 0 | O605: 0 | P605: 0 | Q605: =IF(G605="01 Jan 1900","Unregistered","Registered") -> Unregistered
A606: 10801 | B606: NYATI ELENOR | C606: B TOWER | D606: B TOWER -2302 | E606: DEEPENDER SINGH RAJPAL | F606: 46140 | G606: 01 Jan 1900 | H606: 40400000 | I606: 0 | L606: 0 | M606: 0 | N606: 0 | O606: 0 | P606: 0 | Q606: =IF(G606="01 Jan 1900","Unregistered","Registered") -> Unregistered
A607: 10802 | B607: NYATI ELENOR | C607: B TOWER | D607: B TOWER -2303 | E607: VINESH OSWAL | F607: 46195 | G607: 01 Jan 1900 | H607: 32600000 | I607: 0 | L607: 0 | M607: 0 | N607: 0 | O607: 0 | P607: 0 | Q607: =IF(G607="01 Jan 1900","Unregistered","Registered") -> Unregistered
A608: 10803 | B608: NYATI ELENOR | C608: B TOWER | D608: B TOWER -2902 | E608: SMITA MAHINDRA KOTHARI | F608: 46140 | G608: 01 Jan 1900 | H608: 38683800 | I608: 0 | L608: 0 | M608: 0 | N608: 0 | O608: 0 | P608: 0 | Q608: =IF(G608="01 Jan 1900","Unregistered","Registered") -> Unregistered
A609: 5068 | B609: NYATI EMBLEM | C609: F BUILDING | D609: F BUILDING - UNIT NO.1202 | E609: RAJENDRA RAMKRISHNA KULKARNI | F609: 46092 | G609: 26 Mar 2026 | H609: 44459821 | I609: 13337946 | J609: 13337946 | K609: 0 | L609: 0 | M609: 0 | N609: 0 | O609: 0 | P609: 0 | Q609: =IF(G609="01 Jan 1900","Unregistered","Registered") -> Registered
A610: 5069 | B610: NYATI EMBLEM | C610: F BUILDING | D610: F BUILDING - UNIT NO.1402 | E610: VAIBHAV SUBHASH MITHARE | F610: 45525 | G610: 22 Apr 2025 | H610: 33000000 | I610: 9900000 | J610: 9900000 | K610: 0 | L610: 0 | M610: 0 | N610: 0 | O610: 0 | P610: 0 | Q610: =IF(G610="01 Jan 1900","Unregistered","Registered") -> Registered
A611: 5070 | B611: NYATI EMBLEM | C611: F BUILDING | D611: F BUILDING - UNIT NO.1502 | E611: SHIVRAJ SUBHASH MITHARE | F611: 45525 | G611: 22 Apr 2025 | H611: 33000000 | I611: 9900000 | J611: 9900000 | K611: 0 | L611: 0 | M611: 0 | N611: 0 | O611: 0 | P611: 0 | Q611: =IF(G611="01 Jan 1900","Unregistered","Registered") -> Registered
A612: 5071 | B612: NYATI EMBLEM | C612: F BUILDING | D612: F BUILDING - UNIT NO.802 | E612: CHARUDATTA RAMKRISHNA KULKARNI | F612: 46092 | G612: 20 Mar 2026 | H612: 44459821 | I612: 15389938 | J612: 15389938 | K612: 0 | L612: 0 | M612: 0 | N612: 0 | O612: 0 | P612: 0 | Q612: =IF(G612="01 Jan 1900","Unregistered","Registered") -> Registered
A613: 5072 | B613: NYATI EMBLEM | C613: F BUILDING | D613: F BUILDING - UNIT NO.901 | E613: PRANAV VINAY MUNDI | F613: 45565 | G613: 09 Jan 2025 | H613: 38969400 | I613: 11690820 | J613: 11690820 | K613: 0 | L613: 0 | M613: 0 | N613: 0 | O613: 0 | P613: 0 | Q613: =IF(G613="01 Jan 1900","Unregistered","Registered") -> Registered
A614: 10804 | B614: NYATI EMBLEM | C614: F BUILDING | D614: F BUILDING - UNIT NO.1401 | E614: VINAY ZUMBERLAL BALDOTA | F614: 46199 | G614: 01 Jan 1900 | H614: 39000000 | I614: 0 | L614: 0 | M614: 0 | N614: 0 | O614: 0 | P614: 0 | Q614: =IF(G614="01 Jan 1900","Unregistered","Registered") -> Unregistered
A615: 10805 | B615: NYATI EMBLEM | C615: F BUILDING | D615: F BUILDING - UNIT NO.2402 | E615: SHWETA RAVIRAJ LAYGUDE | F615: 46142 | G615: 01 Jan 1900 | H615: 45700000 | I615: 0 | L615: 0 | M615: 0 | N615: 0 | O615: 0 | P615: 0 | Q615: =IF(G615="01 Jan 1900","Unregistered","Registered") -> Unregistered
A616: 10806 | B616: NYATI EMBLEM | C616: F BUILDING | D616: F BUILDING - UNIT NO.702 | E616: BHAVESH VIJAYKUMAR RAYSONI | F616: 46173 | G616: 01 Jan 1900 | H616: 36500000 | I616: 0 | L616: 0 | M616: 0 | N616: 0 | O616: 0 | P616: 0 | Q616: =IF(G616="01 Jan 1900","Unregistered","Registered") -> Unregistered
A617: 5073 | B617: NYATI EMERALD I | C617: AQUAMARINE - (PMC - A1) | D617: AQUAMARINE - A1 - 1002 | E617: NIKHIL MORESHWAR KATEKHAYE | F617: 45142 | G617: 11 Sep 2023 | H617: 8169643 | I617: 6535715 | J617: 6535715 | K617: 0 | L617: 0 | M617: 0 | N617: 0 | O617: 0 | P617: 0 | Q617: =IF(G617="01 Jan 1900","Unregistered","Registered") -> Registered
A618: 5074 | B618: NYATI EMERALD I | C618: AQUAMARINE - (PMC - A1) | D618: AQUAMARINE - A1 - 1003 | E618: VISHWAMBHAR PRABHAKAR PATIL | F618: 45176 | G618: 07 Nov 2023 | H618: 12008929 | I618: 9607143 | J618: 9607143 | K618: 0 | L618: 0 | M618: 0 | N618: 0 | O618: 0 | P618: 0 | Q618: =IF(G618="01 Jan 1900","Unregistered","Registered") -> Registered
A619: 5075 | B619: NYATI EMERALD I | C619: AQUAMARINE - (PMC - A1) | D619: AQUAMARINE - A1 - 1101 | E619: RASHMI KUMARI | F619: 45138 | G619: 10 Oct 2024 | H619: 8152350 | I619: 6521882 | J619: 6521882 | K619: 0 | L619: 0 | M619: 0 | N619: 0 | O619: 0 | P619: 0 | Q619: =IF(G619="01 Jan 1900","Unregistered","Registered") -> Registered
A620: 5076 | B620: NYATI EMERALD I | C620: AQUAMARINE - (PMC - A1) | D620: AQUAMARINE - A1 - 1104 | E620: SOMESH KUMAR | F620: 45135 | G620: 19 Aug 2023 | H620: 11970900 | I620: 9576720 | J620: 9576720 | K620: 0 | L620: 0 | M620: 0 | N620: 0 | O620: 0 | P620: 0 | Q620: =IF(G620="01 Jan 1900","Unregistered","Registered") -> Registered
A621: 5077 | B621: NYATI EMERALD I | C621: AQUAMARINE - (PMC - A1) | D621: AQUAMARINE - A1 - 1201 | E621: AMRUTA PATIDAR | F621: 45094 | G621: 07 Aug 2023 | H621: 8258929 | I621: 6607143 | J621: 6607143 | K621: 0 | L621: 0 | M621: 0 | N621: 0 | O621: 0 | P621: 0 | Q621: =IF(G621="01 Jan 1900","Unregistered","Registered") -> Registered
A622: 5078 | B622: NYATI EMERALD I | C622: AQUAMARINE - (PMC - A1) | D622: AQUAMARINE - A1 - 1203 | E622: PRASHANT SATISH GHAM | F622: 45104 | G622: 24 Jul 2023 | H622: 11831664 | I622: 9465332 | J622: 9465332 | K622: 0 | L622: 0 | M622: 0 | N622: 0 | O622: 0 | P622: 0 | Q622: =IF(G622="01 Jan 1900","Unregistered","Registered") -> Registered
A623: 5079 | B623: NYATI EMERALD I | C623: AQUAMARINE - (PMC - A1) | D623: AQUAMARINE - A1 - 1204 | E623: DEEPA NAGDEV | F623: 45100 | G623: 12 Jul 2023 | H623: 11563380 | I623: 9250704 | J623: 9250704 | K623: 0 | L623: 0 | M623: 0 | N623: 0 | O623: 0 | P623: 0 | Q623: =IF(G623="01 Jan 1900","Unregistered","Registered") -> Registered
A624: 5080 | B624: NYATI EMERALD I | C624: AQUAMARINE - (PMC - A1) | D624: AQUAMARINE - A1 - 1301 | E624: NILKANTH BHAGWAN LAHANE | F624: 45523 | G624: 21 Aug 2024 | H624: 8983036 | I624: 7186428 | J624: 7186428 | K624: 0 | L624: 0 | M624: 0 | N624: 0 | O624: 0 | P624: 0 | Q624: =IF(G624="01 Jan 1900","Unregistered","Registered") -> Registered
A625: 5081 | B625: NYATI EMERALD I | C625: AQUAMARINE - (PMC - A1) | D625: AQUAMARINE - A1 - 1302 | E625: AJAY PRAMOD BHAGAT | F625: 45176 | G625: 27 Oct 2023 | H625: 8188396 | I625: 6550719 | J625: 6550719 | K625: 0 | L625: 0 | M625: 0 | N625: 0 | O625: 0 | P625: 0 | Q625: =IF(G625="01 Jan 1900","Unregistered","Registered") -> Registered
A626: 5082 | B626: NYATI EMERALD I | C626: AQUAMARINE - (PMC - A1) | D626: AQUAMARINE - A1 - 1304 | E626: KUNAL ANAND TALOKAR | F626: 45103 | G626: 14 Jul 2023 | H626: 11563380 | I626: 9250704 | J626: 9250704 | K626: 0 | L626: 0 | M626: 0 | N626: 0 | O626: 0 | P626: 0 | Q626: =IF(G626="01 Jan 1900","Unregistered","Registered") -> Registered
A627: 5083 | B627: NYATI EMERALD I | C627: AQUAMARINE - (PMC - A1) | D627: AQUAMARINE - A1 - 1401 | E627: NITIN TRIVEDI | F627: 45404 | G627: 29 May 2024 | H627: 8621550 | I627: 6897242 | J627: 6897242 | K627: 0 | L627: 0 | M627: 0 | N627: 0 | O627: 0 | P627: 0 | Q627: =IF(G627="01 Jan 1900","Unregistered","Registered") -> Registered
A628: 5084 | B628: NYATI EMERALD I | C628: AQUAMARINE - (PMC - A1) | D628: AQUAMARINE - A1 - 1402 | E628: PURVI NIMISH ZAVERI | F628: 45117 | G628: 03 Aug 2023 | H628: 8152350 | I628: 6521882 | J628: 6521882 | K628: 0 | L628: 0 | M628: 0 | N628: 0 | O628: 0 | P628: 0 | Q628: =IF(G628="01 Jan 1900","Unregistered","Registered") -> Registered
... A991: 5447 | B991: NYATI EMERALD I | C991: SAPPHIRE - (PMC - A2) | D991: SAPPHIRE - A2 - 604 | E991: GIRISH N LAKHMAPURE | F991: 45194 | G991: 27 Sep 2023 | H991: 11784120 | I991: 10016502 | J991: 10016502 | K991: 0 | L991: 0 | M991: 0 | N991: 0 | O991: 0 | P991: 0 | Q991: =IF(G991="01 Jan 1900","Unregistered","Registered") -> Registered
A992: 10807 | B992: NYATI EMERALD I | C992: BERYL - (PMC - B1) | D992: BERYL - B1 - 2901 | E992: VARUN SINGLA | F992: 46195 | G992: 01 Jan 1900 | H992: 10266071 | I992: 0 | L992: 0 | M992: 0 | N992: 0 | O992: 0 | P992: 0 | Q992: =IF(G992="01 Jan 1900","Unregistered","Registered") -> Unregistered
A993: 10808 | B993: NYATI EMERALD I | C993: BERYL - (PMC - B1) | D993: BERYL - B1 - 503 | E993: SHWETA UPADHYAY | F993: 46133 | G993: 05 May 2026 | H993: 14016990 | I993: 0 | L993: 0 | M993: 0 | N993: 0 | O993: 0 | P993: 0 | Q993: =IF(G993="01 Jan 1900","Unregistered","Registered") -> Registered
A994: 10810 | B994: NYATI EMERALD I | C994: EMERALD SHOP | D994: SHOP - A3 -28 | E994: RAGHUBIR SINGH SALUJA | F994: 46195 | G994: 01 Jan 1900 | H994: 45100000 | I994: 0 | L994: 0 | M994: 0 | N994: 0 | O994: 0 | P994: 0 | Q994: =IF(G994="01 Jan 1900","Unregistered","Registered") -> Unregistered
A995: 10811 | B995: NYATI EMERALD I | C995: SAPPHIRE - (PMC - A2) | D995: SAPPHIRE - A2 - 101 PREMIUM PNN FLAT | E995: VAISHNAVI KULKARNI | F995: 46162 | G995: 01 Jan 1900 | H995: 9911850 | I995: 0 | L995: 0 | M995: 0 | N995: 0 | O995: 0 | P995: 0 | Q995: =IF(G995="01 Jan 1900","Unregistered","Registered") -> Unregistered
A996: 5448 | B996: NYATI EMERALD II | C996: MHADA | D996: F BUILDING -801 | E996: SUBHASH SITARAM CHAUGULE | F996: 45784 | G996: 19 May 2025 | H996: 2217900 | I996: 1441635 | J996: 1441635 | K996: 0 | L996: 0 | M996: 0 | N996: 0 | O996: 0 | P996: 0 | Q996: =IF(G996="01 Jan 1900","Unregistered","Registered") -> Registered
A997: 10813 | B997: NYATI EMERALD II | C997: MHADA | D997: F BUILDING -404 | E997: BALAJI VISHWANATH KAKDE | F997: 46188 | G997: 01 Jan 1900 | H997: 2217900 | I997: 0 | L997: 0 | M997: 0 | N997: 0 | O997: 0 | P997: 0 | Q997: =IF(G997="01 Jan 1900","Unregistered","Registered") -> Unregistered
A998: 10815 | B998: NYATI EMERALD II | C998: MHADA | D998: F BUILDING -901 | E998: SHRIKRUSHANA DATTOPANT MULAVEKAR | F998: 46164 | G998: 26 May 2026 | H998: 2217900 | I998: 0 | L998: 0 | M998: 0 | N998: 0 | O998: 0 | P998: 0 | Q998: =IF(G998="01 Jan 1900","Unregistered","Registered") -> Registered
A999: 5449 | B999: NYATI EMERALD III | C999: AGATE - (PMC NO - D1) | D999: AGATE - D1 -1803 | E999: SHREENAD SUDHIR BHINGARDE | F999: 46052 | G999: 05 Mar 2026 | H999: 14489286 | I999: 2897857 | J999: 2897857 | K999: 0 | L999: 0 | M999: 0 | N999: 0 | O999: 0 | P999: 0 | Q999: =IF(G999="01 Jan 1900","Unregistered","Registered") -> Registered
A1000: 5450 | B1000: NYATI EMERALD III | C1000: AGATE - (PMC NO - D1) | D1000: AGATE - D1 -2102 | E1000: SATYENMITRA MOTWANI | F1000: 46045 | G1000: 12 Feb 2026 | H1000: 9501300 | I1000: 4275585 | J1000: 4275585 | K1000: 0 | L1000: 0 | M1000: 0 | N1000: 0 | O1000: 0 | P1000: 0 | Q1000: =IF(G1000="01 Jan 1900","Unregistered","Registered") -> Registered
A1001: 5451 | B1001: NYATI EMERALD III | C1001: RUBY - (PMC NO - C2) | D1001: RUBY - C2 -2702 | E1001: SONIA ANAND | F1001: 45985 | G1001: 16 Dec 2025 | H1001: 9321622 | I1001: 7923379 | J1001: 7923379 | K1001: 0 | L1001: 0 | M1001: 0 | N1001: 0 | O1001: 0 | P1001: 0 | Q1001: =IF(G1001="01 Jan 1900","Unregistered","Registered") -> Registered
A1002: 5452 | B1002: NYATI EMERALD III | C1002: TOPAZ - (PMC NO - C3) | D1002: TOPAZ - C3 -1003 | E1002: MADHURI NIKHIL JANBANDHU | F1002: 45987 | G1002: 10 Jan 2026 | H1002: 13980357 | I1002: 8528017 | J1002: 8528017 | K1002: 0 | L1002: 0 | M1002: 0 | N1002: 0 | O1002: 0 | P1002: 0 | Q1002: =IF(G1002="01 Jan 1900","Unregistered","Registered") -> Registered
A1003: 5453 | B1003: NYATI EMERALD III | C1003: TOPAZ - (PMC NO - C3) | D1003: TOPAZ - C3 -1004 | E1003: SHITAL KIRAN THORAT | F1003: 45976 | G1003: 05 Jan 2026 | H1003: 13881549 | I1003: 7634851 | J1003: 7634851 | K1003: 0 | L1003: 0 | M1003: 0 | N1003: 0 | O1003: 0 | P1003: 0 | Q1003: =IF(G1003="01 Jan 1900","Unregistered","Registered") -> Registered
A1004: 5454 | B1004: NYATI EMERALD III | C1004: TOPAZ - (PMC NO - C3) | D1004: TOPAZ - C3 -1404 | E1004: MRUNALI MUKUND JOSHI | F1004: 46001 | G1004: 10 Jan 2026 | H1004: 13569100 | I1004: 7734387 | J1004: 7734387 | K1004: 0 | L1004: 0 | M1004: 0 | N1004: 0 | O1004: 0 | P1004: 0 | Q1004: =IF(G1004="01 Jan 1900","Unregistered","Registered") -> Registered
A1005: 5455 | B1005: NYATI EMERALD III | C1005: TOPAZ - (PMC NO - C3) | D1005: TOPAZ - C3 -1801 | E1005: VAISHALI PUROHIT | F1005: 45988 | G1005: 23 Dec 2025 | H1005: 9703571 | I1005: 5919179 | J1005: 5919179 | K1005: 0 | L1005: 0 | M1005: 0 | N1005: 0 | O1005: 0 | P1005: 0 | Q1005: =IF(G1005="01 Jan 1900","Unregistered","Registered") -> Registered
A1006: 5456 | B1006: NYATI EMERALD III | C1006: TOPAZ - (PMC NO - C3) | D1006: TOPAZ - C3 -2002 | E1006: PALKAR ANURAG RAVINDRA | F1006: 46022 | G1006: 28 Jan 2026 | H1006: 9684821 | I1006: 5907741 | J1006: 5907741 | K1006: 0 | L1006: 0 | M1006: 0 | N1006: 0 | O1006: 0 | P1006: 0 | Q1006: =IF(G1006="01 Jan 1900","Unregistered","Registered") -> Registered
...

Sheet Booking May
A1: Booking Register
A2: From Date -01 May 2026 | To Date- 31 May 2026
A3: Page 1 of 1
A4: Total Records: 65 Records 1 To 65
A5: Company | B5: project | C5: Building | D5: Unit | E5: customer_name | F5: Customer_address | G5: Customer_Mobile | H5: PAN_NO | I5: Booking_Date | J5: Aggr_Date | K5: Area1 | L5: Agg_Value | M5: Claimed_Amt | N5: Claimed_GST | O5: Amount_Received | P5: RelationManager | Q5: SaleManager | R5: Source | S5: Subsource | T5: Referredbycustomer | U5: Sourcing Team/ROM | V5: Swabhiman (Defence) | W5: International Office | X5: Poona Office | Y5: Reference By
A6: Mihir Homes Enterprise LLP | B6: NYATI EQUINOX I | C6: PODIUM - 3 | D6: P3 - SHOP NO - 234 | E6: ANITA ASHAWATHA MULE | F6: FLAT NO. 22, B5 BUILDING, SAUDAMINI CO-OP HOUSING SOCIETY, RIGHT BHUSARI COLONY, PAUD ROAD, KOTHRUD, PUNE – 411038 (MAHARASHTRA) | G6: 8208537012 | H6: AMBPJ0740M | I6: 46155 | J6: 46167 | K6: 506 | L6: 6030000 | M6: 1809000 | N6: 90450 | O6: 1790910 | P6: Prasad Kamble | Q6: Manoj Digwa (Mihir Team) | R6: REFERENCE | S6: CHANNEL PARTNER | X6: YES
A7: Mihir Homes Enterprise LLP | B7: NYATI EQUINOX I | C7: GALAXY - (PMC NO. 2B) | D7: GALAXY - 2B -1703 | E7: Mahesh Mane | F7: At post Chachegaon Karad DIST. Satara 415122 | G7: 9175851666 | I7: 46162 | J7: 2 | K7: 1152 | L7: 9158400 | M7: 0 | N7: 0 | O7: 100000 | P7: Prasad Kamble | Q7: Anirudh Nair (Mihir Team) | R7: REFERENCE | S7: CHANNEL PARTNER | X7: YES
A8: Mihir Homes Enterprise LLP | B8: NYATI EQUINOX I | C8: PHOENIX - (PMC NO. 2A) | D8: PHOENIX - 2A - 301 | E8: ANJALI KUMARI | F8: HOUSE - A32, ROAD - 2A, MAGISTRATE COLONY, ASHIANA NAGAR, PATNA, BIHAR - 800025 | G8: 7204317004 | H8: AFXPK3020J | I8: 46167 | J8: 46188 | K8: 1719 | L8: 13923900 | M8: 0 | N8: 0 | O8: 4177170 | P8: Prasad Kamble | Q8: Anirudh Nair (Mihir Team) | R8: DIRECT SALES | S8: WALK IN | X8: YES
A9: Mihir Homes Enterprise LLP | B9: NYATI EQUINOX I | C9: EROS - (PMC NO. 2C) | D9: EROS - 2C -603 | E9: DIVYA SIKHA | F9: B - 119, SANCHAR VIHAR COLONY, I T I TOWNSHIP, MAU, MANKAPUR, GONDA, UTTAR PRADESH - 271308 | G9: 9764626194 | H9: DCBPS1896C | I9: 46168 | J9: 46181 | K9: 1152 | L9: 9245952 | M9: 0 | N9: 0 | O9: 2773785 | P9: Prasad Kamble | Q9: Jitendra Reddy | R9: REFERENCE | S9: CHANNEL PARTNER | X9: YES
A10: Mihir Homes Enterprise LLP | B10: NYATI EQUINOX I | C10: PODIUM - 2 | D10: P2 - SHOP NO - 130 | E10: SONALI AJIT PHADKE | F10: Flat No,H2-401 Vanraji Heightsmit Collage Road Rambagh Colony Kothurd Pune : 411038 | G10: 9511680936 | I10: 46168 | J10: 46168 | K10: 682 | L10: 6816800 | M10: 0 | N10: 0 | O10: 1481680 | P10: Prasad Kamble | Q10: Manoj Digwa (Mihir Team) | R10: REFERENCE | S10: CHANNEL PARTNER | X10: YES
A11: Mihir Homes Enterprise LLP | B11: NYATI EQUINOX I | C11: GALAXY - (PMC NO. 2B) | D11: GALAXY - 2B -904 | E11: SHEELPRIYA GAUTAM | F11: GH -71 , 6 G SECTOR ,WATER TANK KE PASS , DEENDAYAL NAGAR , MAHARAJAPURA , MADHYA PRADAESH , GWALIOR : 474005 | G11: 18604941392 | I11: 46170 | J11: 2 | K11: 1152 | L11: 9194000 | M11: 0 | N11: 0 | O11: 919400 | P11: Prasad Kamble | R11: CHANNEL PARTNER | S11: ALPHA HOUSING -PUNE | X11: YES
A12: Mihir Homes Enterprise LLP | B12: NYATI EQUINOX II | C12: MIRA (PMC - B) | D12: MIRA - B - 2205 | E12: DINESH ROHIDAS SALVE | F12: 497, PANCHSHEEL NIWAS, TEMBHODE, SAMARTH NAGAR, NEAR MARATHI SCHOOL, TAL- PALGHAR, THANE - 401404 (MAHARASHTRA) | G12: 8369209965 | H12: BKFPS5211R | I12: 46155 | J12: 2 | K12: 733 | L12: 5062831 | M12: 0 | N12: 0 | O12: 607283 | P12: Prasad Kamble | Q12: Anirudh Nair (Mihir Team) | R12: CHANNEL PARTNER | S12: ASSET DEALS | X12: YES
A13: Nyati Builders Pvt Ltd | B13: NYATI DEFENCE ENCLAVE III | C13: "G" (MHADA) | D13: G -1 | E13: PATHAN SAMAD HAMID | F13: S/O HAMEED PATHAN, HOUSE NO. 1174, GAVANDI GALLI, VAIRAG, SOLAPUR - 413402 (MAHARASHTRA) | G13: 9082903966 | H13: AYPPP3310F | I13: 46164 | J13: 2 | K13: 581 | L13: 1627000 | M13: 0 | N13: 0 | O13: 161390 | P13: Harish Shroff | X13: YES
A14: Nyati Builders Pvt Ltd | B14: NYATI ELENOR | C14: A TOWER | D14: A TOWER -2601 | E14: Trupti Manish Dudhedia | G14: 9921754040 | I14: 46147 | J14: 2 | K14: 2675 | L14: 33705000 | M14: 0 | N14: 0 | O14: 1100000 | P14: Ashish Bhasin | Q14: Janavhi Chugera | R14: CHANNEL PARTNER
A15: Nyati Builders Pvt Ltd | B15: NYATI ELENOR | C15: B TOWER | D15: B TOWER - 1303 | E15: KAPIL BINAKIYA | G15: 9850007484 | I15: 46147 | J15: 2 | K15: 3255 | L15: 40687500 | M15: 0 | N15: 0 | O15: 4068750 | P15: Ashish Bhasin | Q15: Janavhi Chugera | R15: REFERENCE | S15: CHANNEL PARTNER | X15: YES
A16: Nyati Builders Pvt Ltd | B16: NYATI ELENOR | C16: A TOWER | D16: A TOWER -2404 | E16: DINESH PRAVIN PALRECHA | F16: FLOWER VALLY, LOTUS, FLAT NO.106, MOTHER TERRESA CHOWK, NEAR SACRED HEART TOWN, WANOWARIE, PUNE - 411040 (MAHARASHTRA) | G16: 9422308211 | H16: ADVPP2031L | I16: 46148 | J16: 46157 | K16: 3255 | L16: 33500000 | M16: 15075000 | N16: 753750 | O16: 8350000 | P16: Ashish Bhasin | Q16: Janavhi Chugera | R16: CHANNEL PARTNER | S16: FERIN KIRIT VORA HUF
A17: Nyati Builders Pvt Ltd | B17: NYATI ELENOR | C17: B TOWER | D17: B TOWER -1703 | E17: Ritesh Pravin Palrecha | G17: 9822880369 | I17: 46148 | J17: 2 | K17: 3255 | L17: 33500000 | M17: 0 | N17: 0 | O17: 3350000 | P17: Ashish Bhasin | Q17: Janavhi Chugera | R17: CHANNEL PARTNER | S17: VIRAG KIRIT VORA
A18: Nyati Builders Pvt Ltd | B18: NYATI ELENOR | C18: A TOWER | D18: A TOWER -1004 | E18: Bharat Vinod shah | F18: 926 Synagogue Street 101 Sagar Apartment Pune 411001 | G18: 982227122 | I18: 46168 | J18: 2 | K18: 3255 | L18: 34300000 | M18: 0 | N18: 0 | O18: 2100000 | P18: Ashish Bhasin | Q18: Janavhi Chugera
A19: Nyati Builders Pvt Ltd | B19: NYATI ELENOR | C19: A TOWER | D19: A TOWER -1901 | E19: PRADEEP SOLANKI | F19: 348 Center Street Adesh Jewellers Pune 411001 | G19: 9420276663 | I19: 46168 | J19: 2 | K19: 3255 | L19: 33500000 | M19: 0 | N19: 0 | O19: 1100000 | P19: Ashish Bhasin | Q19: Janavhi Chugera
A20: Nyati Builders Pvt Ltd | B20: NYATI ELENOR | C20: A TOWER | D20: A TOWER -1602 | E20: MAHAVEER KOTHARI | F20: Flat no 410 Wing H1, Gangadham Phase - 2, Survey No - 612 Bibewadi Pune 411037 | G20: 77988955324 | I20: 46168 | J20: 2 | K20: 2505 | L20: 28200000 | M20: 0 | N20: 0 | O20: 1000000 | P20: Ashish Bhasin | Q20: Janavhi Chugera
A21: Nyati Builders Pvt Ltd | B21: NYATI ELENOR | C21: A TOWER | D21: A TOWER -2101 | E21: UTTAMCHAND KOTHARI | F21: 540 Center Street Camp Pune 411001 | G21: 9822813818 | I21: 46168 | J21: 2 | K21: 2675 | L21: 31100000 | M21: 0 | N21: 0 | O21: 1100000 | P21: Ashish Bhasin | Q21: Janavhi Chugera | R21: REFERENCE | S21: CHANNEL PARTNER
A22: Nyati Builders Pvt Ltd | B22: NYATI ELENOR | C22: A TOWER | D22: A TOWER -1601 | E22: Bharti Shah | F22: A - 7/8 Kumar Castle , Convent Street Camp Pune - 411001 | G22: 9049966433 | I22: 46170 | J22: 2 | K22: 2675 | L22: 26800000 | M22: 0 | N22: 0 | O22: 900000 | P22: Ashish Bhasin | Q22: Janavhi Chugera
A23: Nyati Builders Pvt Ltd | B23: NYATI ELENOR | C23: A TOWER | D23: A TOWER -3001 | E23: SAGAR SHAH | F23: A 7/8 Kuamar Castle Convent Street Camp Pune - 411001 | G23: 9970291011 | I23: 46170 | J23: 2 | K23: 2675 | L23: 26800000 | M23: 0 | N23: 0 | O23: 900000 | X23: YES
A24: Nyati Builders Pvt Ltd | B24: NYATI ELENOR | C24: A TOWER | D24: A TOWER -1401 | E24: Kejal Mehta | F24: 266, B-7 Bhawani Peth Durga Society Neaxt To Mahindra Bank Pune 411042 | G24: 9860408449 | I24: 46173 | J24: 2 | K24: 3255 | L24: 32700000 | M24: 0 | N24: 0 | O24: 2100000 | P24: Ashish Bhasin | Q24: Janavhi Chugera | X24: YES
A25: Nyati Builders Pvt Ltd | B25: NYATI EMERALD I | C25: SAPPHIRE - (PMC - A2) | D25: SAPPHIRE - A2 - 101 PREMIUM PNN FLAT | E25: VAISHNAVI KULKARNI | F25: A25, Prathamesh Nagri, Opp Kausar park, Deolai road,Beed by pass, Satara parisar, Aurangabad PIN code 431002 | G25: 8080253967 | H25: BNPPB2596B | I25: 46162 | J25: 2 | K25: 1173 | L25: 9911850 | M25: 0 | N25: 0 | O25: 991185 | P25: Ashish Bhasin | Q25: Sanjay Zaveri | R25: CHANNEL PARTNER | X25: YES
A26: Nyati Builders Pvt Ltd | B26: NYATI EMERALD III | C26: RUBY - (PMC NO - C2) | D26: RUBY - C2 -702 | E26: KUNDAN CHOUDHARY | F26: 104 – BLOCK, B SILVER LINES APPARTMENT, NEAR GEETA BHAVAN TEMPLE, 20/2 MANORAMAGANJ, INDORE, MADHYA PRADESH – 452001 | G26: 9987898782 | H26: ALTPC8697B | I26: 46162 | J26: 46169 | K26: 1173 | L26: 9735900 | M26: 5938899 | N26: 296948 | O26: 6036258 | P26: Ashish Bhasin | Q26: Stanley | R26: DIRECT SALES | X26: YES
A27: Nyati Builders Pvt Ltd | B27: NYATI EMERALD III | C27: RUBY - (PMC NO - C2) | D27: RUBY - C2 -503 | E27: SHUBHRA NANDKUMAR DEVI | F27: 74 KASBA PETH, SHRI KRUPA APARTMENT/FLAT NO 2, NEAR PHANIALI TALIM, KASBA PETH, PUNE – 411011, MAHARASHTRA. | G27: 8180072717 | H27: BKXPD4484R | I27: 46168 | J27: 46191 | K27: 1698 | L27: 14441771 | M27: 0 | N27: 0 | O27: 1444177.1 | P27: Ashish Bhasin | Q27: Sanjay Zaveri | R27: CHANNEL PARTNER | X27: YES
A28: Nyati Builders Pvt Ltd | B28: NYATI EMERALD III | C28: AGATE - (PMC NO - D1) | D28: AGATE - D1 -1401 | E28: VIKASH KUMAR BERLIA | F28: Twin Tower CHS Ltd, Flat No.614 B, B Wing, Pump House, Manish Park, Parsi Colony, Near Raksha Multi Speciality Hospital, Andheri East, Mumbai, Po : Chakala MIDC, Dist : Mumbai Suburban, Maharashtra - 400093 | G28: 9903914388 | H28: AJHPB7602D | I28: 46171 | J28: 2 | K28: 1173 | L28: 9916964 | M28: 0 | N28: 0 | O28: 991696.4 | P28: Ashish Bhasin | Q28: Harshil Parikh | R28: DIRECT SALES
A29: Nyati Builders Pvt Ltd | B29: NYATI EMERALD III | C29: RUBY - (PMC NO - C2) | D29: RUBY - C2 -1002 | E29: AKSHAY ASHOK POTDAR | F29: SR. NO. 14/3, BULDING – A, FLAT NO.103, MAJESTIC TOWERS, KATRAJ, NEAR LAKE TOWN, PUNE, MAHARASHTRA – 411046. | G29: 9890900809 | H29: APDPP5705P | I29: 46173 | J29: 2 | K29: 1173 | L29: 9501300 | M29: 0 | N29: 0 | O29: 950130 | P29: Harish Shroff | R29: DIRECT SALES | X29: YES
A30: Nyati Builders Pvt Ltd | B30: NYATI EVOQUE | C30: OLIVE - (PMC NO A2) | D30: OLIVE - A2 -2401 | E30: HARSHIT TYAGI | G30: 9545904330 | I30: 46155 | J30: 2 | K30: 2126 | L30: 26396416 | M30: 0 | N30: 0 | O30: 300000 | P30: Ashish Bhasin | R30: CHANNEL PARTNER | X30: YES
A31: Nyati Builders Pvt Ltd | B31: NYATI EVOQUE | C31: LAVENDER - (PMC NO. A1) | D31: LAVENDER - A 1 -1604 | E31: SHUBHAM SHAH | F31: Jai Jalaram Bunglow Sr.no 29, Lane no 13 Near Atria Hsg Society Tingrenagar Pune 411015 | G31: 9763350126 | I31: 46168 | J31: 2 | K31: 2571 | L31: 28300000 | M31: 0 | N31: 0 | O31: 3113000 | P31: Ashish Bhasin | Q31: Ranit Chaudhary | R31: REFERENCE | S31: CHANNEL PARTNER
A32: Nyati Builders Pvt Ltd | B32: NYATI EVOQUE | C32: LAVENDER - (PMC NO. A1) | D32: LAVENDER - A 1 -1501 | E32: SMITA HIRAMAN PAWAR | F32: PLOT NO. 64, CIDCO DEVGIRIHILLS, NEAR MORYA MANGAL KARYALAYA, SHIVAJI NAGAR EAST, GARKHEDA, CHATRAPATI SAMBHAJI NAGAR – 431009 (MAHARASHTRA) | G32: 9860954878 | H32: AVBPP7815N | I32: 46168 | J32: 2 | K32: 2492 | L32: 25000000 | M32: 0 | N32: 0 | O32: 2550000 | P32: Ashish Bhasin | Q32: Ranit Chaudhary | R32: REFERENCE | S32: CHANNEL PARTNER
A33: Nyati Builders Pvt Ltd | B33: NYATI EVOQUE | C33: OLIVE - (PMC NO A2) | D33: OLIVE - A2 -1704 | E33: SUTRISHNA SAHA | F33: B - 301, REVELL ORCHID, PORWAL ROAD, LOHEGAON, PUNE - 411047 (MAHARASHTRA) | G33: 9175009649 | H33: BCWPP9140H | I33: 46170 | J33: 2 | K33: 2175 | L33: 27140000 | M33: 0 | N33: 0 | O33: 500000 | P33: Ashish Bhasin | Q33: Ranit Chaudhary | X33: YES
A34: Nyati Builders Pvt Ltd | B34: NYATI EXUBERANCE III | C34: BLUEBELL (PMC NO. D) | D34: BLUEBELL - D -401 | E34: BHANWAR HUKUM SINGH | F34: S/O, HUKUM SINGH GAJANAWAS BAWARLI JODHPUR RAJASTHAN – 342001 | G34: 9371201199 | H34: DAOPS6331H | I34: 46153 | J34: 46157 | K34: 460 | L34: 1513200 | M34: 1513200 | N34: 0 | O34: 1513200 | P34: Harish Shroff
A35: Nyati Builders Pvt Ltd | B35: NYATI EXUBERANCE IV | C35: CAMELLIA (PMC NO. C5) | D35: CAMELLIA - C5 -504 | E35: Geeta Kamthe | F35: Sr No-110 Ramtekdi Hadapsar ,Pune - 411013. | G35: 7276288105 | I35: 46153 | J35: 2 | K35: 981 | L35: 5654484 | M35: 0 | N35: 0 | O35: 100000 | P35: Sanjeev Deshpande | R35: CHANNEL PARTNER | X35: YES
A36: Nyati Builders Pvt Ltd | B36: NYATI EXUBERANCE IV | C36: CAMELLIA (PMC NO. C5) | D36: CAMELLIA - C5 -403 | E36: KHURSHED MEHMOOD BUTT | F36: MISSISSIPPI, FLAT NO. 1105 NYATI ETHOS CO-OP HOUSING SOCIETY, NEAR COUNTRY CLUB, UNDRI, PUNE - 411060, MAHARASHTRA. | G36: 9769087766 | H36: AEZPB1577L | I36: 46162 | J36: 2 | K36: 981 | L36: 5689800 | M36: 0 | N36: 0 | O36: 568980 | P36: Sanjeev Deshpande | Q36: Neharkar Swapnil | X36: YES
A37: Nyati Builders Pvt Ltd | B37: NYATI EXUBERANCE IV | C37: CAMELLIA (PMC NO. C5) | D37: CAMELLIA - C5 -304 | E37: SUMIT BHASKER | F37: 229, VASUNDHRA, NEAR VANASTHALI SCHOOL, 10 C, VASUNDHRA, HAPUR, UTTAR PRADESH -201012 | G37: 8491936034 | H37: AKRPB9132H | I37: 46164 | J37: 46197 | K37: 981 | L37: 5426892 | M37: 0 | N37: 0 | O37: 542689.2 | P37: Sanjeev Deshpande | Q37: Neharkar Swapnil | R37: DIRECT SALES
A38: Nyati Builders Pvt Ltd | B38: NYATI EXUBERANCE IV | C38: CAMELLIA (PMC NO. C5) | D38: CAMELLIA - C5 -902 | E38: SUNEET SINGH | F38: Mid Town Society, C-64, Florentine Society, Sopan Baug, Ghorpadi, Pune - 411001, Maharashtra. | G38: 9823728439 | H38: DLGPS5581A | I38: 46164 | J38: 46177 | K38: 985 | L38: 5447050 | M38: 0 | N38: 0 | O38: 3758466 | P38: Sanjeev Deshpande | Q38: Pallavi Shendge | R38: DIRECT SALES | S38: EXISTING CLIENT
A39: Nyati Builders Pvt Ltd | B39: NYATI EXUBERANCE IV | C39: PRIMROSE (PMC NO. C4) | D39: PRIMROSE - C4 -1404 | E39: CHAFEKALI RAJESH SONAWANE | F39: PLOT NO. 1, GAT 191, SIDDHI VINAYAK COLONY, JALGAON, MAHARASHTRA - 425001. | G39: 7588730417 | H39: IXBPS0756K | I39: 46172 | J39: 46176 | K39: 981 | L39: 5886981 | M39: 0 | N39: 0 | O39: 5886981 | P39: Sanjeev Deshpande | Q39: Ganesh Waghmare | R39: CHANNEL PARTNER | X39: YES
A40: Nyati Builders Pvt Ltd | B40: NYATI EXUBERANCE IV | C40: PRIMROSE (PMC NO. C4) | D40: PRIMROSE - C4 -101 | E40: MAYUR NARENDRA RAJGURU | F40: HOUSE NO. 30, AZAD ALI, NEAR JAIN MANDIR, YERWADA, PUNE - 411006, MAHARASHTRA | G40: 9881610460 | I40: 46172 | J40: 2 | K40: 985 | L40: 5844005 | M40: 0 | N40: 0 | O40: 1555900 | P40: Sanjeev Deshpande | Q40: Akshay Tagad | R40: DIRECT SALES | X40: YES
A41: Nyati Construction Pvt.Ltd. | B41: NYATI EMBLEM | C41: F BUILDING | D41: F BUILDING - UNIT NO.702 | E41: BHAVESH VIJAYKUMAR RAYSONI | F41: NEAR DURGA MANDIR MAIN ROAD A/P- BHIGWAN TAL- INDAPUR DIST. PUNE-413130 | G41: 8793332587 | I41: 46173 | J41: 2 | K41: 3642 | L41: 36500000 | M41: 0 | N41: 0 | O41: 4000000 | P41: Ashish Bhasin | R41: REFERENCE | S41: CHANNEL PARTNER
A42: Nyati Construction Pvt.Ltd. | B42: NYATI ERA II | C42: T - WING - FIRST FLOOR | D42: T - WING - SHOP NO. 128 | E42: TEJ KARAN SINGHI | F42: S/O PRITHWI RAJ SINGHI, NEAR PUGLIYA GUEST HOUSE, ADASAR BASS, WARD NO. 22, DUNGARGARH, BIKANER, RAJASTHAN - 331803 | G42: 7259036890 | H42: AXKPK3467G | I42: 46169 | J42: 46192 | K42: 248 | L42: 2897196 | M42: 0 | N42: 0 | O42: 2897196 | P42: Rakesh Pillai | Q42: Manual | R42: CHANNEL PARTNER | X42: YES
A43: Nyati Construction Pvt.Ltd. | B43: NYATI ERA IV | C43: ORION - (PMC NO. WING O) | D43: ORION - O - 1002 | E43: HARSHADA TOTARAM CHAUDHARI | F43: C- 103 PARAMOUNT SMART CITY LOHEGAON PUNE | G43: 9766354508 | H43: ARYPC8993P | I43: 46164 | J43: 2 | K43: 1143 | L43: 7943850 | M43: 0 | N43: 0 | O43: 50000 | P43: Rakesh Pillai | Q43: Komal Alhat | R43: CHANNEL PARTNER
A44: Nyati Construction Pvt.Ltd. | B44: NYATI ERA IV | C44: ORION - (PMC NO. WING O) | D44: ORION - O - 1003 | E44: HARSHADA TOTARAM CHAUDHARI | F44: C- 103 PARAMOUNT SMART CITY LOHEGAON PUNE | G44: 9766354508 | H44: ARYPC8993P | I44: 46164 | J44: 2 | K44: 1143 | L44: 7943850 | M44: 0 | N44: 0 | O44: 100000 | P44: Rakesh Pillai | Q44: Komal Alhat | R44: CHANNEL PARTNER
A45: Nyati Construction Pvt.Ltd. | B45: NYATI ERA IV | C45: ORION - (PMC NO. WING O) | D45: ORION - O - 1203 | E45: RANGAM SREENIVASULU | F45: Flat No.313, 3rd Floor, Lalitha Majestic, KGR Enclave, Ameenapur, PO: Ameenpur, DIST: Sangareddy, Telangana - 502032 | G45: 9952010728 | H45: CWGPS9709G | I45: 46164 | J45: 46192 | K45: 1143 | L45: 7829550 | M45: 0 | N45: 0 | O45: 782955 | P45: Sanjeev Deshpande | Q45: Anna Saheb Bhosale | R45: DEFENCE | S45: DEFENCE
A46: Nyati Construction Pvt.Ltd. | B46: NYATI ERA IV | C46: JOY - (PMC NO. WING J) | D46: JOY - J - 901 | E46: KULAMBIL RAMANUNNI | F46: FLAT NO. A- 301, DEVI ORCHID, BHAU PATIL ROAD, BOPODI, PUNE - 411020, MAHARASHTRA. | G46: 8308942980 | H46: AATPR9756R | I46: 46169 | J46: 46178 | K46: 1625 | L46: 10812900 | M46: 0 | N46: 0 | O46: 3243870 | P46: Rakesh Pillai | Q46: Manual | R46: REFERENCE | S46: EXISTING CLIENT | X46: YES
A47: Nyati Construction Pvt.Ltd. | B47: NYATI ERA IV | C47: ORION - (PMC NO. WING O) | D47: ORION - O - 704 | E47: SHARDA SHIVAJI CHOUDHARI | F47: VYAS NAGAR, NALDURG, OSMANABAD, MAHARASHTRA – 413602. | G47: 8390347838 | I47: 46173 | J47: 46191 | K47: 1116 | L47: 7548214 | M47: 0 | N47: 0 | O47: 3501100 | P47: Rakesh Pillai | Q47: Komal Alhat | X47: YES
A48: Nyati Construction Pvt.Ltd. | B48: NYATI ERA IV | C48: JOY - (PMC NO. WING J) | D48: JOY - J - 802 | E48: BHARATBHUSHAN SATPAL GOGIA | F48: FLAT NO. 401, SR NO. 298/2D/2/1, NYATI EVITA, CELINA, PO : LOHEGAON, DIST : PUNE, MAHARASHTRA - 411047 | G48: 9850080099 | H48: AHMPG6857E | I48: 46173 | J48: 2 | K48: 1625 | L48: 11382000 | M48: 0 | N48: 0 | O48: 1138200 | P48: Rakesh Pillai | R48: CHANNEL PARTNER | S48: A B ENTERPRISES
A49: Nyati Construction Pvt.Ltd. | B49: NYATI ERA IV | C49: ORION - (PMC NO. WING O) | D49: ORION - O - 1201 | E49: SAMEER SUTRADHAR | F49: C-133, PUNARWAS COLONY, PANCHDEV MANDIR KE PASS, MUKAM/POST PUNARWAS COLONY, SAGWARA, DUNGARPUR, SAGWARA, RAJASTHAN - 314025. | G49: 9867661477 | H49: FGOPS4232R | I49: 46173 | J49: 46197 | K49: 1116 | L49: 7593750 | M49: 0 | N49: 0 | O49: 400000 | P49: Rakesh Pillai | Q49: Manual | X49: YES
A50: Nyati Construction Pvt.Ltd. | B50: NYATI ERA IV | C50: NOBLE - (PMC NO. WING N) | D50: NOBLE - N - 401 | E50: DEEPTI DAS | F50: PLOT NO – 26, S. NO – 253, LANE NO – 3, KHESE PARK, LOHEGAON ROAD, IN FRONT OF GANESH TEMPLE, PUNE – 411032, MAHARASHTRA | G50: 8308917396 | H50: AJWPD1328D | I50: 46173 | J50: 46192 | K50: 1153 | L50: 7833600 | M50: 0 | N50: 0 | O50: 783360 | P50: Rakesh Pillai | Q50: Manual | R50: DIRECT SALES | X50: YES
A51: Nyati Landmark Projects LLP | B51: NYATI ENTHRAL I | C51: OFFICE | D51: OFFICE - 1608 | E51: RNRCLOUD SOLUTION LLP | F51: A 1106, WELLINGTON, PRIDE WORLD CITY, CHARHOLI BK., KHED, PUNE - 412105 (MAHARASHTRA) | G51: 9566066441 | H51: ABJFR2945P | I51: 46150 | J51: 46168 | K51: 10675 | L51: 83000000 | M51: 83000000 | N51: 0 | O51: 83000000 | P51: Harish Shroff | X51: YES
A52: Nyati Landmark Projects LLP | B52: NYATI ENTHRAL I | C52: OFFICE | D52: OFFICE - 1701 | E52: SHIVTEJ REALITY LLP | F52: DOMKHEL WASTI, ZILLA PARISHAD PRIMARY SCHOOL WADJAI, WAGHOLI, AWHALWADI, PUNE - 412207 (MAHARASHTRA) | G52: 9890001818 | H52: AFRFS9204E | I52: 46164 | J52: 46198 | K52: 14310 | L52: 93015000 | M52: 0 | N52: 0 | O52: 48950000 | P52: Harish Shroff | X52: YES
A53: Nyati Realtors LLP | B53: NYATI ESTEBAN II | C53: ALEXANDRITE (PMC - D5) | D53: ALEXANDRITE - D5 - 1902 | E53: Ankita Gaurav Shivani | F53: 1368, Nai Basti Mehendi Bagh, Jhansi, Uttar Pradesh - 284001. | G53: 9892500649 | H53: ARYPV4846Q | I53: 46162 | J53: 2 | K53: 1699 | L53: 9945402 | M53: 0 | N53: 0 | O53: 100000 | P53: Sanjeev Deshpande | Q53: Neharkar Swapnil | R53: DIRECT SALES | S53: EXISTING CLIENT
A54: Nyati Realtors LLP | B54: NYATI ESTEBAN II | C54: ALEXANDRITE (PMC - D5) | D54: ALEXANDRITE - D5 - 1402 | E54: SHABANA HUSSAIN | F54: F-301, Unity Park, Kondhwa, Pune - 411048, maharashtra | G54: 9234658576 | H54: ANYPH7138M | I54: 46162 | J54: 46197 | K54: 1699 | L54: 10092060 | M54: 0 | N54: 0 | O54: 1009206 | P54: Sanjeev Deshpande | Q54: Ganesh Waghmare | R54: CHANNEL PARTNER | S54: HOMESFY REALTY LIMITED | X54: YES
A55: Nyati Realtors LLP | B55: NYATI ESTEBAN II | C55: PEARL (PMC - D1) | D55: PEARL - D1 - 2702 | E55: Malati Shevate | F55: C - 501, 5TH FLOOR, AERONEST SOCIETY, WADACHIWADI ROAD, UNDRI, PUNE – 411060, MAHARASHTRA. | G55: 9860338586 | H55: DPVPS9395B | I55: 46172 | J55: 2 | K55: 1699 | L55: 10047886 | M55: 0 | N55: 0 | O55: 100000 | P55: Sanjeev Deshpande | X55: YES
A56: Nyati Realtors LLP | B56: NYATI ESTEBAN II | C56: ALEXANDRITE (PMC - D5) | D56: ALEXANDRITE - D5 - 1903 | E56: Jagjit Oberoi | F56: M1/702 Elburz Hills And Dales Nibm Road Near Sanskriti School Undri Pune - 411060 | G56: 9890909649 | H56: ABOPO7493G | I56: 46172 | J56: 2 | K56: 1172 | L56: 6824127 | M56: 0 | N56: 0 | O56: 500000 | P56: Sanjeev Deshpande | Q56: Neharkar Swapnil | R56: CHANNEL PARTNER | S56: RAJANI ESTATE | X56: YES
A57: Nyati Realtors LLP | B57: NYATI ESTEBAN II | C57: ALEXANDRITE (PMC - D5) | D57: ALEXANDRITE - D5 - 2704 | E57: Malati Shevate | F57: C - 501, 5th Floor, Aeronest Society, Wadachiwadi Road, Undri, Pune – 411060, Maharashtra. | G57: 9860338586 | H57: DPVPS9395B | I57: 46172 | J57: 2 | K57: 1172 | L57: 6877299 | M57: 0 | N57: 0 | O57: 100000 | P57: Sanjeev Deshpande | X57: YES
A58: Nyati Realtors LLP | B58: NYATI ESTEBAN II | C58: ALEXANDRITE (PMC - D5) | D58: ALEXANDRITE - D5 - 2203 | E58: Jagjit Oberoi | F58: M1/702 Elburz Hills And Dales Nibm Road Near Sanskriti School Undri Pune - 411060 | G58: 9890909649 | I58: 46172 | J58: 2 | K58: 1172 | L58: 6824127 | M58: 0 | N58: 0 | O58: 500000 | P58: Sanjeev Deshpande | Q58: Neharkar Swapnil | R58: CHANNEL PARTNER | S58: RAJANI ESTATE
A59: Nyati Realtors LLP | B59: NYATI ESTEBAN II | C59: ALEXANDRITE (PMC - D5) | D59: ALEXANDRITE - D5 - 1904 | E59: AKZSHAT PANDE | F59: FLAT NO. A-902, GAGAN ARENA, SR NO. 12 KAD NAGAR, OPPOSITE MISTY MOORS, UNDRI, PUNE, MAHARASHTRA - 411060. | G59: 9049257538 | H59: BRGPP0140L | I59: 46172 | J59: 2 | K59: 1172 | L59: 6985215 | M59: 0 | N59: 0 | O59: 209557 | P59: Sanjeev Deshpande | Q59: Akshay Tagad | R59: CHANNEL PARTNER | S59: KEY MANSIONS PVT LTD | X59: YES
A60: Nyati Realtors LLP | B60: NYATI ESTEBAN II | C60: TANZANITE (PMC - D4) | D60: TANZANITE - D4 - 501 | E60: CHINMAY TIWARI | F60: B-801, MARVEL FRIA,LOHEGAON WAGHOLI ROAD, NEAR KAMAL BAUG SOCIETY, WAGHOLI, PUNE, MAHARASHTRA – 412207. | G60: 9970178007 | H60: AGJPT6944P | I60: 46172 | J60: 46183 | K60: 1699 | L60: 9957839 | M60: 0 | N60: 0 | O60: 995783.9 | P60: Sanjeev Deshpande | Q60: Akshay Tagad | R60: CHANNEL PARTNER | S60: BK ALPHA HOUSING REALTY LLP | X60: YES
A61: Nyati Realtors LLP | B61: NYATI ESTEBAN II | C61: PEARL (PMC - D1) | D61: PEARL - D1 - 2803 | E61: Prashant Chavan | F61: Sr.no.49 Shivray Colony, kale borate Nagar. Hadapsar Pune 411028 | G61: 8975976770 | H61: AFTPC2813F | I61: 46173 | J61: 2 | K61: 1172 | L61: 6921873 | M61: 0 | N61: 0 | O61: 0 | P61: Sanjeev Deshpande | Q61: Priyanka Thombare | R61: CHANNEL PARTNER | X61: YES
A62: Nyati Realtors LLP | B62: NYATI ESTEBAN II | C62: ALEXANDRITE (PMC - D5) | D62: ALEXANDRITE - D5 - 1302 | E62: MUSTUFA LOKHANDWALA | F62: 64, KALIMI COLONY, RATLAM, MADHYA PRADESH - 457001. | G62: 9828618352 | H62: EQIPM5956F | I62: 46173 | J62: 2 | K62: 1699 | L62: 9913665 | M62: 0 | N62: 0 | O62: 200000 | P62: Harish Shroff | X62: YES
A63: Nyshaa Builders LLP | B63: NYATI EMPRESS | C63: A WING | D63: A WING - SHOP - 118 | E63: TINAZ ARMIN ANKLESARIA | F63: KALPATARU REGENCY PHASE - 1, NORTH AVENUE KALYANI NAGAR, B - 501, YERWADA, PUNE - 411006 | G63: 9822650980 | H63: AAAPR9272K | I63: 46168 | J63: 2 | K63: 561 | L63: 5582000 | M63: 0 | N63: 0 | O63: 500000 | P63: Harish Shroff | X63: YES
A64: Nyshaa Builders LLP | B64: NYATI EMPRESS | C64: A WING | D64: A WING - OFFICE - 503 | E64: ASHUTOSH KHANNA | F64: 1001, F P NO. 21, MAGNOLIA, 8TH ROAD, BH SANTACRUZ GYMKHANA, VTC : MUMBAI PO: SANTACRUZ (EAST), MUMBAI - 400055 (MAHARASHTRA) | G64: 9819610306 | H64: AWKPK9119L | I64: 46170 | J64: 46174 | K64: 2574 | L64: 20735000 | M64: 0 | N64: 0 | O64: 19018750 | P64: Harish Shroff | X64: YES

Sheet Cancel May
A1: ProjectName | B1: Building | C1: UnitNo | D1: CustomerName | E1: Customer_Address | F1: TotalArea | G1: Agg_Value | H1: Sale_Date | I1: TransCan_Remark | J1: Cancel_Date | K1: Column5 | L1: Aadhaar_Card_No | M1: PAN_NO | N1: ReceivedAmount | O1: Sale_Status
A2: NYATI ESTEBAN II | B2: ALEXANDRITE (PMC - D5) | C2: ALEXANDRITE - D5 - 902 | D2: BHAVNA GUPTA | E2: B-1503, MANTRA MIRARI, GHORPADI ROAD, MUNDHWA, PUNE – 411036, MAHARASHTRA | F2: 1699 | G2: 10136234 | H2: 46142 | I2: Financial Issue | J2: 46164 | K2: 0 | M2: AKSPG0045R | N2: 100000 | O2: Cancel
A3: NYATI EXUBERANCE IV | B3: PERIWINKLE ( PMC NO. C3) | C3: PERIWINKLE - C3 -201 | D3: TANIYA ZOHEB MIRZA | E3: C/1104, Atrium Skywards, Next Undri City Center, Undri, Pune – 411060, Maharashtra | F3: 985 | G3: 5417500 | H3: 46078 | I3: FINANCIAL ISSUE | J3: 46172 | K3: 0 | L3: 917454384779 | M3: CRQPM9559R | N3: 100000 | O3: Cancel
A4: NYATI EMERALD III | B4: RUBY - (PMC NO - C2) | C4: RUBY - C2 -1804 | D4: AJAY BHANUDAS JOSHI | E4: FLAT NO-504/A, PINNACLE GULMOHAR, DSK RANWARA ROAD, PATIL NAGAR, NEAR SURYADATTA COLLEGE, BAVDHAN, PASHAN, ARMAMENT, PUNE, MAHARASHTRA - 411021 | F4: 1698 | G4: 13256250 | H4: 45930 | I4: Defaulted For Registration. | J4: 46155 | K4: 0 | M4: AGXPJ7086Q | N4: 1391907 | O4: Cancel
A5: NYATI EQUINOX I | B5: GALAXY - (PMC NO. 2B) | C5: GALAXY - 2B -1303 | D5: Mangal Tanaji Mane | E5: AT POST CHACHEGAON , TAL -KARAD ATST -SATARA :415122 | F5: 1152 | G5: 9158400 | H5: 46134 | I5: FINANCIAL ISSUE. | J5: 46172 | K5: 0 | N5: 0 | O5: Cancel
A6: NYATI EXUBERANCE IV | B6: CAMELLIA (PMC NO. C5) | C6: CAMELLIA - C5 -702 | D6: Suraj Vishnu Chaudhari | E6: Karmveer Nagar At Post Vadut Tal.Khatav Vadut Dist Satara - 415506 | F6: 985 | G6: 5516000 | H6: 46173 | I6: Legal Dispute | J6: 46173 | K6: 0 | N6: 50000 | O6: Cancel
A7: NYATI PLAZA | B7: FOOD COURT 202 | C7: FOOD STALL NO.2 | D7: ADITYA AMRUT DESHPANDE HUF | E7: FLAT NO.Q 111/2, FOREST COUNTY, KHARADI, OPP EON IT PARK, PUNE CITY, PUNE 411014 | F7: 527 | G7: 6900000 | H7: 45351 | I7: As per Sales Instruction | J7: 46156 | K7: 0 | M7: AAXHA8693N | N7: 1112800 | O7: Cancel
A8: NYATI EVOQUE | B8: OLIVE - (PMC NO A2) | C8: OLIVE - A2 -1701 - PREMIUM FLAT | D8: HARSHIT TYAGI | E8: 28 Somnath Colony Pratap Nagar Chittorgarh 312001 , | F8: 2126 | G8: 26396416 | H8: 45929 | I8: Shifted to 2401 A2 | J8: 46155 | K8: 0 | N8: 300000 | O8: Cancel
A9: NYATI EQUINOX I | B9: HERMES - (PMC NO.2E) | C9: HERMES - 2E - 104 | D9: Mallika Razvi | E9: R h No 22 Karan Avenue Hsg . Society Pashan Road Bavdhan Khurd Pune : 411021 | F9: 1698 | G9: 13795401 | H9: 46142 | I9: Cancelled Due to Financial | J9: 46164 | K9: 0 | N9: 200000 | O9: Cancel
A10: NYATI EMPRESS | B10: A WING | C10: A WING - OFFICE - 503 | D10: SAB INVESTMENTS | F10: 2574 | G10: 19300000 | H10: 2 | I10: cancelled | J10: 46170 | K10: 0 | N10: 2000000 | O10: Cancel
A11: NYATI ERA IV | B11: NOBLE - (PMC NO. WING N) | C11: NOBLE - N - 1102 | D11: USHA DEVI DIXIT | E11: K-213, PALLADIUM GRAND, PHASE II, DHANORI, PUNE-411015 | F11: 1376 | G11: 9380357 | H11: 46022 | I11: Job Loss | J11: 46149 | K11: 0 | N11: 210000 | O11: Cancel
A12: NYATI ENTHRAL I | B12: OFFICE | C12: OFFICE - 1201 | D12: ATUL SATAV AND MAHENDRA GALANDE | F12: 14310 | G12: 85956000 | H12: 45083 | I12: SHIFTED TO 1701 | J12: 46164 | K12: 0 | N12: 47900000 | O12: Cancel
A13: NYATI ENTHRAL I | B13: OFFICE | C13: OFFICE - 817 | D13: SIDHANT JAIN | E13: FINSWELL WOODS, FLAT NO. 1002, SAKORE NAGAR, VIMAN NAGAR, PUNE - 411014 | F13: 1502 | G13: 9500000 | H13: 45290 | I13: Cancellation Deed | J13: 46172 | K13: 0 | N13: 3192000 | O13: Cancel

Sheet Coll May
A1: Project_Name | B1: Building_Name | C1: Opening Sales Value | D1: Sales Value For The Period | E1: Total Sales Value | F1: Opening Due | G1: Due For Period | H1: Total Due | I1: Opening Collection | J1: Collection For Period | K1: Total Collection | L1: Opening Outstanding | M1: Closing Outstanding
A2: NIVAAN MEADOWS | B2: PLOT | C2: 1906.81 | D2: 0 | E2: 1906.81 | F2: 0 | G2: 0 | H2: 0 | I2: 1238.83 | J2: 0 | K2: 1238.83 | L2: -1238.83 | M2: -1238.83
A3: NYATI CORPORATE OFFICE | B3: OFFICE | C3: 7995.7 | D3: 0 | E3: 7995.7 | F3: 7963.75 | G3: 0 | H3: 7963.75 | I3: 7917.77 | J3: 0 | K3: 7917.77 | L3: 45.98 | M3: 45.98
A4: NYATI CORPORATE OFFICE | B4: SHOWROOM | C4: 4451.11 | D4: 0 | E4: 4451.11 | F4: 4451.11 | G4: 0 | H4: 4451.11 | I4: 4375.28 | J4: 0 | K4: 4375.28 | L4: 75.83 | M4: 75.83
A5: NYATI DEFENCE ENCLAVE I | B5: VIKRANT ( PMC NO. D) | C5: 1719.42 | D5: 0 | E5: 1719.42 | F5: 1847.1 | G5: 0 | H5: 1847.1 | I5: 1847.1 | J5: 0 | K5: 1847.1 | L5: 0 | M5: 0
A6: NYATI DEFENCE ENCLAVE I | B6: SUKHOI ( PMC NO. C) | C6: 1826.28 | D6: 0 | E6: 1826.28 | F6: 1826.28 | G6: 0 | H6: 1826.28 | I6: 1824.82 | J6: 0 | K6: 1824.82 | L6: 1.46 | M6: 1.46
A7: NYATI DEFENCE ENCLAVE II | B7: CHETAK ( PMC NO. E) | C7: 1564.46 | D7: 0 | E7: 1564.46 | F7: 1564.46 | G7: 0 | H7: 1564.46 | I7: 1564.46 | J7: 0 | K7: 1564.46 | L7: 0 | M7: 0
A8: NYATI DEFENCE ENCLAVE II | B8: BEAS ( PMC NO. F) | C8: 1445.34 | D8: 0 | E8: 1445.34 | F8: 1554.8 | G8: 0 | H8: 1554.8 | I8: 1554.8 | J8: 0 | K8: 1554.8 | L8: 0 | M8: 0
A9: NYATI DEFENCE ENCLAVE III | B9: BHISHMA ( PMC NO. B) | C9: 1868.35 | D9: 0 | E9: 1868.35 | F9: 1868.35 | G9: 0 | H9: 1868.35 | I9: 1868.35 | J9: 0 | K9: 1868.35 | L9: 0 | M9: 0
A10: NYATI DEFENCE ENCLAVE III | B10: "G" (MHADA) | C10: 436.63 | D10: 16.27 | E10: 452.9 | F10: 436.63 | G10: 0 | H10: 436.63 | I10: 436.63 | J10: 1.61 | K10: 438.25 | L10: 0 | M10: -1.61
A11: NYATI DEFENCE ENCLAVE III | B11: ARJUN ( PMC NO. A) | C11: 1852.79 | D11: 0 | E11: 1852.79 | F11: 1852.79 | G11: 0 | H11: 1852.79 | I11: 1852.79 | J11: 0 | K11: 1852.79 | L11: 0 | M11: 0
A12: Nyati Demo Project - 1 | B12: Demo | C12: 0 | D12: 0 | E12: 0 | F12: 0 | G12: 0 | H12: 0 | I12: 0 | J12: 0 | K12: 0 | L12: 0 | M12: 0
A13: NYATI ELAN (N - SE) | B13: CELESTIAL ( PMRDA NO. B2) | C13: 2340.59 | D13: 0 | E13: 2340.59 | F13: 2318.14 | G13: 0 | H13: 2318.14 | I13: 2318.14 | J13: 0 | K13: 2318.14 | L13: 0 | M13: 0
... A228: TEST PROJECT MIS | B228: Building A | C228: 39 | D228: 0 | E228: 39 | F228: 0 | G228: 0 | H228: 0 | I228: 0 | J228: 0 | K228: 0 | L228: 0 | M228: 0

Sheet Ageing May
A1: SrNo | B1: Project | C1: Building | D1: Unit | E1: Booking_Date | F1: Registration_Date | G1: Agg_Value | H1: Claimed Value | I1: Received | J1: Total Outstanding | K1: 0-30 Days | L1: 31-60 Days | M1: 61-90 Days | N1: 91-120 Days | O1: > 120 Days | P1: Status
A2: 1 | B2: NYATI ENTHRAL I | C2: OFFICE | D2: OFFICE - 1001 | E2: 44162 | F2: 25 Dec 2020 | G2: 180000001 | H2: 180000001 | I2: 91750000 | J2: 88250001 | K2: 0 | L2: 0 | M2: 0 | N2: 0 | O2: 88250001 | P2: Registered
A3: 2 | B3: NYATI ENTHRAL I | C3: OFFICE | D3: OFFICE - 1108 | E3: 45230 | F3: 04 Jan 2024 | G3: 69400000 | H3: 69400000 | I3: 8300000 | J3: 61100000 | K3: 0 | L3: 0 | M3: 0 | N3: 0 | O3: 61100000 | P3: Registered
A4: 3 | B4: NYATI ENTHRAL I | C4: OFFICE | D4: OFFICE - 1208 | E4: 45316 | F4: 02 Feb 2024 | G4: 73657500 | H4: 73657500 | I4: 13803575 | J4: 59853925 | K4: 0 | L4: 0 | M4: 0 | N4: 0 | O4: 59853925 | P4: Registered
A5: 4 | B5: NYATI ENTHRAL I | C5: OFFICE | D5: OFFICE - 1205 | E5: 44995 | F5: 16 Mar 2023 | G5: 51750000 | H5: 51750000 | I5: 178400 | J5: 51571600 | K5: 0 | L5: 0 | M5: 0 | N5: 0 | O5: 51571600 | P5: Registered
A6: 5 | B6: NYATI ENTHRAL I | C6: OFFICE | D6: OFFICE - 1206 | E6: 45000 | F6: 30 Mar 2023 | G6: 40700000 | H6: 40700000 | I6: 274000 | J6: 40426000 | K6: 0 | L6: 0 | M6: 0 | N6: 0 | O6: 40426000 | P6: Registered
A7: 7 | B7: NYATI ENTHRAL I | C7: OFFICE | D7: OFFICE - 1507 | E7: 45565 | F7: 21 Oct 2024 | G7: 34552000 | H7: 34552000 | I7: 3100000 | J7: 31452000 | K7: 0 | L7: 0 | M7: 0 | N7: 0 | O7: 31452000 | P7: Registered
A8: 8 | B8: NYATI ENTHRAL I | C8: OFFICE | D8: OFFICE - 1207 | E8: 45014 | F8: 20 Jun 2024 | G8: 32500000 | H8: 32500000 | I8: 3250000 | J8: 29250000 | K8: 0 | L8: 0 | M8: 0 | N8: 0 | O8: 29250000 | P8: Registered
A9: 9 | B9: NYATI ENTHRAL I | C9: OFFICE | D9: OFFICE - 1203 | E9: 45619 | F9: 03 Jun 2025 | G9: 33500000 | H9: 33500000 | I9: 4428000 | J9: 29072000 | K9: 0 | L9: 0 | M9: 0 | N9: 0 | O9: 29072000 | P9: Registered
A10: 10 | B10: NYATI ENTHRAL I | C10: OFFICE | D10: OFFICE - 1307 | E10: 45516 | F10: 23 Aug 2024 | G10: 32500000 | H10: 32500000 | I10: 3575000 | J10: 28925000 | K10: 0 | L10: 0 | M10: 0 | N10: 0 | O10: 28925000 | P10: Registered
A11: 11 | B11: NYATI ENTHRAL I | C11: OFFICE | D11: OFFICE - 1107 | E11: 45230 | F11: 04 Jan 2024 | G11: 32100000 | H11: 32100000 | I11: 3300000 | J11: 28800000 | K11: 0 | L11: 0 | M11: 0 | N11: 0 | O11: 28800000 | P11: Registered
A12: 12 | B12: NYATI ENTHRAL I | C12: OFFICE | D12: OFFICE - 1406 | E12: 45535 | F12: 20 Dec 2024 | G12: 43600000 | H12: 43600000 | I12: 19886000 | J12: 23714000 | K12: 0 | L12: 0 | M12: 0 | N12: 0 | O12: 23714000 | P12: Registered
A13: 13 | B13: NYATI ENTHRAL I | C13: OFFICE | D13: OFFICE - 1605 | E13: 45971 | F13: 17 Nov 2025 | G13: 60396000 | H13: 60396000 | I13: 36863270 | J13: 23532730 | K13: 0 | L13: 0 | M13: 0 | N13: 0 | O13: 23532730 | P13: Registered
... A4049: 10876 | B4049: NYATI ENTHRAL I | C4049: OFFICE | D4049: OFFICE - 1101 | E4049: 45149 | F4049: 01 Jan 1900 | G4049: 85782000 | H4049: 0 | I4049: 36000000 | J4049: -36000000 | K4049: 0 | L4049: 0 | M4049: 0 | N4049: 0 | O4049: 0 | P4049: Unregistered
A4050: 10885 | B4050: NYATI DEFENCE ENCLAVE III | C4050: "G" (MHADA) | D4050: G -1 | E4050: 46164 | F4050: 01 Jan 1900 | G4050: 1627000 | H4050: 0 | K4050: 0 | L4050: 0 | M4050: 0 | N4050: 0 | O4050: 0 | P4050: Unregistered
A4051: 10891 | B4051: NYATI ELENOR | C4051: A TOWER | D4051: A TOWER -1004 | E4051: 46168 | F4051: 01 Jan 1900 | G4051: 34300000 | H4051: 0 | K4051: 0 | L4051: 0 | M4051: 0 | N4051: 0 | O4051: 0 | P4051: Unregistered
A4052: 10892 | B4052: NYATI ELENOR | C4052: A TOWER | D4052: A TOWER -1303 | E4052: 46195 | F4052: 01 Jan 1900 | G4052: 25200000 | H4052: 0 | K4052: 0 | L4052: 0 | M4052: 0 | N4052: 0 | O4052: 0 | P4052: Unregistered
A4053: 10893 | B4053: NYATI ELENOR | C4053: A TOWER | D4053: A TOWER -1401 | E4053: 46173 | F4053: 01 Jan 1900 | G4053: 32700000 | H4053: 0 | K4053: 0 | L4053: 0 | M4053: 0 | N4053: 0 | O4053: 0 | P4053: Unregistered
A4054: 10894 | B4054: NYATI ELENOR | C4054: A TOWER | D4054: A TOWER -1601 | E4054: 46170 | F4054: 01 Jan 1900 | G4054: 26800000 | H4054: 0 | K4054: 0 | L4054: 0 | M4054: 0 | N4054: 0 | O4054: 0 | P4054: Unregistered
A4055: 10895 | B4055: NYATI ELENOR | C4055: A TOWER | D4055: A TOWER -1602 | E4055: 46168 | F4055: 01 Jan 1900 | G4055: 28200000 | H4055: 0 | K4055: 0 | L4055: 0 | M4055: 0 | N4055: 0 | O4055: 0 | P4055: Unregistered
A4056: 10896 | B4056: NYATI ELENOR | C4056: A TOWER | D4056: A TOWER -1901 | E4056: 46168 | F4056: 01 Jan 1900 | G4056: 33500000 | H4056: 0 | K4056: 0 | L4056: 0 | M4056: 0 | N4056: 0 | O4056: 0 | P4056: Unregistered
A4057: 10897 | B4057: NYATI ELENOR | C4057: A TOWER | D4057: A TOWER -2101 | E4057: 46168 | F4057: 01 Jan 1900 | G4057: 31100000 | H4057: 0 | K4057: 0 | L4057: 0 | M4057: 0 | N4057: 0 | O4057: 0 | P4057: Unregistered
A4058: 10898 | B4058: NYATI ELENOR | C4058: A TOWER | D4058: A TOWER -2404 | E4058: 46148 | F4058: 15 May 2026 | G4058: 33500000 | H4058: 15075000 | K4058: 15075000 | L4058: 0 | M4058: 0 | N4058: 0 | O4058: 0 | P4058: Registered
A4059: 10899 | B4059: NYATI ELENOR | C4059: A TOWER | D4059: A TOWER -2601 | E4059: 46147 | F4059: 01 Jan 1900 | G4059: 33705000 | H4059: 0 | K4059: 0 | L4059: 0 | M4059: 0 | N4059: 0 | O4059: 0 | P4059: Unregistered
A4060: 10900 | B4060: NYATI ELENOR | C4060: A TOWER | D4060: A TOWER -3001 | E4060: 46170 | G4060: 26800000 | H4060: 0 | K4060: 0 | L4060: 0 | M4060: 0 | N4060: 0 | O4060: 0 | P4060: Registered
A4061: 10901 | B4061: NYATI ELENOR | C4061: B TOWER | D4061: B TOWER - 1202 | E4061: 46140 | F4061: 01 Jan 1900 | G4061: 41000000 | H4061: 0 | K4061: 0 | L4061: 0 | M4061: 0 | N4061: 0 | O4061: 0 | P4061: Unregistered
A4062: 10902 | B4062: NYATI ELENOR | C4062: B TOWER | D4062: B TOWER - 1303 | E4062: 46147 | F4062: 01 Jan 1900 | G4062: 40687500 | H4062: 0 | K4062: 0 | L4062: 0 | M4062: 0 | N4062: 0 | O4062: 0 | P4062: Unregistered
A4063: 10903 | B4063: NYATI ELENOR | C4063: B TOWER | D4063: B TOWER - 902 | E4063: 46193 | F4063: 24 Jun 2026 | G4063: 49000000 | H4063: 0 | K4063: 0 | L4063: 0 | M4063: 0 | N4063: 0 | O4063: 0 | P4063: Registered
A4064: 10904 | B4064: NYATI ELENOR | C4064: B TOWER | D4064: B TOWER -1703 | E4064: 46148 | F4064: 01 Jan 1900 | G4064: 33500000 | H4064: 0 | K4064: 0 | L4064: 0 | M4064: 0 | N4064: 0 | O4064: 0 | P4064: Unregistered
A4065: 10905 | B4065: NYATI ELENOR | C4065: B TOWER | D4065: B TOWER -2101 | E4065: 46195 | F4065: 01 Jan 1900 | G4065: 25250000 | H4065: 0 | K4065: 0 | L4065: 0 | M4065: 0 | N4065: 0 | O4065: 0 | P4065: Unregistered
A4066: 10906 | B4066: NYATI ELENOR | C4066: B TOWER | D4066: B TOWER -2202 | E4066: 46140 | F4066: 01 Jan 1900 | G4066: 41000000 | H4066: 0 | K4066: 0 | L4066: 0 | M4066: 0 | N4066: 0 | O4066: 0 | P4066: Unregistered
A4067: 10907 | B4067: NYATI ELENOR | C4067: B TOWER | D4067: B TOWER -2302 | E4067: 46140 | F4067: 01 Jan 1900 | G4067: 40400000 | H4067: 0 | K4067: 0 | L4067: 0 | M4067: 0 | N4067: 0 | O4067: 0 | P4067: Unregistered
A4068: 10908 | B4068: NYATI ELENOR | C4068: B TOWER | D4068: B TOWER -2303 | E4068: 46195 | F4068: 01 Jan 1900 | G4068: 32600000 | H4068: 0 | K4068: 0 | L4068: 0 | M4068: 0 | N4068: 0 | O4068: 0 | P4068: Unregistered
A4069: 10909 | B4069: NYATI EMBLEM | C4069: F BUILDING | D4069: F BUILDING - UNIT NO.1401 | E4069: 46199 | F4069: 01 Jan 1900 | G4069: 39000000 | H4069: 0 | K4069: 0 | L4069: 0 | M4069: 0 | N4069: 0 | O4069: 0 | P4069: Unregistered
A4070: 10910 | B4070: NYATI EMBLEM | C4070: F BUILDING | D4070: F BUILDING - UNIT NO.2402 | E4070: 46142 | F4070: 01 Jan 1900 | G4070: 45700000 | H4070: 0 | K4070: 0 | L4070: 0 | M4070: 0 | N4070: 0 | O4070: 0 | P4070: Unregistered
A4071: 10911 | B4071: NYATI EMBLEM | C4071: F BUILDING | D4071: F BUILDING - UNIT NO.702 | E4071: 46173 | F4071: 01 Jan 1900 | G4071: 36500000 | H4071: 0 | K4071: 0 | L4071: 0 | M4071: 0 | N4071: 0 | O4071: 0 | P4071: Unregistered
A4072: 10912 | B4072: NYATI EMERALD I | C4072: BERYL - (PMC - B1) | D4072: BERYL - B1 - 2901 | E4072: 46195 | F4072: 01 Jan 1900 | G4072: 10266071 | H4072: 0 | K4072: 0 | L4072: 0 | M4072: 0 | N4072: 0 | O4072: 0 | P4072: Unregistered
... A4202: 11091 | B4202: NYATI EXUBERANCE IV | C4202: PRIMROSE (PMC NO. C4) | D4202: PRIMROSE - C4 -804 | E4202: 45986 | F4202: 25 Nov 2025 | G4202: 1 | H4202: 0 | K4202: 0 | L4202: 0 | M4202: 0 | N4202: 0 | O4202: 0 | P4202: Registered

Sheet Booking Jun
A1: Booking Register
A2: From Date -01 Jun 2026 | To Date- 30 Jun 2026
A3: Page 1 of 1
A4: Total Records: 84 Records 1 To 84
A5: Company | B5: project | C5: Building | D5: Unit | E5: customer_name | F5: Customer_address | G5: Customer_Mobile | H5: PAN_NO | I5: Booking_Date | J5: Aggr_Date | K5: Area1 | L5: Agg_Value | M5: Claimed_Amt | N5: Claimed_GST | O5: Amount_Received | P5: RelationManager | Q5: SaleManager | R5: Source | S5: Subsource | T5: Referredbycustomer | U5: Sourcing Team/ROM | V5: Swabhiman (Defence) | W5: International Office | X5: Poona Office | Y5: Reference By
A6: Nyati Builders Pvt Ltd | B6: NYATI ELENOR | C6: B TOWER | D6: B TOWER - 902 | E6: VINITA NITIN BAFANA | F6: TRISHALA, 321/A3, SHANKARSHETH ROAD, OPP. MEERA SOCIETY, MAHATMA PHULE PETH, PUNE - 411042 (MAHARASHTRA) | G6: 9730070070 | H6: ANFPB2150G | I6: 46193 | J6: 46197 | K6: 3958 | L6: 49000000 | M6: 16333333 | N6: 816666 | O6: 34471698 | P6: Ashish Bhasin | Q6: Janavhi Chugera | R6: CHANNEL PARTNER | S6: NITIN DHAMANE | X6: YES
A7: Nyati Builders Pvt Ltd | B7: NYATI ELENOR | C7: B TOWER | D7: B TOWER -2303 | E7: VINESH OSWAL | G7: 8055177770 | I7: 46195 | J7: 2 | K7: 3255 | L7: 32600000 | M7: 0 | N7: 0 | O7: 3300000 | P7: Ashish Bhasin | Q7: Janavhi Chugera | R7: CHANNEL PARTNER
A8: Nyati Builders Pvt Ltd | B8: NYATI ELENOR | C8: A TOWER | D8: A TOWER -1303 | E8: MUKESH OSWAL | G8: 8308303088 | I8: 46195 | J8: 2 | K8: 2518 | L8: 25200000 | M8: 0 | N8: 0 | O8: 2500000 | P8: Ashish Bhasin | Q8: Janavhi Chugera | R8: CHANNEL PARTNER
A9: Nyati Builders Pvt Ltd | B9: NYATI ELENOR | C9: B TOWER | D9: B TOWER - 1604 | E9: KANTA SURESHKUMAR JAIN | F9: 383, BUILDING C2, FLAT NO. 10, PADAMJEE PARADISE SOCIETY, BHAWANI PETH, PUNE - 411042 (MAHARASHTRA) | G9: 9970758075 | H9: ANHPJ1897J | I9: 46196 | J9: 2 | K9: 2518 | L9: 25381000 | M9: 0 | N9: 0 | O9: 2500000 | X9: YES
A10: Nyati Builders Pvt Ltd | B10: NYATI ELENOR | C10: B TOWER | D10: B TOWER -2402 | E10: Pallavi Rohan Lunawat | F10: E- 101, Lake Town Society, Bibewadi Pune 411037 | G10: 8888033299 | I10: 46203 | J10: 2 | K10: 3860 | L10: 38600000 | M10: 0 | N10: 0 | O10: 1100000 | P10: Ashish Bhasin
A11: Nyati Builders Pvt Ltd | B11: NYATI ELENOR | C11: A TOWER | D11: A TOWER -702 | E11: ASHOK KURANI | F11: 57-Madhuram Gangadham Phase - 1 Bibewadi Lullanagar Road Market Yard Pune 411037 | G11: 9850507058 | I11: 46203 | J11: 2 | K11: 2568 | L11: 30777500 | M11: 0 | N11: 0 | O11: 3500000 | P11: Ashish Bhasin
A12: Nyati Construction Pvt.Ltd. | B12: NYATI EMBLEM | C12: F BUILDING | D12: F BUILDING - UNIT NO.1401 | E12: VINAY ZUMBERLAL BALDOTA | F12: FLAT NO.203 C WING THE LEGEND LAKETOWN ROAD CHAITRABAN SR.NO.662/1+2/665 BIBWEWADI PUNE. | G12: 9822172072 | I12: 46199 | J12: 2 | K12: 3642 | L12: 39000000 | M12: 0 | N12: 0 | O12: 1100000 | P12: Ashish Bhasin
A13: Nyati Builders Pvt Ltd | B13: NYATI EMERALD I | C13: BERYL - (PMC - B1) | D13: BERYL - B1 - 2901 | E13: VARUN SINGLA | F13: B-1102, SHAPORJI JOYVILLE SOCIETY, MAAN, MAN, PO : INFOTECH PARK (HINJAWADI), DIST PUNE, MAHARASHTRA - 411057 | G13: 9888907479 | H13: FOKPS8543M | I13: 46195 | J13: 2 | K13: 1173 | L13: 10266071 | M13: 0 | N13: 0 | O13: 200000 | P13: Ashish Bhasin | Q13: Sanjay Zaveri | R13: CHANNEL PARTNER | S13: SGRO | X13: YES
A14: Nyati Builders Pvt Ltd | B14: NYATI EMERALD I | C14: EMERALD SHOP | D14: SHOP - A3 -28 | E14: RAGHUBIR SINGH SALUJA | F14: FLAT NO.102, B- BLOCK, GVK SKY CITY, BESIDE RAJBHAVAN SOMAJIGUDA HYDERABAD, TELANGANA HYDERABAD- 500082 | G14: 9849026348 | I14: 46195 | J14: 2 | K14: 4645 | L14: 45100000 | M14: 0 | N14: 0 | O14: 12500000 | P14: Ashish Bhasin | R14: CHANNEL PARTNER | S14: THEME PROPERTIES | X14: YES
A15: Nyati Builders Pvt Ltd | B15: NYATI EMERALD III | C15: AGATE - (PMC NO - D1) | D15: AGATE - D1 -1102 | E15: HARSHAD KAMALAKAR GORE | F15: A 401, MEDINOVA CGHS, PLOT GH 50, NEAR HUDA MARKET, SECTOR 56, GURGAON - 122011, HARYANA. | G15: 9999394629 | H15: ACKPG6102H | I15: 46181 | J15: 46202 | K15: 1173 | L15: 9281949 | M15: 0 | N15: 0 | O15: 928194.9 | P15: Sanjeev Deshpande | Q15: Manoj Udawant | R15: DIRECT SALES
A16: Nyati Builders Pvt Ltd | B16: NYATI EMERALD III | C16: AGATE - (PMC NO - D1) | D16: AGATE - D1 -1001 | E16: OM PRASHANT ZILPILWAR | F16: VYANKATESH APARTMENT, SHASTRI NAGAR, PANDHARKAWADA, KELAPUR, YAVATMAL, MAHARASHTRA - 445302. | G16: 9325517186 | H16: ADIPZ3532D | I16: 46195 | J16: 2 | K16: 1173 | L16: 9595536 | M16: 0 | N16: 0 | O16: 200000 | P16: Ashish Bhasin | Q16: Stanley | R16: DIRECT SALES
A17: Nyati Builders Pvt Ltd | B17: NYATI EMERALD III | C17: TOPAZ - (PMC NO - C3) | D17: TOPAZ - C3 -2802 | E17: CHANDAN LATHI | F17: 132 GANDHI NAGAR NATRAJ THEATER ROAD JALGAON 425001 | G17: 9270504914 | H17: AIZPL0727A | I17: 46203 | J17: 2 | K17: 1173 | L17: 9640179 | M17: 0 | N17: 0 | O17: 224001 | P17: Ashish Bhasin | Q17: Stanley | R17: CHANNEL PARTNER | X17: YES
